{"accounts":[{"account":{"active":false,"allocationHistory":[],"balance":"0","identity":{"address":"N\u0000sourcecred\u0000core\u0000IDENTITY\u0000KQKvQcwRPp92ejv2jWjn1A\u0000","aliases":[{"address":"N\u0000sourcecred\u0000discord\u0000MEMBER\u0000user\u0000104190369457016832\u0000","description":"discord/Justin#8531"}],"id":"KQKvQcwRPp92ejv2jWjn1A","name":"Justin","subtype":"USER"},"mergedIdentityIds":["KQKvQcwRPp92ejv2jWjn1A"],"paid":"0","payoutAddresses":{}},"cred":[2.0389715564573686e-34,2.0389715564573686e-34,2.0389715564573686e-34,2.0389715564573686e-34],"totalCred":8.155886225829474e-34},{"account":{"active":false,"allocationHistory":[],"balance":"0","identity":{"address":"N\u0000sourcecred\u0000core\u0000IDENTITY\u0000Ahx3kXtnjNerBt70Z4skTg\u0000","aliases":[{"address":"N\u0000sourcecred\u0000discord\u0000MEMBER\u0000user\u0000137289101983350784\u0000","description":"discord/cryptocrpt#5239"}],"id":"Ahx3kXtnjNerBt70Z4skTg","name":"cryptocrpt","subtype":"USER"},"mergedIdentityIds":["Ahx3kXtnjNerBt70Z4skTg"],"paid":"0","payoutAddresses":{}},"cred":[2.0389715564573686e-34,2.0389715564573686e-34,2.0389715564573686e-34,2.0389715564573686e-34],"totalCred":8.155886225829474e-34},{"account":{"active":false,"allocationHistory":[],"balance":"0","identity":{"address":"N\u0000sourcecred\u0000core\u0000IDENTITY\u0000PKjzMcaKwGVLZDkysNdTKw\u0000","aliases":[{"address":"N\u0000sourcecred\u0000discord\u0000MEMBER\u0000user\u0000142538186109747200\u0000","description":"discord/Dheeraj#6128"}],"id":"PKjzMcaKwGVLZDkysNdTKw","name":"Dheeraj","subtype":"USER"},"mergedIdentityIds":["PKjzMcaKwGVLZDkysNdTKw"],"paid":"0","payoutAddresses":{}},"cred":[0.526889127178267,0.3785867952210258,1.336884391050462,0.19856151887060397],"totalCred":2.4409218323203588},{"account":{"active":false,"allocationHistory":[],"balance":"0","identity":{"address":"N\u0000sourcecred\u0000core\u0000IDENTITY\u0000QJEzTRFKlBn5Qiyj5tbBzQ\u0000","aliases":[{"address":"N\u0000sourcecred\u0000discord\u0000MEMBER\u0000user\u0000182163295262867458\u0000","description":"discord/Target_Sir#4116"}],"id":"QJEzTRFKlBn5Qiyj5tbBzQ","name":"Target-Sir","subtype":"USER"},"mergedIdentityIds":["QJEzTRFKlBn5Qiyj5tbBzQ"],"paid":"0","payoutAddresses":{}},"cred":[0.00635760023587907,0.05721840396108231,0.005786131009396149,0.0006429029828534776],"totalCred":0.07000503818921101},{"account":{"active":false,"allocationHistory":[],"balance":"0","identity":{"address":"N\u0000sourcecred\u0000core\u0000IDENTITY\u00000Bc8CP5Mkcwwj8ZwkZf88w\u0000","aliases":[{"address":"N\u0000sourcecred\u0000discord\u0000MEMBER\u0000user\u0000209315927005724672\u0000","description":"discord/magicturtle#3057"}],"id":"0Bc8CP5Mkcwwj8ZwkZf88w","name":"magicturtle","subtype":"USER"},"mergedIdentityIds":["0Bc8CP5Mkcwwj8ZwkZf88w"],"paid":"0","payoutAddresses":{}},"cred":[2.0389715564573686e-34,2.0389715564573686e-34,2.0389715564573686e-34,2.0389715564573686e-34],"totalCred":8.155886225829474e-34},{"account":{"active":false,"allocationHistory":[],"balance":"0","identity":{"address":"N\u0000sourcecred\u0000core\u0000IDENTITY\u0000amlimfbtPNE3aQznJwmNkg\u0000","aliases":[{"address":"N\u0000sourcecred\u0000discord\u0000MEMBER\u0000user\u0000228250011115323392\u0000","description":"discord/atakan-IntroToDefi#7962"}],"id":"amlimfbtPNE3aQznJwmNkg","name":"atakan-IntroToDefi","subtype":"USER"},"mergedIdentityIds":["amlimfbtPNE3aQznJwmNkg"],"paid":"0","payoutAddresses":{}},"cred":[2.0389715564573686e-34,2.0389715564573686e-34,2.0389715564573686e-34,2.0389715564573686e-34],"totalCred":8.155886225829474e-34},{"account":{"active":false,"allocationHistory":[],"balance":"0","identity":{"address":"N\u0000sourcecred\u0000core\u0000IDENTITY\u0000aZKAQryczJk1vvBgomCrOw\u0000","aliases":[{"address":"N\u0000sourcecred\u0000discord\u0000MEMBER\u0000user\u0000242510303248646146\u0000","description":"discord/bigba_daboom#2008"}],"id":"aZKAQryczJk1vvBgomCrOw","name":"bigba-daboom","subtype":"USER"},"mergedIdentityIds":["aZKAQryczJk1vvBgomCrOw"],"paid":"0","payoutAddresses":{}},"cred":[2.0389715564573686e-34,2.0389715564573686e-34,2.0389715564573686e-34,2.0389715564573686e-34],"totalCred":8.155886225829474e-34},{"account":{"active":false,"allocationHistory":[],"balance":"0","identity":{"address":"N\u0000sourcecred\u0000core\u0000IDENTITY\u0000TroK9QDxlJzrvrF2oJ7NFw\u0000","aliases":[{"address":"N\u0000sourcecred\u0000discord\u0000MEMBER\u0000user\u0000281055990315614208\u0000","description":"discord/cusx#2103"}],"id":"TroK9QDxlJzrvrF2oJ7NFw","name":"cusx","subtype":"USER"},"mergedIdentityIds":["TroK9QDxlJzrvrF2oJ7NFw"],"paid":"0","payoutAddresses":{}},"cred":[2.0389715564573686e-34,2.0389715564573686e-34,2.0389715564573686e-34,2.0389715564573686e-34],"totalCred":8.155886225829474e-34},{"account":{"active":false,"allocationHistory":[],"balance":"0","identity":{"address":"N\u0000sourcecred\u0000core\u0000IDENTITY\u00004arSrXvpvcAGHxvmQHAesQ\u0000","aliases":[{"address":"N\u0000sourcecred\u0000discord\u0000MEMBER\u0000user\u0000282871599563014144\u0000","description":"discord/Tony Tony Chopper#4606"}],"id":"4arSrXvpvcAGHxvmQHAesQ","name":"Tony-Tony-Chopper","subtype":"USER"},"mergedIdentityIds":["4arSrXvpvcAGHxvmQHAesQ"],"paid":"0","payoutAddresses":{}},"cred":[2.0389715564573686e-34,2.0389715564573686e-34,2.0389715564573686e-34,2.0389715564573686e-34],"totalCred":8.155886225829474e-34},{"account":{"active":false,"allocationHistory":[],"balance":"0","identity":{"address":"N\u0000sourcecred\u0000core\u0000IDENTITY\u0000aksWzN21VZc8dxAozcLfbw\u0000","aliases":[{"address":"N\u0000sourcecred\u0000discord\u0000MEMBER\u0000user\u0000310803263530336257\u0000","description":"discord/QE4EVER | hotnewcrypto#4324"}],"id":"aksWzN21VZc8dxAozcLfbw","name":"QE4EVER---hotnewcrypto","subtype":"USER"},"mergedIdentityIds":["aksWzN21VZc8dxAozcLfbw"],"paid":"0","payoutAddresses":{}},"cred":[2.5715091780396175,0.3042078832884203,0.03076262865655486,0.0034180649405882477],"totalCred":2.909897754925181},{"account":{"active":false,"allocationHistory":[],"balance":"0","identity":{"address":"N\u0000sourcecred\u0000core\u0000IDENTITY\u0000G5peCnoW5LfpYURnYEbB9w\u0000","aliases":[{"address":"N\u0000sourcecred\u0000discord\u0000MEMBER\u0000user\u0000318511843020767252\u0000","description":"discord/poopster#3593"}],"id":"G5peCnoW5LfpYURnYEbB9w","name":"poopster","subtype":"USER"},"mergedIdentityIds":["G5peCnoW5LfpYURnYEbB9w"],"paid":"0","payoutAddresses":{}},"cred":[0.19064277087608764,0.8248255277369716,2.353443069448404,3.567303070679353],"totalCred":6.936214438740816},{"account":{"active":false,"allocationHistory":[],"balance":"0","identity":{"address":"N\u0000sourcecred\u0000core\u0000IDENTITY\u0000KO7iyAonFQeZ52rmqgmRsA\u0000","aliases":[{"address":"N\u0000sourcecred\u0000discord\u0000MEMBER\u0000user\u0000325303654376538113\u0000","description":"discord/pupuu#4248"}],"id":"KO7iyAonFQeZ52rmqgmRsA","name":"pupuu","subtype":"USER"},"mergedIdentityIds":["KO7iyAonFQeZ52rmqgmRsA"],"paid":"0","payoutAddresses":{}},"cred":[2.0389715564573686e-34,2.0389715564573686e-34,2.0389715564573686e-34,2.0389715564573686e-34],"totalCred":8.155886225829474e-34},{"account":{"active":false,"allocationHistory":[],"balance":"0","identity":{"address":"N\u0000sourcecred\u0000core\u0000IDENTITY\u0000aQcDxNEc4bl2YPcoxNblUA\u0000","aliases":[{"address":"N\u0000sourcecred\u0000discord\u0000MEMBER\u0000user\u0000334693448131149834\u0000","description":"discord/redmption#7706"}],"id":"aQcDxNEc4bl2YPcoxNblUA","name":"redmption","subtype":"USER"},"mergedIdentityIds":["aQcDxNEc4bl2YPcoxNblUA"],"paid":"0","payoutAddresses":{}},"cred":[2.0389715564573686e-34,2.0389715564573686e-34,2.0389715564573686e-34,2.0389715564573686e-34],"totalCred":8.155886225829474e-34},{"account":{"active":false,"allocationHistory":[],"balance":"0","identity":{"address":"N\u0000sourcecred\u0000core\u0000IDENTITY\u0000yJjB1GqDX6tY3LpVJB5Q3w\u0000","aliases":[{"address":"N\u0000sourcecred\u0000discord\u0000MEMBER\u0000user\u0000335535847002865674\u0000","description":"discord/Goon Machine#3334"}],"id":"yJjB1GqDX6tY3LpVJB5Q3w","name":"Goon-Machine","subtype":"USER"},"mergedIdentityIds":["yJjB1GqDX6tY3LpVJB5Q3w"],"paid":"0","payoutAddresses":{}},"cred":[2.0389715564573686e-34,2.0389715564573686e-34,2.0389715564573686e-34,2.0389715564573686e-34],"totalCred":8.155886225829474e-34},{"account":{"active":false,"allocationHistory":[],"balance":"0","identity":{"address":"N\u0000sourcecred\u0000core\u0000IDENTITY\u0000W5qaeFWPo29TdBynPGNhMg\u0000","aliases":[{"address":"N\u0000sourcecred\u0000discord\u0000MEMBER\u0000user\u0000337602572514754560\u0000","description":"discord/Magnus#3558"}],"id":"W5qaeFWPo29TdBynPGNhMg","name":"Magnus","subtype":"USER"},"mergedIdentityIds":["W5qaeFWPo29TdBynPGNhMg"],"paid":"0","payoutAddresses":{}},"cred":[2.0389715564573686e-34,2.0389715564573686e-34,2.0389715564573686e-34,2.0389715564573686e-34],"totalCred":8.155886225829474e-34},{"account":{"active":false,"allocationHistory":[],"balance":"0","identity":{"address":"N\u0000sourcecred\u0000core\u0000IDENTITY\u00001pP2Vx81KfyukenmXsEb3g\u0000","aliases":[{"address":"N\u0000sourcecred\u0000discord\u0000MEMBER\u0000user\u0000344236964385521666\u0000","description":"discord/sls#0012"}],"id":"1pP2Vx81KfyukenmXsEb3g","name":"sls","subtype":"USER"},"mergedIdentityIds":["1pP2Vx81KfyukenmXsEb3g"],"paid":"0","payoutAddresses":{}},"cred":[0.09326168804642854,0.009421438004442442,0.0009527293831004966,0.00010585895349270328],"totalCred":0.10374171438746417},{"account":{"active":false,"allocationHistory":[],"balance":"0","identity":{"address":"N\u0000sourcecred\u0000core\u0000IDENTITY\u00001lMmLAZcGfqCKoJm1NnNKA\u0000","aliases":[{"address":"N\u0000sourcecred\u0000discord\u0000MEMBER\u0000user\u0000347836520100659202\u0000","description":"discord/Viktorskf (Viktor)#3931"}],"id":"1lMmLAZcGfqCKoJm1NnNKA","name":"Viktorskf--Viktor-","subtype":"USER"},"mergedIdentityIds":["1lMmLAZcGfqCKoJm1NnNKA"],"paid":"0","payoutAddresses":{}},"cred":[2.0389715564573686e-34,2.0389715564573686e-34,2.0389715564573686e-34,2.0389715564573686e-34],"totalCred":8.155886225829474e-34},{"account":{"active":false,"allocationHistory":[],"balance":"0","identity":{"address":"N\u0000sourcecred\u0000core\u0000IDENTITY\u0000IdUXOWGc6QT1AwxcvRjvDQ\u0000","aliases":[{"address":"N\u0000sourcecred\u0000discord\u0000MEMBER\u0000user\u0000362804848996909077\u0000","description":"discord/Satish143 (3, 3)#8241"}],"id":"IdUXOWGc6QT1AwxcvRjvDQ","name":"Satish143--3--3-","subtype":"USER"},"mergedIdentityIds":["IdUXOWGc6QT1AwxcvRjvDQ"],"paid":"0","payoutAddresses":{}},"cred":[2.0389715564573686e-34,2.0389715564573686e-34,2.0389715564573686e-34,2.0389715564573686e-34],"totalCred":8.155886225829474e-34},{"account":{"active":false,"allocationHistory":[],"balance":"0","identity":{"address":"N\u0000sourcecred\u0000core\u0000IDENTITY\u0000pC5o0bj9lQL9QL1LZV9rmQ\u0000","aliases":[{"address":"N\u0000sourcecred\u0000discord\u0000MEMBER\u0000user\u0000369959429476712449\u0000","description":"discord/Nikhil#3582"}],"id":"pC5o0bj9lQL9QL1LZV9rmQ","name":"Nikhil","subtype":"USER"},"mergedIdentityIds":["pC5o0bj9lQL9QL1LZV9rmQ"],"paid":"0","payoutAddresses":{}},"cred":[2.0389715564573686e-34,2.0389715564573686e-34,2.0389715564573686e-34,2.0389715564573686e-34],"totalCred":8.155886225829474e-34},{"account":{"active":false,"allocationHistory":[],"balance":"0","identity":{"address":"N\u0000sourcecred\u0000core\u0000IDENTITY\u0000qxUafX986pGrQXVhBFvWxA\u0000","aliases":[{"address":"N\u0000sourcecred\u0000discord\u0000MEMBER\u0000user\u0000370678198632972289\u0000","description":"discord/HD#0330"}],"id":"qxUafX986pGrQXVhBFvWxA","name":"HD","subtype":"USER"},"mergedIdentityIds":["qxUafX986pGrQXVhBFvWxA"],"paid":"0","payoutAddresses":{}},"cred":[0.00010354188823689054,0.000931876375509789,0.00009423475749832914,0.000010470522285552194],"totalCred":0.0011401235435305607},{"account":{"active":false,"allocationHistory":[],"balance":"0","identity":{"address":"N\u0000sourcecred\u0000core\u0000IDENTITY\u0000HkKm4c1cdHZfNVW9AhqI8Q\u0000","aliases":[{"address":"N\u0000sourcecred\u0000discord\u0000MEMBER\u0000user\u0000385601403944566785\u0000","description":"discord/sniper25#0414"}],"id":"HkKm4c1cdHZfNVW9AhqI8Q","name":"sniper25","subtype":"USER"},"mergedIdentityIds":["HkKm4c1cdHZfNVW9AhqI8Q"],"paid":"0","payoutAddresses":{}},"cred":[2.0389715564573686e-34,2.0389715564573686e-34,2.0389715564573686e-34,2.0389715564573686e-34],"totalCred":8.155886225829474e-34},{"account":{"active":false,"allocationHistory":[],"balance":"0","identity":{"address":"N\u0000sourcecred\u0000core\u0000IDENTITY\u0000wdj18FLsAOvnHqlR0eMqtQ\u0000","aliases":[{"address":"N\u0000sourcecred\u0000discord\u0000MEMBER\u0000user\u0000391276669702242319\u0000","description":"discord/Strikeanerve#3801"}],"id":"wdj18FLsAOvnHqlR0eMqtQ","name":"Strikeanerve","subtype":"USER"},"mergedIdentityIds":["wdj18FLsAOvnHqlR0eMqtQ"],"paid":"0","payoutAddresses":{}},"cred":[0.057115329695450925,0.005769879620696459,0.0005834706256526073,0.00006483015434410718],"totalCred":0.0635335100961441},{"account":{"active":false,"allocationHistory":[],"balance":"0","identity":{"address":"N\u0000sourcecred\u0000core\u0000IDENTITY\u0000IkTx0M5WWAVcNQf8djkINw\u0000","aliases":[{"address":"N\u0000sourcecred\u0000discord\u0000MEMBER\u0000user\u0000392154072691638272\u0000","description":"discord/theshark#4172"}],"id":"IkTx0M5WWAVcNQf8djkINw","name":"theshark","subtype":"USER"},"mergedIdentityIds":["IkTx0M5WWAVcNQf8djkINw"],"paid":"0","payoutAddresses":{}},"cred":[2.0389715564573686e-34,2.0389715564573686e-34,2.0389715564573686e-34,2.0389715564573686e-34],"totalCred":8.155886225829474e-34},{"account":{"active":false,"allocationHistory":[],"balance":"0","identity":{"address":"N\u0000sourcecred\u0000core\u0000IDENTITY\u00007tA1uboinqfbNUmbeVPpnw\u0000","aliases":[{"address":"N\u0000sourcecred\u0000discord\u0000MEMBER\u0000user\u0000392634073455263744\u0000","description":"discord/ayyylmao#5047"}],"id":"7tA1uboinqfbNUmbeVPpnw","name":"ayyylmao","subtype":"USER"},"mergedIdentityIds":["7tA1uboinqfbNUmbeVPpnw"],"paid":"0","payoutAddresses":{}},"cred":[2.0389715564573686e-34,2.0389715564573686e-34,2.0389715564573686e-34,2.0389715564573686e-34],"totalCred":8.155886225829474e-34},{"account":{"active":false,"allocationHistory":[],"balance":"0","identity":{"address":"N\u0000sourcecred\u0000core\u0000IDENTITY\u0000OUJLpT4VQKcQDjqv8rH8PA\u0000","aliases":[{"address":"N\u0000sourcecred\u0000discord\u0000MEMBER\u0000user\u0000393318050465579009\u0000","description":"discord/500bitcoins#0682"}],"id":"OUJLpT4VQKcQDjqv8rH8PA","name":"500bitcoins","subtype":"USER"},"mergedIdentityIds":["OUJLpT4VQKcQDjqv8rH8PA"],"paid":"0","payoutAddresses":{}},"cred":[2.0389715564573686e-34,2.0389715564573686e-34,2.0389715564573686e-34,2.0389715564573686e-34],"totalCred":8.155886225829474e-34},{"account":{"active":false,"allocationHistory":[],"balance":"0","identity":{"address":"N\u0000sourcecred\u0000core\u0000IDENTITY\u0000JMuXVUAVO9AP458EvDhnMw\u0000","aliases":[{"address":"N\u0000sourcecred\u0000discord\u0000MEMBER\u0000user\u0000394339917888487445\u0000","description":"discord/cryptodetweiler#0830"}],"id":"JMuXVUAVO9AP458EvDhnMw","name":"cryptodetweiler","subtype":"USER"},"mergedIdentityIds":["JMuXVUAVO9AP458EvDhnMw"],"paid":"0","payoutAddresses":{}},"cred":[2.0389715564573686e-34,2.0389715564573686e-34,2.0389715564573686e-34,2.0389715564573686e-34],"totalCred":8.155886225829474e-34},{"account":{"active":false,"allocationHistory":[],"balance":"0","identity":{"address":"N\u0000sourcecred\u0000core\u0000IDENTITY\u0000WZ6fVOLq3mt5mdCaI5YBWw\u0000","aliases":[{"address":"N\u0000sourcecred\u0000discord\u0000MEMBER\u0000user\u0000396007432675131405\u0000","description":"discord/arunphilips | Polygon#9899"}],"id":"WZ6fVOLq3mt5mdCaI5YBWw","name":"arunphilips---Polygon","subtype":"USER"},"mergedIdentityIds":["WZ6fVOLq3mt5mdCaI5YBWw"],"paid":"0","payoutAddresses":{}},"cred":[2.0389715564573686e-34,2.0389715564573686e-34,2.0389715564573686e-34,2.0389715564573686e-34],"totalCred":8.155886225829474e-34},{"account":{"active":false,"allocationHistory":[],"balance":"0","identity":{"address":"N\u0000sourcecred\u0000core\u0000IDENTITY\u0000akvY1hAtBrfkAumvjuWrtQ\u0000","aliases":[{"address":"N\u0000sourcecred\u0000discord\u0000MEMBER\u0000user\u0000398213240703811604\u0000","description":"discord/Eric Bal#8862"}],"id":"akvY1hAtBrfkAumvjuWrtQ","name":"Eric-Bal","subtype":"USER"},"mergedIdentityIds":["akvY1hAtBrfkAumvjuWrtQ"],"paid":"0","payoutAddresses":{}},"cred":[0.001726246935699385,0.015536236929150366,0.0015710785048833416,0.00017456446915544704],"totalCred":0.019008126838888535},{"account":{"active":false,"allocationHistory":[],"balance":"0","identity":{"address":"N\u0000sourcecred\u0000core\u0000IDENTITY\u0000p9YB3DgIpDBEOrjJv9Vjyw\u0000","aliases":[{"address":"N\u0000sourcecred\u0000discord\u0000MEMBER\u0000user\u0000398644583308853249\u0000","description":"discord/dogoshii#3081"}],"id":"p9YB3DgIpDBEOrjJv9Vjyw","name":"dogoshii","subtype":"USER"},"mergedIdentityIds":["p9YB3DgIpDBEOrjJv9Vjyw"],"paid":"0","payoutAddresses":{}},"cred":[2.0389715564573686e-34,2.0389715564573686e-34,2.0389715564573686e-34,2.0389715564573686e-34],"totalCred":8.155886225829474e-34},{"account":{"active":false,"allocationHistory":[],"balance":"0","identity":{"address":"N\u0000sourcecred\u0000core\u0000IDENTITY\u000068gZLwKIbb69idbpgOhbeA\u0000","aliases":[{"address":"N\u0000sourcecred\u0000discord\u0000MEMBER\u0000user\u0000401590407160659978\u0000","description":"discord/atron#1528"}],"id":"68gZLwKIbb69idbpgOhbeA","name":"atron","subtype":"USER"},"mergedIdentityIds":["68gZLwKIbb69idbpgOhbeA"],"paid":"0","payoutAddresses":{}},"cred":[2.0389715564573686e-34,2.0389715564573686e-34,2.0389715564573686e-34,2.0389715564573686e-34],"totalCred":8.155886225829474e-34},{"account":{"active":false,"allocationHistory":[],"balance":"0","identity":{"address":"N\u0000sourcecred\u0000core\u0000IDENTITY\u0000Vx6UADwaQTmREnYukYL1VA\u0000","aliases":[{"address":"N\u0000sourcecred\u0000discord\u0000MEMBER\u0000user\u0000408416190700978176\u0000","description":"discord/NameMe#5233"}],"id":"Vx6UADwaQTmREnYukYL1VA","name":"NameMe","subtype":"USER"},"mergedIdentityIds":["Vx6UADwaQTmREnYukYL1VA"],"paid":"0","payoutAddresses":{}},"cred":[2.0389715564573686e-34,2.0389715564573686e-34,2.0389715564573686e-34,2.0389715564573686e-34],"totalCred":8.155886225829474e-34},{"account":{"active":false,"allocationHistory":[],"balance":"0","identity":{"address":"N\u0000sourcecred\u0000core\u0000IDENTITY\u0000CYmYm20k7V3rhR5wTg5U7w\u0000","aliases":[{"address":"N\u0000sourcecred\u0000discord\u0000MEMBER\u0000user\u0000415086679649550347\u0000","description":"discord/Classics23#5299"}],"id":"CYmYm20k7V3rhR5wTg5U7w","name":"Classics23","subtype":"USER"},"mergedIdentityIds":["CYmYm20k7V3rhR5wTg5U7w"],"paid":"0","payoutAddresses":{}},"cred":[2.0389715564573686e-34,2.0389715564573686e-34,2.0389715564573686e-34,2.0389715564573686e-34],"totalCred":8.155886225829474e-34},{"account":{"active":false,"allocationHistory":[],"balance":"0","identity":{"address":"N\u0000sourcecred\u0000core\u0000IDENTITY\u0000CRrGh60rbdsRqJGrfYfATA\u0000","aliases":[{"address":"N\u0000sourcecred\u0000discord\u0000MEMBER\u0000user\u0000417846775395647499\u0000","description":"discord/Ceazor.eth (Snack Sandwich YT)#8074"}],"id":"CRrGh60rbdsRqJGrfYfATA","name":"Ceazor-eth--Snack-Sandwich-YT-","subtype":"USER"},"mergedIdentityIds":["CRrGh60rbdsRqJGrfYfATA"],"paid":"0","payoutAddresses":{}},"cred":[9.043983669516816,1.309193871657254,0.5546431270913604,0.5240825834961621],"totalCred":11.431903251761591},{"account":{"active":false,"allocationHistory":[],"balance":"0","identity":{"address":"N\u0000sourcecred\u0000core\u0000IDENTITY\u00008Vf5fKaPS5glZunQWoeOLg\u0000","aliases":[{"address":"N\u0000sourcecred\u0000discord\u0000MEMBER\u0000user\u0000437030516282097685\u0000","description":"discord/E.S#6018"}],"id":"8Vf5fKaPS5glZunQWoeOLg","name":"E-S","subtype":"USER"},"mergedIdentityIds":["8Vf5fKaPS5glZunQWoeOLg"],"paid":"0","payoutAddresses":{}},"cred":[2.0389715564573686e-34,2.0389715564573686e-34,2.0389715564573686e-34,2.0389715564573686e-34],"totalCred":8.155886225829474e-34},{"account":{"active":false,"allocationHistory":[],"balance":"0","identity":{"address":"N\u0000sourcecred\u0000core\u0000IDENTITY\u0000wfpFqRYuAhrfMilbnxjegA\u0000","aliases":[{"address":"N\u0000sourcecred\u0000discord\u0000MEMBER\u0000user\u0000445851056308748301\u0000","description":"discord/Pedrowww#8870"}],"id":"wfpFqRYuAhrfMilbnxjegA","name":"Pedrowww","subtype":"USER"},"mergedIdentityIds":["wfpFqRYuAhrfMilbnxjegA"],"paid":"0","payoutAddresses":{}},"cred":[2.0389715564573686e-34,2.0389715564573686e-34,2.0389715564573686e-34,2.0389715564573686e-34],"totalCred":8.155886225829474e-34},{"account":{"active":false,"allocationHistory":[],"balance":"0","identity":{"address":"N\u0000sourcecred\u0000core\u0000IDENTITY\u0000V4l9lqPfVzbJbrnH0KzXaw\u0000","aliases":[{"address":"N\u0000sourcecred\u0000discord\u0000MEMBER\u0000user\u0000448599377590878208\u0000","description":"discord/0xJudah#2820"}],"id":"V4l9lqPfVzbJbrnH0KzXaw","name":"0xJudah","subtype":"USER"},"mergedIdentityIds":["V4l9lqPfVzbJbrnH0KzXaw"],"paid":"0","payoutAddresses":{}},"cred":[2.0389715564573686e-34,2.0389715564573686e-34,2.0389715564573686e-34,2.0389715564573686e-34],"totalCred":8.155886225829474e-34},{"account":{"active":false,"allocationHistory":[],"balance":"0","identity":{"address":"N\u0000sourcecred\u0000core\u0000IDENTITY\u0000uzZI9Xfzlqa3j2AdNWiZ5w\u0000","aliases":[{"address":"N\u0000sourcecred\u0000discord\u0000MEMBER\u0000user\u0000455731206919684097\u0000","description":"discord/LeoY#6329"}],"id":"uzZI9Xfzlqa3j2AdNWiZ5w","name":"LeoY","subtype":"USER"},"mergedIdentityIds":["uzZI9Xfzlqa3j2AdNWiZ5w"],"paid":"0","payoutAddresses":{}},"cred":[0.00635760023587907,0.05721840396108231,0.005786131009396149,0.0006429029828534776],"totalCred":0.07000503818921101},{"account":{"active":false,"allocationHistory":[],"balance":"0","identity":{"address":"N\u0000sourcecred\u0000core\u0000IDENTITY\u0000OosLGEtr44FN2bjLat6YXw\u0000","aliases":[{"address":"N\u0000sourcecred\u0000discord\u0000MEMBER\u0000user\u0000457977265997742090\u0000","description":"discord/CryptoInfluence#1805"}],"id":"OosLGEtr44FN2bjLat6YXw","name":"CryptoInfluence","subtype":"USER"},"mergedIdentityIds":["OosLGEtr44FN2bjLat6YXw"],"paid":"0","payoutAddresses":{}},"cred":[0.006043528387121352,0.054391758986942595,0.005500290297884516,0.0006111429487649818],"totalCred":0.06654672062071344},{"account":{"active":false,"allocationHistory":[],"balance":"0","identity":{"address":"N\u0000sourcecred\u0000core\u0000IDENTITY\u0000uw55dh2F5CluK48NhXMr8A\u0000","aliases":[{"address":"N\u0000sourcecred\u0000discord\u0000MEMBER\u0000user\u0000465372733308534785\u0000","description":"discord/david sunil#2490"}],"id":"uw55dh2F5CluK48NhXMr8A","name":"david-sunil","subtype":"USER"},"mergedIdentityIds":["uw55dh2F5CluK48NhXMr8A"],"paid":"0","payoutAddresses":{}},"cred":[2.0389715564573686e-34,2.0389715564573686e-34,2.0389715564573686e-34,2.0389715564573686e-34],"totalCred":8.155886225829474e-34},{"account":{"active":false,"allocationHistory":[],"balance":"0","identity":{"address":"N\u0000sourcecred\u0000core\u0000IDENTITY\u0000uOEOG20A58BbB6M8AHpZJQ\u0000","aliases":[{"address":"N\u0000sourcecred\u0000discord\u0000MEMBER\u0000user\u0000470961639399620608\u0000","description":"discord/Dan | Benchmark#8122"}],"id":"uOEOG20A58BbB6M8AHpZJQ","name":"Dan---Benchmark","subtype":"USER"},"mergedIdentityIds":["uOEOG20A58BbB6M8AHpZJQ"],"paid":"0","payoutAddresses":{}},"cred":[2.0389715564573686e-34,2.0389715564573686e-34,2.0389715564573686e-34,2.0389715564573686e-34],"totalCred":8.155886225829474e-34},{"account":{"active":false,"allocationHistory":[],"balance":"0","identity":{"address":"N\u0000sourcecred\u0000core\u0000IDENTITY\u0000Bs4naz7JMK8Kb5I9tVvJhA\u0000","aliases":[{"address":"N\u0000sourcecred\u0000discord\u0000MEMBER\u0000user\u0000476544222833672204\u0000","description":"discord/Degen#8380"}],"id":"Bs4naz7JMK8Kb5I9tVvJhA","name":"Degen","subtype":"USER"},"mergedIdentityIds":["Bs4naz7JMK8Kb5I9tVvJhA"],"paid":"0","payoutAddresses":{}},"cred":[2.0389715564573686e-34,2.0389715564573686e-34,2.0389715564573686e-34,2.0389715564573686e-34],"totalCred":8.155886225829474e-34},{"account":{"active":false,"allocationHistory":[],"balance":"0","identity":{"address":"N\u0000sourcecred\u0000core\u0000IDENTITY\u0000F74jDr0R3n1IGzUNOzozrQ\u0000","aliases":[{"address":"N\u0000sourcecred\u0000discord\u0000MEMBER\u0000user\u0000484191958743384085\u0000","description":"discord/wir#4873"}],"id":"F74jDr0R3n1IGzUNOzozrQ","name":"wir","subtype":"USER"},"mergedIdentityIds":["F74jDr0R3n1IGzUNOzozrQ"],"paid":"0","payoutAddresses":{}},"cred":[2.0389715564573686e-34,2.0389715564573686e-34,2.0389715564573686e-34,2.0389715564573686e-34],"totalCred":8.155886225829474e-34},{"account":{"active":false,"allocationHistory":[],"balance":"0","identity":{"address":"N\u0000sourcecred\u0000core\u0000IDENTITY\u0000Km4wrNk4QtkiOn5SX2zMlQ\u0000","aliases":[{"address":"N\u0000sourcecred\u0000discord\u0000MEMBER\u0000user\u0000488408777981165571\u0000","description":"discord/blakeburrito#1313"}],"id":"Km4wrNk4QtkiOn5SX2zMlQ","name":"blakeburrito","subtype":"USER"},"mergedIdentityIds":["Km4wrNk4QtkiOn5SX2zMlQ"],"paid":"0","payoutAddresses":{}},"cred":[0.1629127928566779,1.466215741011869,0.46401118089268056,3.1738980128481056],"totalCred":5.267037727609333},{"account":{"active":false,"allocationHistory":[],"balance":"0","identity":{"address":"N\u0000sourcecred\u0000core\u0000IDENTITY\u00004V4rC85qB9O7bzXK2bP90g\u0000","aliases":[{"address":"N\u0000sourcecred\u0000discord\u0000MEMBER\u0000user\u0000492160201420701696\u0000","description":"discord/SurfTranquille#5721"}],"id":"4V4rC85qB9O7bzXK2bP90g","name":"SurfTranquille","subtype":"USER"},"mergedIdentityIds":["4V4rC85qB9O7bzXK2bP90g"],"paid":"0","payoutAddresses":{}},"cred":[0.19239372595281568,1.731543693416937,2.018723909216491,0.22430260419689108],"totalCred":4.166963932783135},{"account":{"active":false,"allocationHistory":[],"balance":"0","identity":{"address":"N\u0000sourcecred\u0000core\u0000IDENTITY\u0000w8ocOVroL28DpJ3yI6OWBg\u0000","aliases":[{"address":"N\u0000sourcecred\u0000discord\u0000MEMBER\u0000user\u0000502120545186218007\u0000","description":"discord/&#x221E; haikukoten | Honey DAO &#x1F36F;#8725"}],"id":"w8ocOVroL28DpJ3yI6OWBg","name":"--haikukoten---Honey-DAO---","subtype":"USER"},"mergedIdentityIds":["w8ocOVroL28DpJ3yI6OWBg"],"paid":"0","payoutAddresses":{}},"cred":[2.0389715564573686e-34,2.0389715564573686e-34,2.0389715564573686e-34,2.0389715564573686e-34],"totalCred":8.155886225829474e-34},{"account":{"active":false,"allocationHistory":[],"balance":"0","identity":{"address":"N\u0000sourcecred\u0000core\u0000IDENTITY\u0000hGRZkGkt0Va9ZS1vj1RjCw\u0000","aliases":[{"address":"N\u0000sourcecred\u0000discord\u0000MEMBER\u0000user\u0000540264282927923232\u0000","description":"discord/ayyyeandy#1924"}],"id":"hGRZkGkt0Va9ZS1vj1RjCw","name":"ayyyeandy","subtype":"USER"},"mergedIdentityIds":["hGRZkGkt0Va9ZS1vj1RjCw"],"paid":"0","payoutAddresses":{}},"cred":[0.6679978970231125,5.406693710302953,0.5516896173377306,0.11020642110682972],"totalCred":6.736587645770626},{"account":{"active":false,"allocationHistory":[],"balance":"0","identity":{"address":"N\u0000sourcecred\u0000core\u0000IDENTITY\u000081l8m8V0KtxTDFo6elrfDw\u0000","aliases":[{"address":"N\u0000sourcecred\u0000discord\u0000MEMBER\u0000user\u0000542761771405017099\u0000","description":"discord/Bee926#4033"}],"id":"81l8m8V0KtxTDFo6elrfDw","name":"Bee926","subtype":"USER"},"mergedIdentityIds":["81l8m8V0KtxTDFo6elrfDw"],"paid":"0","payoutAddresses":{}},"cred":[0.024493231147158415,0.2204390391323469,1.0259628273218606,0.3713850096489063],"totalCred":1.6422801072502722},{"account":{"active":false,"allocationHistory":[],"balance":"0","identity":{"address":"N\u0000sourcecred\u0000core\u0000IDENTITY\u0000G6oF5RqhDFaBy0b3xB20HA\u0000","aliases":[{"address":"N\u0000sourcecred\u0000discord\u0000MEMBER\u0000user\u0000547419159785373708\u0000","description":"discord/TokenBrice.xyz#6531"}],"id":"G6oF5RqhDFaBy0b3xB20HA","name":"TokenBrice-xyz","subtype":"USER"},"mergedIdentityIds":["G6oF5RqhDFaBy0b3xB20HA"],"paid":"0","payoutAddresses":{}},"cred":[2.0389715564573686e-34,2.0389715564573686e-34,2.0389715564573686e-34,2.0389715564573686e-34],"totalCred":8.155886225829474e-34},{"account":{"active":false,"allocationHistory":[],"balance":"0","identity":{"address":"N\u0000sourcecred\u0000core\u0000IDENTITY\u0000CVbkfneh5Mrl7k39cxbbSg\u0000","aliases":[{"address":"N\u0000sourcecred\u0000discord\u0000MEMBER\u0000user\u0000548358064076619776\u0000","description":"discord/dunks411#2178"}],"id":"CVbkfneh5Mrl7k39cxbbSg","name":"dunks411","subtype":"USER"},"mergedIdentityIds":["CVbkfneh5Mrl7k39cxbbSg"],"paid":"0","payoutAddresses":{}},"cred":[7.716743643635316,9.148129609992546,16.104530266378436,7.395730168078991],"totalCred":40.36513368808529},{"account":{"active":false,"allocationHistory":[],"balance":"0","identity":{"address":"N\u0000sourcecred\u0000core\u0000IDENTITY\u0000ZqG2yWPDFLMQeK8OgEAJIg\u0000","aliases":[{"address":"N\u0000sourcecred\u0000discord\u0000MEMBER\u0000user\u0000561559631072198656\u0000","description":"discord/Ade#2314"}],"id":"ZqG2yWPDFLMQeK8OgEAJIg","name":"Ade","subtype":"USER"},"mergedIdentityIds":["ZqG2yWPDFLMQeK8OgEAJIg"],"paid":"0","payoutAddresses":{}},"cred":[2.0389715564573686e-34,2.0389715564573686e-34,2.0389715564573686e-34,2.0389715564573686e-34],"totalCred":8.155886225829474e-34},{"account":{"active":false,"allocationHistory":[],"balance":"0","identity":{"address":"N\u0000sourcecred\u0000core\u0000IDENTITY\u0000gdRgKaf1xHE8VHV2K73uDw\u0000","aliases":[{"address":"N\u0000sourcecred\u0000discord\u0000MEMBER\u0000user\u0000585660108542050347\u0000","description":"discord/greenbarkeep#2998"}],"id":"gdRgKaf1xHE8VHV2K73uDw","name":"greenbarkeep","subtype":"USER"},"mergedIdentityIds":["gdRgKaf1xHE8VHV2K73uDw"],"paid":"0","payoutAddresses":{}},"cred":[2.0389715564573686e-34,2.0389715564573686e-34,2.0389715564573686e-34,2.0389715564573686e-34],"totalCred":8.155886225829474e-34},{"account":{"active":false,"allocationHistory":[],"balance":"0","identity":{"address":"N\u0000sourcecred\u0000core\u0000IDENTITY\u0000bagmW5DY6aVkiQJ9H55FYQ\u0000","aliases":[{"address":"N\u0000sourcecred\u0000discord\u0000MEMBER\u0000user\u0000588212990990352384\u0000","description":"discord/28ickler(Zorx)#1913"}],"id":"bagmW5DY6aVkiQJ9H55FYQ","name":"28ickler-Zorx-","subtype":"USER"},"mergedIdentityIds":["bagmW5DY6aVkiQJ9H55FYQ"],"paid":"0","payoutAddresses":{}},"cred":[2.0389715564573686e-34,2.0389715564573686e-34,2.0389715564573686e-34,2.0389715564573686e-34],"totalCred":8.155886225829474e-34},{"account":{"active":false,"allocationHistory":[],"balance":"0","identity":{"address":"N\u0000sourcecred\u0000core\u0000IDENTITY\u00009SxEkD69vzvVrEMogjggKg\u0000","aliases":[{"address":"N\u0000sourcecred\u0000discord\u0000MEMBER\u0000user\u0000602285689056526366\u0000","description":"discord/brrrick#9351"}],"id":"9SxEkD69vzvVrEMogjggKg","name":"brrrick","subtype":"USER"},"mergedIdentityIds":["9SxEkD69vzvVrEMogjggKg"],"paid":"0","payoutAddresses":{}},"cred":[2.0389715564573686e-34,2.0389715564573686e-34,2.0389715564573686e-34,2.0389715564573686e-34],"totalCred":8.155886225829474e-34},{"account":{"active":false,"allocationHistory":[],"balance":"0","identity":{"address":"N\u0000sourcecred\u0000core\u0000IDENTITY\u0000kbDDlX1Z8Y6o2XdG6smhJw\u0000","aliases":[{"address":"N\u0000sourcecred\u0000discord\u0000MEMBER\u0000bot\u0000616754792965865495\u0000","description":"discord/sesh#1244"}],"id":"kbDDlX1Z8Y6o2XdG6smhJw","name":"sesh","subtype":"BOT"},"mergedIdentityIds":["kbDDlX1Z8Y6o2XdG6smhJw"],"paid":"0","payoutAddresses":{}},"cred":[1.769692629314957,15.927238875712,6.753947131804775,0.7504387135702819],"totalCred":25.201317350402014},{"account":{"active":false,"allocationHistory":[],"balance":"0","identity":{"address":"N\u0000sourcecred\u0000core\u0000IDENTITY\u0000RdiyBfYrce7J3Niae5QEtg\u0000","aliases":[{"address":"N\u0000sourcecred\u0000discord\u0000MEMBER\u0000user\u0000618248969901965312\u0000","description":"discord/jaybird#5235"}],"id":"RdiyBfYrce7J3Niae5QEtg","name":"jaybird","subtype":"USER"},"mergedIdentityIds":["RdiyBfYrce7J3Niae5QEtg"],"paid":"0","payoutAddresses":{}},"cred":[0.07843587226789515,0.19426860546247587,0.019645135262800678,0.002182792326805814],"totalCred":0.29453240531997754},{"account":{"active":false,"allocationHistory":[],"balance":"0","identity":{"address":"N\u0000sourcecred\u0000core\u0000IDENTITY\u0000S9X3HeWRp3naBaTpZXvgRw\u0000","aliases":[{"address":"N\u0000sourcecred\u0000discord\u0000MEMBER\u0000bot\u0000620126394390675466\u0000","description":"discord/Taco#0086"}],"id":"S9X3HeWRp3naBaTpZXvgRw","name":"Taco","subtype":"BOT"},"mergedIdentityIds":["S9X3HeWRp3naBaTpZXvgRw"],"paid":"0","payoutAddresses":{}},"cred":[2.0389715564573686e-34,2.0389715564573686e-34,2.0389715564573686e-34,2.0389715564573686e-34],"totalCred":8.155886225829474e-34},{"account":{"active":false,"allocationHistory":[],"balance":"0","identity":{"address":"N\u0000sourcecred\u0000core\u0000IDENTITY\u0000VvW6NYX3yvkriZuMzZ819g\u0000","aliases":[{"address":"N\u0000sourcecred\u0000discord\u0000MEMBER\u0000user\u0000634462979911581713\u0000","description":"discord/SkyHawkDP#3825"}],"id":"VvW6NYX3yvkriZuMzZ819g","name":"SkyHawkDP","subtype":"USER"},"mergedIdentityIds":["VvW6NYX3yvkriZuMzZ819g"],"paid":"0","payoutAddresses":{}},"cred":[1.1881807480658177,0.12003183842256232,0.012138064879829533,0.0013486716725656757],"totalCred":1.3216993230407752},{"account":{"active":false,"allocationHistory":[],"balance":"0","identity":{"address":"N\u0000sourcecred\u0000core\u0000IDENTITY\u0000krMx3bbJlHA7UZpcmM8e5Q\u0000","aliases":[{"address":"N\u0000sourcecred\u0000discord\u0000MEMBER\u0000user\u0000638493028952178738\u0000","description":"discord/uh#2064"}],"id":"krMx3bbJlHA7UZpcmM8e5Q","name":"uh","subtype":"USER"},"mergedIdentityIds":["krMx3bbJlHA7UZpcmM8e5Q"],"paid":"0","payoutAddresses":{}},"cred":[0.004619131244763282,0.041572200357402715,0.00420392862451865,0.0004671030205394581],"totalCred":0.0508623632472241},{"account":{"active":false,"allocationHistory":[],"balance":"0","identity":{"address":"N\u0000sourcecred\u0000core\u0000IDENTITY\u0000sd19QOJbJn4e0ArQeppJSQ\u0000","aliases":[{"address":"N\u0000sourcecred\u0000discord\u0000MEMBER\u0000user\u0000640144569710673930\u0000","description":"discord/sisyphus1337#7913"}],"id":"sd19QOJbJn4e0ArQeppJSQ","name":"sisyphus1337","subtype":"USER"},"mergedIdentityIds":["sd19QOJbJn4e0ArQeppJSQ"],"paid":"0","payoutAddresses":{}},"cred":[0.1732214671383072,0.03389109009791182,0.0034271857309084957,0.00038079889859490124],"totalCred":0.21092054186572243},{"account":{"active":false,"allocationHistory":[],"balance":"0","identity":{"address":"N\u0000sourcecred\u0000core\u0000IDENTITY\u0000q4YrAMYo5uGcAYwwgrKr1Q\u0000","aliases":[{"address":"N\u0000sourcecred\u0000discord\u0000MEMBER\u0000user\u0000653348489433972756\u0000","description":"discord/Gabrielhaines#0617"}],"id":"q4YrAMYo5uGcAYwwgrKr1Q","name":"Gabrielhaines","subtype":"USER"},"mergedIdentityIds":["q4YrAMYo5uGcAYwwgrKr1Q"],"paid":"0","payoutAddresses":{}},"cred":[7.45780886086357,4.670611649191454,0.9057033626303697,3.08429333685314],"totalCred":16.118417209538535},{"account":{"active":false,"allocationHistory":[],"balance":"0","identity":{"address":"N\u0000sourcecred\u0000core\u0000IDENTITY\u000009Ir1w5uKAdC183IvKdnQw\u0000","aliases":[{"address":"N\u0000sourcecred\u0000discord\u0000MEMBER\u0000user\u0000655679782360449075\u0000","description":"discord/0x.Hemsta#3248"}],"id":"09Ir1w5uKAdC183IvKdnQw","name":"0x-Hemsta","subtype":"USER"},"mergedIdentityIds":["09Ir1w5uKAdC183IvKdnQw"],"paid":"0","payoutAddresses":{}},"cred":[0.00635760023587907,0.05721840396108231,0.005786131009396149,0.0006429029828534776],"totalCred":0.07000503818921101},{"account":{"active":false,"allocationHistory":[],"balance":"0","identity":{"address":"N\u0000sourcecred\u0000core\u0000IDENTITY\u00001WkZOSdsJ899PCOyW11NeA\u0000","aliases":[{"address":"N\u0000sourcecred\u0000discord\u0000MEMBER\u0000user\u0000693968649052094525\u0000","description":"discord/cryptouf#2315"}],"id":"1WkZOSdsJ899PCOyW11NeA","name":"cryptouf","subtype":"USER"},"mergedIdentityIds":["1WkZOSdsJ899PCOyW11NeA"],"paid":"0","payoutAddresses":{}},"cred":[0.14715708787337176,0.022759188069334833,0.0023014906362175905,0.00025572132598114473],"totalCred":0.17247348790490533},{"account":{"active":false,"allocationHistory":[],"balance":"0","identity":{"address":"N\u0000sourcecred\u0000core\u0000IDENTITY\u0000Yh95DxYad2NXz7f8Jv2wfg\u0000","aliases":[{"address":"N\u0000sourcecred\u0000discord\u0000MEMBER\u0000user\u0000698267000845238483\u0000","description":"discord/revolutionary_spaces#5629"}],"id":"Yh95DxYad2NXz7f8Jv2wfg","name":"revolutionary-spaces","subtype":"USER"},"mergedIdentityIds":["Yh95DxYad2NXz7f8Jv2wfg"],"paid":"0","payoutAddresses":{}},"cred":[2.0389715564573686e-34,2.0389715564573686e-34,2.0389715564573686e-34,2.0389715564573686e-34],"totalCred":8.155886225829474e-34},{"account":{"active":false,"allocationHistory":[],"balance":"0","identity":{"address":"N\u0000sourcecred\u0000core\u0000IDENTITY\u0000iO943JIJrmenFlexcwZTew\u0000","aliases":[{"address":"N\u0000sourcecred\u0000discord\u0000MEMBER\u0000user\u0000698723963014217790\u0000","description":"discord/bg999#6547"}],"id":"iO943JIJrmenFlexcwZTew","name":"bg999","subtype":"USER"},"mergedIdentityIds":["iO943JIJrmenFlexcwZTew"],"paid":"0","payoutAddresses":{}},"cred":[2.0389715564573686e-34,2.0389715564573686e-34,2.0389715564573686e-34,2.0389715564573686e-34],"totalCred":8.155886225829474e-34},{"account":{"active":false,"allocationHistory":[],"balance":"0","identity":{"address":"N\u0000sourcecred\u0000core\u0000IDENTITY\u0000pWHbWXe2NFlnMT9HewgWWw\u0000","aliases":[{"address":"N\u0000sourcecred\u0000discord\u0000MEMBER\u0000user\u0000719350246223642687\u0000","description":"discord/Heruvim78#6876"}],"id":"pWHbWXe2NFlnMT9HewgWWw","name":"Heruvim78","subtype":"USER"},"mergedIdentityIds":["pWHbWXe2NFlnMT9HewgWWw"],"paid":"0","payoutAddresses":{}},"cred":[2.0389715564573686e-34,2.0389715564573686e-34,2.0389715564573686e-34,2.0389715564573686e-34],"totalCred":8.155886225829474e-34},{"account":{"active":false,"allocationHistory":[],"balance":"0","identity":{"address":"N\u0000sourcecred\u0000core\u0000IDENTITY\u00007vNTPpj76OILPcnlQ2AfEw\u0000","aliases":[{"address":"N\u0000sourcecred\u0000discord\u0000MEMBER\u0000user\u0000722575082156851211\u0000","description":"discord/PVMihalache#8517"}],"id":"7vNTPpj76OILPcnlQ2AfEw","name":"PVMihalache","subtype":"USER"},"mergedIdentityIds":["7vNTPpj76OILPcnlQ2AfEw"],"paid":"0","payoutAddresses":{}},"cred":[0.019050214491277882,0.07078737339348684,0.007158267065361996,0.0007953637771892933],"totalCred":0.09779121872731601},{"account":{"active":false,"allocationHistory":[],"balance":"0","identity":{"address":"N\u0000sourcecred\u0000core\u0000IDENTITY\u0000S9Tvq9mirHMEqVHQdeiokA\u0000","aliases":[{"address":"N\u0000sourcecred\u0000discord\u0000MEMBER\u0000user\u0000739481321105260677\u0000","description":"discord/louve&#x1F311;#8063"}],"id":"S9Tvq9mirHMEqVHQdeiokA","name":"louve--","subtype":"USER"},"mergedIdentityIds":["S9Tvq9mirHMEqVHQdeiokA"],"paid":"0","payoutAddresses":{}},"cred":[2.0389715564573686e-34,2.0389715564573686e-34,2.0389715564573686e-34,2.0389715564573686e-34],"totalCred":8.155886225829474e-34},{"account":{"active":false,"allocationHistory":[],"balance":"0","identity":{"address":"N\u0000sourcecred\u0000core\u0000IDENTITY\u0000twTZ7vw0UANfVuduD3tynA\u0000","aliases":[{"address":"N\u0000sourcecred\u0000discord\u0000MEMBER\u0000user\u0000744095301173772358\u0000","description":"discord/Bertaliot#0156"}],"id":"twTZ7vw0UANfVuduD3tynA","name":"Bertaliot","subtype":"USER"},"mergedIdentityIds":["twTZ7vw0UANfVuduD3tynA"],"paid":"0","payoutAddresses":{}},"cred":[0.001534228581136673,0.013808071322024948,0.0013963202320176418,0.00015514687758911587],"totalCred":0.016893767012768377},{"account":{"active":false,"allocationHistory":[],"balance":"0","identity":{"address":"N\u0000sourcecred\u0000core\u0000IDENTITY\u0000mK2RxuErkXWWJpOCrMfVTw\u0000","aliases":[{"address":"N\u0000sourcecred\u0000discord\u0000MEMBER\u0000user\u0000744523836115910758\u0000","description":"discord/0xkowloon#3337"}],"id":"mK2RxuErkXWWJpOCrMfVTw","name":"0xkowloon","subtype":"USER"},"mergedIdentityIds":["mK2RxuErkXWWJpOCrMfVTw"],"paid":"0","payoutAddresses":{}},"cred":[4.071392628288236,1.0185862882368732,0.41018572556181854,1.9179091481032065],"totalCred":7.418073790190135},{"account":{"active":false,"allocationHistory":[],"balance":"0","identity":{"address":"N\u0000sourcecred\u0000core\u0000IDENTITY\u0000bH70NnOI5FlsyYRcLD7tQA\u0000","aliases":[{"address":"N\u0000sourcecred\u0000discord\u0000MEMBER\u0000user\u0000745702107801452634\u0000","description":"discord/Singikin#6817"}],"id":"bH70NnOI5FlsyYRcLD7tQA","name":"Singikin","subtype":"USER"},"mergedIdentityIds":["bH70NnOI5FlsyYRcLD7tQA"],"paid":"0","payoutAddresses":{}},"cred":[2.0389715564573686e-34,2.0389715564573686e-34,2.0389715564573686e-34,2.0389715564573686e-34],"totalCred":8.155886225829474e-34},{"account":{"active":false,"allocationHistory":[],"balance":"0","identity":{"address":"N\u0000sourcecred\u0000core\u0000IDENTITY\u0000ueVkKqaNRE7h3nde6EC29A\u0000","aliases":[{"address":"N\u0000sourcecred\u0000discord\u0000MEMBER\u0000user\u0000764477382185713690\u0000","description":"discord/akshayraw#0698"}],"id":"ueVkKqaNRE7h3nde6EC29A","name":"akshayraw","subtype":"USER"},"mergedIdentityIds":["ueVkKqaNRE7h3nde6EC29A"],"paid":"0","payoutAddresses":{}},"cred":[2.0389715564573686e-34,2.0389715564573686e-34,2.0389715564573686e-34,2.0389715564573686e-34],"totalCred":8.155886225829474e-34},{"account":{"active":false,"allocationHistory":[],"balance":"0","identity":{"address":"N\u0000sourcecred\u0000core\u0000IDENTITY\u0000rD8yzQwO7EVbFRm3UqDA7Q\u0000","aliases":[{"address":"N\u0000sourcecred\u0000discord\u0000MEMBER\u0000user\u0000775192734562517016\u0000","description":"discord/fugu#1472"}],"id":"rD8yzQwO7EVbFRm3UqDA7Q","name":"fugu","subtype":"USER"},"mergedIdentityIds":["rD8yzQwO7EVbFRm3UqDA7Q"],"paid":"0","payoutAddresses":{}},"cred":[4.017783357471354,0.5361027972510253,0.7343652915095146,6.807552807756483],"totalCred":12.095804253988376},{"account":{"active":false,"allocationHistory":[],"balance":"0","identity":{"address":"N\u0000sourcecred\u0000core\u0000IDENTITY\u0000N0BMze0ubtyCDMSo9fqkMA\u0000","aliases":[{"address":"N\u0000sourcecred\u0000discord\u0000MEMBER\u0000user\u0000794837781801205761\u0000","description":"discord/PassiveCrypto#6857"}],"id":"N0BMze0ubtyCDMSo9fqkMA","name":"PassiveCrypto","subtype":"USER"},"mergedIdentityIds":["N0BMze0ubtyCDMSo9fqkMA"],"paid":"0","payoutAddresses":{}},"cred":[0.00046924698831151286,0.004223224332176276,0.04176301306321097,0.004640332702228703],"totalCred":0.05109581708592746},{"account":{"active":false,"allocationHistory":[],"balance":"0","identity":{"address":"N\u0000sourcecred\u0000core\u0000IDENTITY\u0000QLEPfx5SVylLn4abS3u60g\u0000","aliases":[{"address":"N\u0000sourcecred\u0000discord\u0000MEMBER\u0000user\u0000795973530025066506\u0000","description":"discord/loco#1403"}],"id":"QLEPfx5SVylLn4abS3u60g","name":"loco","subtype":"USER"},"mergedIdentityIds":["QLEPfx5SVylLn4abS3u60g"],"paid":"0","payoutAddresses":{}},"cred":[2.0389715564573686e-34,2.0389715564573686e-34,2.0389715564573686e-34,2.0389715564573686e-34],"totalCred":8.155886225829474e-34},{"account":{"active":false,"allocationHistory":[],"balance":"0","identity":{"address":"N\u0000sourcecred\u0000core\u0000IDENTITY\u0000kMr8jf2OmW4ZDoYMCpJO4A\u0000","aliases":[{"address":"N\u0000sourcecred\u0000discord\u0000MEMBER\u0000user\u0000797330295371202613\u0000","description":"discord/cc2#2803"}],"id":"kMr8jf2OmW4ZDoYMCpJO4A","name":"cc2","subtype":"USER"},"mergedIdentityIds":["kMr8jf2OmW4ZDoYMCpJO4A"],"paid":"0","payoutAddresses":{}},"cred":[2.0389715564573686e-34,2.0389715564573686e-34,2.0389715564573686e-34,2.0389715564573686e-34],"totalCred":8.155886225829474e-34},{"account":{"active":false,"allocationHistory":[],"balance":"0","identity":{"address":"N\u0000sourcecred\u0000core\u0000IDENTITY\u0000TVzXsOy4QDgnj2Q9Zbg3QA\u0000","aliases":[{"address":"N\u0000sourcecred\u0000discord\u0000MEMBER\u0000user\u0000812348750394556457\u0000","description":"discord/Beij#2923"}],"id":"TVzXsOy4QDgnj2Q9Zbg3QA","name":"Beij","subtype":"USER"},"mergedIdentityIds":["TVzXsOy4QDgnj2Q9Zbg3QA"],"paid":"0","payoutAddresses":{}},"cred":[2.0389715564573686e-34,2.0389715564573686e-34,2.0389715564573686e-34,2.0389715564573686e-34],"totalCred":8.155886225829474e-34},{"account":{"active":false,"allocationHistory":[],"balance":"0","identity":{"address":"N\u0000sourcecred\u0000core\u0000IDENTITY\u00007faA0kyrRFWbAlxUNvYxMQ\u0000","aliases":[{"address":"N\u0000sourcecred\u0000discord\u0000MEMBER\u0000user\u0000814527474251726928\u0000","description":"discord/evgeniy#5551"}],"id":"7faA0kyrRFWbAlxUNvYxMQ","name":"evgeniy","subtype":"USER"},"mergedIdentityIds":["7faA0kyrRFWbAlxUNvYxMQ"],"paid":"0","payoutAddresses":{}},"cred":[2.0389715564573686e-34,2.0389715564573686e-34,2.0389715564573686e-34,2.0389715564573686e-34],"totalCred":8.155886225829474e-34},{"account":{"active":false,"allocationHistory":[],"balance":"0","identity":{"address":"N\u0000sourcecred\u0000core\u0000IDENTITY\u0000NO5MZT2eWzVJ890r8C5MWw\u0000","aliases":[{"address":"N\u0000sourcecred\u0000discord\u0000MEMBER\u0000user\u0000820466501022122034\u0000","description":"discord/0xtundra#7151"}],"id":"NO5MZT2eWzVJ890r8C5MWw","name":"0xtundra","subtype":"USER"},"mergedIdentityIds":["NO5MZT2eWzVJ890r8C5MWw"],"paid":"0","payoutAddresses":{}},"cred":[2.0389715564573686e-34,2.0389715564573686e-34,2.0389715564573686e-34,2.0389715564573686e-34],"totalCred":8.155886225829474e-34},{"account":{"active":false,"allocationHistory":[],"balance":"0","identity":{"address":"N\u0000sourcecred\u0000core\u0000IDENTITY\u0000CnnExBWEwxfaKCEfa2Wa6A\u0000","aliases":[{"address":"N\u0000sourcecred\u0000discord\u0000MEMBER\u0000user\u0000823084051589103668\u0000","description":"discord/Rheta Thurber#0017"}],"id":"CnnExBWEwxfaKCEfa2Wa6A","name":"Rheta-Thurber","subtype":"USER"},"mergedIdentityIds":["CnnExBWEwxfaKCEfa2Wa6A"],"paid":"0","payoutAddresses":{}},"cred":[2.0389715564573686e-34,2.0389715564573686e-34,2.0389715564573686e-34,2.0389715564573686e-34],"totalCred":8.155886225829474e-34},{"account":{"active":false,"allocationHistory":[],"balance":"0","identity":{"address":"N\u0000sourcecred\u0000core\u0000IDENTITY\u0000NqDFemirw5HAzaA9lgKVdg\u0000","aliases":[{"address":"N\u0000sourcecred\u0000discord\u0000MEMBER\u0000user\u0000824093377544454185\u0000","description":"discord/0xLingonberry#2327"}],"id":"NqDFemirw5HAzaA9lgKVdg","name":"0xLingonberry","subtype":"USER"},"mergedIdentityIds":["NqDFemirw5HAzaA9lgKVdg"],"paid":"0","payoutAddresses":{}},"cred":[2.0389715564573686e-34,2.0389715564573686e-34,2.0389715564573686e-34,2.0389715564573686e-34],"totalCred":8.155886225829474e-34},{"account":{"active":false,"allocationHistory":[],"balance":"0","identity":{"address":"N\u0000sourcecred\u0000core\u0000IDENTITY\u0000DjZCgNiPPbHGl3f7fWwx2A\u0000","aliases":[{"address":"N\u0000sourcecred\u0000discord\u0000MEMBER\u0000user\u0000827017198660747274\u0000","description":"discord/yousnoel#7108"}],"id":"DjZCgNiPPbHGl3f7fWwx2A","name":"yousnoel","subtype":"USER"},"mergedIdentityIds":["DjZCgNiPPbHGl3f7fWwx2A"],"paid":"0","payoutAddresses":{}},"cred":[0.057115329695450925,0.005769879620696459,0.0005834706256526073,0.00006483015434410718],"totalCred":0.0635335100961441},{"account":{"active":false,"allocationHistory":[],"balance":"0","identity":{"address":"N\u0000sourcecred\u0000core\u0000IDENTITY\u0000oIyMilsE3IniY7spOaw5rg\u0000","aliases":[{"address":"N\u0000sourcecred\u0000discord\u0000MEMBER\u0000user\u0000830296854428254229\u0000","description":"discord/redefined_life#4464"}],"id":"oIyMilsE3IniY7spOaw5rg","name":"redefined-life","subtype":"USER"},"mergedIdentityIds":["oIyMilsE3IniY7spOaw5rg"],"paid":"0","payoutAddresses":{}},"cred":[2.0389715564573686e-34,2.0389715564573686e-34,2.0389715564573686e-34,2.0389715564573686e-34],"totalCred":8.155886225829474e-34},{"account":{"active":false,"allocationHistory":[],"balance":"0","identity":{"address":"N\u0000sourcecred\u0000core\u0000IDENTITY\u0000AhxYuZm3xGr4EQ8og851eA\u0000","aliases":[{"address":"N\u0000sourcecred\u0000discord\u0000MEMBER\u0000user\u0000836830322787221546\u0000","description":"discord/C1DoubleDown#4331"}],"id":"AhxYuZm3xGr4EQ8og851eA","name":"C1DoubleDown","subtype":"USER"},"mergedIdentityIds":["AhxYuZm3xGr4EQ8og851eA"],"paid":"0","payoutAddresses":{}},"cred":[0.0016773940850443815,0.015096530467717272,0.0015266171030995752,0.00016962408508827215],"totalCred":0.0184701657409495},{"account":{"active":false,"allocationHistory":[],"balance":"0","identity":{"address":"N\u0000sourcecred\u0000core\u0000IDENTITY\u0000tDD7lMOhVI9PdxyyBfvYBQ\u0000","aliases":[{"address":"N\u0000sourcecred\u0000discord\u0000MEMBER\u0000user\u0000848366279785709598\u0000","description":"discord/insider#7291"}],"id":"tDD7lMOhVI9PdxyyBfvYBQ","name":"insider","subtype":"USER"},"mergedIdentityIds":["tDD7lMOhVI9PdxyyBfvYBQ"],"paid":"0","payoutAddresses":{}},"cred":[2.0389715564573686e-34,2.0389715564573686e-34,2.0389715564573686e-34,2.0389715564573686e-34],"totalCred":8.155886225829474e-34},{"account":{"active":false,"allocationHistory":[],"balance":"0","identity":{"address":"N\u0000sourcecred\u0000core\u0000IDENTITY\u0000d7GhgwD3DNwoz9GJCljaUw\u0000","aliases":[{"address":"N\u0000sourcecred\u0000discord\u0000MEMBER\u0000user\u0000856771322788708373\u0000","description":"discord/eddyCRZ#3063"}],"id":"d7GhgwD3DNwoz9GJCljaUw","name":"eddyCRZ","subtype":"USER"},"mergedIdentityIds":["d7GhgwD3DNwoz9GJCljaUw"],"paid":"0","payoutAddresses":{}},"cred":[2.0389715564573686e-34,2.0389715564573686e-34,2.0389715564573686e-34,2.0389715564573686e-34],"totalCred":8.155886225829474e-34},{"account":{"active":false,"allocationHistory":[],"balance":"0","identity":{"address":"N\u0000sourcecred\u0000core\u0000IDENTITY\u0000Rn7p5myql9NJtoZq0XoZjw\u0000","aliases":[{"address":"N\u0000sourcecred\u0000discord\u0000MEMBER\u0000user\u0000860127400628846613\u0000","description":"discord/lem#5511"}],"id":"Rn7p5myql9NJtoZq0XoZjw","name":"lem","subtype":"USER"},"mergedIdentityIds":["Rn7p5myql9NJtoZq0XoZjw"],"paid":"0","payoutAddresses":{}},"cred":[0.6309109708958577,0.0653391543221566,0.02248084659890279,0.0024978675439162133],"totalCred":0.7212288393608334},{"account":{"active":false,"allocationHistory":[],"balance":"0","identity":{"address":"N\u0000sourcecred\u0000core\u0000IDENTITY\u0000lmBSjFVIl5aWiPPpyTzJAw\u0000","aliases":[{"address":"N\u0000sourcecred\u0000discord\u0000MEMBER\u0000bot\u0000863361964549079041\u0000","description":"discord/cre8rcred#0197"}],"id":"lmBSjFVIl5aWiPPpyTzJAw","name":"cre8rcred","subtype":"BOT"},"mergedIdentityIds":["lmBSjFVIl5aWiPPpyTzJAw"],"paid":"0","payoutAddresses":{}},"cred":[2.0389715564573686e-34,2.0389715564573686e-34,2.0389715564573686e-34,2.0389715564573686e-34],"totalCred":8.155886225829474e-34},{"account":{"active":false,"allocationHistory":[],"balance":"0","identity":{"address":"N\u0000sourcecred\u0000core\u0000IDENTITY\u0000uBfLPUGy7irNVc603ltoSg\u0000","aliases":[{"address":"N\u0000sourcecred\u0000discord\u0000MEMBER\u0000user\u0000180644728675500032\u0000","description":"discord/wassiecapital#3180"}],"id":"uBfLPUGy7irNVc603ltoSg","name":"wassiecapital","subtype":"USER"},"mergedIdentityIds":["uBfLPUGy7irNVc603ltoSg"],"paid":"0","payoutAddresses":{}},"cred":[0.2659197133480884,0.35425568594185564,3.2766366951010784,6.593639529826198],"totalCred":10.49045162421722},{"account":{"active":false,"allocationHistory":[],"balance":"0","identity":{"address":"N\u0000sourcecred\u0000core\u0000IDENTITY\u0000GEqpdhY58OFaH4FLEmZ1Jw\u0000","aliases":[{"address":"N\u0000sourcecred\u0000discord\u0000MEMBER\u0000user\u0000202967732046659586\u0000","description":"discord/iamgaurangdesai#7548"}],"id":"GEqpdhY58OFaH4FLEmZ1Jw","name":"iamgaurangdesai","subtype":"USER"},"mergedIdentityIds":["GEqpdhY58OFaH4FLEmZ1Jw"],"paid":"0","payoutAddresses":{}},"cred":[0.031095849474584786,0.2798622914103667,2.767528273636707,0.8057482328707386],"totalCred":3.884234647392397},{"account":{"active":false,"allocationHistory":[],"balance":"0","identity":{"address":"N\u0000sourcecred\u0000core\u0000IDENTITY\u0000b0AOyK8g4WoCk14LJ1EJ5A\u0000","aliases":[{"address":"N\u0000sourcecred\u0000discord\u0000MEMBER\u0000user\u0000216661390474084352\u0000","description":"discord/minkman#1727"}],"id":"b0AOyK8g4WoCk14LJ1EJ5A","name":"minkman","subtype":"USER"},"mergedIdentityIds":["b0AOyK8g4WoCk14LJ1EJ5A"],"paid":"0","payoutAddresses":{}},"cred":[2.0389715564573686e-34,2.0389715564573686e-34,2.0389715564573686e-34,2.0389715564573686e-34],"totalCred":8.155886225829474e-34},{"account":{"active":false,"allocationHistory":[],"balance":"0","identity":{"address":"N\u0000sourcecred\u0000core\u0000IDENTITY\u0000GSV3X6SlwxAYfkRYaJgwNQ\u0000","aliases":[{"address":"N\u0000sourcecred\u0000discord\u0000MEMBER\u0000user\u0000241759820955385856\u0000","description":"discord/Jacks#6609"}],"id":"GSV3X6SlwxAYfkRYaJgwNQ","name":"Jacks","subtype":"USER"},"mergedIdentityIds":["GSV3X6SlwxAYfkRYaJgwNQ"],"paid":"0","payoutAddresses":{}},"cred":[0.004715883672057472,0.04244289903867157,0.4197132941759062,0.04663479656566902],"totalCred":0.5135068734523043},{"account":{"active":false,"allocationHistory":[],"balance":"0","identity":{"address":"N\u0000sourcecred\u0000core\u0000IDENTITY\u00005xjxPgb43cgtxGwux5KJeA\u0000","aliases":[{"address":"N\u0000sourcecred\u0000discord\u0000MEMBER\u0000user\u0000269021622378168322\u0000","description":"discord/ikonoklast#7445"}],"id":"5xjxPgb43cgtxGwux5KJeA","name":"ikonoklast","subtype":"USER"},"mergedIdentityIds":["5xjxPgb43cgtxGwux5KJeA"],"paid":"0","payoutAddresses":{}},"cred":[2.0389715564573686e-34,2.0389715564573686e-34,2.0389715564573686e-34,2.0389715564573686e-34],"totalCred":8.155886225829474e-34},{"account":{"active":false,"allocationHistory":[],"balance":"0","identity":{"address":"N\u0000sourcecred\u0000core\u0000IDENTITY\u00000HM9hXujmBJiDUJYt9gFGQ\u0000","aliases":[{"address":"N\u0000sourcecred\u0000discord\u0000MEMBER\u0000user\u0000279155446735175680\u0000","description":"discord/Ultima5ky#7126"}],"id":"0HM9hXujmBJiDUJYt9gFGQ","name":"Ultima5ky","subtype":"USER"},"mergedIdentityIds":["0HM9hXujmBJiDUJYt9gFGQ"],"paid":"0","payoutAddresses":{}},"cred":[0.009479896474181404,0.08531895325844133,0.8437102142777948,0.152389799748877],"totalCred":1.0908988637592945},{"account":{"active":false,"allocationHistory":[],"balance":"0","identity":{"address":"N\u0000sourcecred\u0000core\u0000IDENTITY\u0000QE2C1Q9RlVZRoMYbPPASRQ\u0000","aliases":[{"address":"N\u0000sourcecred\u0000discord\u0000MEMBER\u0000user\u0000280003023093366785\u0000","description":"discord/Callidus#0607"}],"id":"QE2C1Q9RlVZRoMYbPPASRQ","name":"Callidus","subtype":"USER"},"mergedIdentityIds":["QE2C1Q9RlVZRoMYbPPASRQ"],"paid":"0","payoutAddresses":{}},"cred":[2.0389715564573686e-34,2.0389715564573686e-34,2.0389715564573686e-34,2.0389715564573686e-34],"totalCred":8.155886225829474e-34},{"account":{"active":false,"allocationHistory":[],"balance":"0","identity":{"address":"N\u0000sourcecred\u0000core\u0000IDENTITY\u0000fLPWQX3E7IzfG47bZc3cjA\u0000","aliases":[{"address":"N\u0000sourcecred\u0000discord\u0000MEMBER\u0000user\u0000317075462935543808\u0000","description":"discord/PunnyUserName#7480"}],"id":"fLPWQX3E7IzfG47bZc3cjA","name":"PunnyUserName","subtype":"USER"},"mergedIdentityIds":["fLPWQX3E7IzfG47bZc3cjA"],"paid":"0","payoutAddresses":{}},"cred":[2.0389715564573686e-34,2.0389715564573686e-34,2.0389715564573686e-34,2.0389715564573686e-34],"totalCred":8.155886225829474e-34},{"account":{"active":false,"allocationHistory":[],"balance":"0","identity":{"address":"N\u0000sourcecred\u0000core\u0000IDENTITY\u00005yWM8ers6zJmEpQdzEooOw\u0000","aliases":[{"address":"N\u0000sourcecred\u0000discord\u0000MEMBER\u0000user\u0000324125816151867403\u0000","description":"discord/CryptoPriest#9804"}],"id":"5yWM8ers6zJmEpQdzEooOw","name":"CryptoPriest","subtype":"USER"},"mergedIdentityIds":["5yWM8ers6zJmEpQdzEooOw"],"paid":"0","payoutAddresses":{}},"cred":[2.0389715564573686e-34,2.0389715564573686e-34,2.0389715564573686e-34,2.0389715564573686e-34],"totalCred":8.155886225829474e-34},{"account":{"active":false,"allocationHistory":[],"balance":"0","identity":{"address":"N\u0000sourcecred\u0000core\u0000IDENTITY\u0000oNfRDA4PAJaknkI3k5ZANg\u0000","aliases":[{"address":"N\u0000sourcecred\u0000discord\u0000MEMBER\u0000user\u0000325769652162658314\u0000","description":"discord/0xDead1#7552"}],"id":"oNfRDA4PAJaknkI3k5ZANg","name":"0xDead1","subtype":"USER"},"mergedIdentityIds":["oNfRDA4PAJaknkI3k5ZANg"],"paid":"0","payoutAddresses":{}},"cred":[2.0389715564573686e-34,2.0389715564573686e-34,2.0389715564573686e-34,2.0389715564573686e-34],"totalCred":8.155886225829474e-34},{"account":{"active":false,"allocationHistory":[],"balance":"0","identity":{"address":"N\u0000sourcecred\u0000core\u0000IDENTITY\u0000sMXMSQf7D6rkM6wy5js1QQ\u0000","aliases":[{"address":"N\u0000sourcecred\u0000discord\u0000MEMBER\u0000user\u0000328630969554960394\u0000","description":"discord/marlo#4556"}],"id":"sMXMSQf7D6rkM6wy5js1QQ","name":"marlo","subtype":"USER"},"mergedIdentityIds":["sMXMSQf7D6rkM6wy5js1QQ"],"paid":"0","payoutAddresses":{}},"cred":[2.0389715564573686e-34,2.0389715564573686e-34,2.0389715564573686e-34,2.0389715564573686e-34],"totalCred":8.155886225829474e-34},{"account":{"active":false,"allocationHistory":[],"balance":"0","identity":{"address":"N\u0000sourcecred\u0000core\u0000IDENTITY\u0000QioVwSzohpxaCMpgb1yjVQ\u0000","aliases":[{"address":"N\u0000sourcecred\u0000discord\u0000MEMBER\u0000user\u0000345943681695744001\u0000","description":"discord/neverclame#1911"}],"id":"QioVwSzohpxaCMpgb1yjVQ","name":"neverclame","subtype":"USER"},"mergedIdentityIds":["QioVwSzohpxaCMpgb1yjVQ"],"paid":"0","payoutAddresses":{}},"cred":[2.0389715564573686e-34,2.0389715564573686e-34,2.0389715564573686e-34,2.0389715564573686e-34],"totalCred":8.155886225829474e-34},{"account":{"active":false,"allocationHistory":[],"balance":"0","identity":{"address":"N\u0000sourcecred\u0000core\u0000IDENTITY\u00006K8DQxsApDrEALrgKVk3Qg\u0000","aliases":[{"address":"N\u0000sourcecred\u0000discord\u0000MEMBER\u0000user\u0000346495966603640833\u0000","description":"discord/Dae#3193"}],"id":"6K8DQxsApDrEALrgKVk3Qg","name":"Dae","subtype":"USER"},"mergedIdentityIds":["6K8DQxsApDrEALrgKVk3Qg"],"paid":"0","payoutAddresses":{}},"cred":[2.0389715564573686e-34,2.0389715564573686e-34,2.0389715564573686e-34,2.0389715564573686e-34],"totalCred":8.155886225829474e-34},{"account":{"active":false,"allocationHistory":[],"balance":"0","identity":{"address":"N\u0000sourcecred\u0000core\u0000IDENTITY\u0000KhYPXag5Y1aWU9fDNsWOSw\u0000","aliases":[{"address":"N\u0000sourcecred\u0000discord\u0000MEMBER\u0000user\u0000362689616098361346\u0000","description":"discord/Andrew_T#1001"}],"id":"KhYPXag5Y1aWU9fDNsWOSw","name":"Andrew-T","subtype":"USER"},"mergedIdentityIds":["KhYPXag5Y1aWU9fDNsWOSw"],"paid":"0","payoutAddresses":{}},"cred":[2.0389715564573686e-34,2.0389715564573686e-34,2.0389715564573686e-34,2.0389715564573686e-34],"totalCred":8.155886225829474e-34},{"account":{"active":false,"allocationHistory":[],"balance":"0","identity":{"address":"N\u0000sourcecred\u0000core\u0000IDENTITY\u0000KPvwb4jg3YoCV9Rn8yZkPQ\u0000","aliases":[{"address":"N\u0000sourcecred\u0000discord\u0000MEMBER\u0000user\u0000372911134900092938\u0000","description":"discord/Big Papi#2308"}],"id":"KPvwb4jg3YoCV9Rn8yZkPQ","name":"Big-Papi","subtype":"USER"},"mergedIdentityIds":["KPvwb4jg3YoCV9Rn8yZkPQ"],"paid":"0","payoutAddresses":{}},"cred":[2.0389715564573686e-34,2.0389715564573686e-34,2.0389715564573686e-34,2.0389715564573686e-34],"totalCred":8.155886225829474e-34},{"account":{"active":false,"allocationHistory":[],"balance":"0","identity":{"address":"N\u0000sourcecred\u0000core\u0000IDENTITY\u0000kiwpwUeSK2lHWUJ655bgjQ\u0000","aliases":[{"address":"N\u0000sourcecred\u0000discord\u0000MEMBER\u0000user\u0000375961688090083328\u0000","description":"discord/AliensAnonymous69#3043"}],"id":"kiwpwUeSK2lHWUJ655bgjQ","name":"AliensAnonymous69","subtype":"USER"},"mergedIdentityIds":["kiwpwUeSK2lHWUJ655bgjQ"],"paid":"0","payoutAddresses":{}},"cred":[2.0389715564573686e-34,2.0389715564573686e-34,2.0389715564573686e-34,2.0389715564573686e-34],"totalCred":8.155886225829474e-34},{"account":{"active":false,"allocationHistory":[],"balance":"0","identity":{"address":"N\u0000sourcecred\u0000core\u0000IDENTITY\u0000VEECnhDj9uBtDX0Wwx5X1w\u0000","aliases":[{"address":"N\u0000sourcecred\u0000discord\u0000MEMBER\u0000user\u0000383445328763813888\u0000","description":"discord/Tangle#0007"}],"id":"VEECnhDj9uBtDX0Wwx5X1w","name":"Tangle","subtype":"USER"},"mergedIdentityIds":["VEECnhDj9uBtDX0Wwx5X1w"],"paid":"0","payoutAddresses":{}},"cred":[2.0389715564573686e-34,2.0389715564573686e-34,2.0389715564573686e-34,2.0389715564573686e-34],"totalCred":8.155886225829474e-34},{"account":{"active":false,"allocationHistory":[],"balance":"0","identity":{"address":"N\u0000sourcecred\u0000core\u0000IDENTITY\u0000I3jbLQ2q3HMyX4Vf8O3QrQ\u0000","aliases":[{"address":"N\u0000sourcecred\u0000discord\u0000MEMBER\u0000user\u0000391912256574849034\u0000","description":"discord/FullNode Meditator#4972"}],"id":"I3jbLQ2q3HMyX4Vf8O3QrQ","name":"FullNode-Meditator","subtype":"USER"},"mergedIdentityIds":["I3jbLQ2q3HMyX4Vf8O3QrQ"],"paid":"0","payoutAddresses":{}},"cred":[2.0389715564573686e-34,2.0389715564573686e-34,2.0389715564573686e-34,2.0389715564573686e-34],"totalCred":8.155886225829474e-34},{"account":{"active":false,"allocationHistory":[],"balance":"0","identity":{"address":"N\u0000sourcecred\u0000core\u0000IDENTITY\u0000dVGvZE9iNsDJ3EhVe5J2fQ\u0000","aliases":[{"address":"N\u0000sourcecred\u0000discord\u0000MEMBER\u0000user\u0000394976051778027521\u0000","description":"discord/Slick-&#x262F;-Rick#7936"}],"id":"dVGvZE9iNsDJ3EhVe5J2fQ","name":"Slick---Rick","subtype":"USER"},"mergedIdentityIds":["dVGvZE9iNsDJ3EhVe5J2fQ"],"paid":"0","payoutAddresses":{}},"cred":[2.0389715564573686e-34,2.0389715564573686e-34,2.0389715564573686e-34,2.0389715564573686e-34],"totalCred":8.155886225829474e-34},{"account":{"active":false,"allocationHistory":[],"balance":"0","identity":{"address":"N\u0000sourcecred\u0000core\u0000IDENTITY\u0000Q98lt8RGfrvfvxYNsbQ0fg\u0000","aliases":[{"address":"N\u0000sourcecred\u0000discord\u0000MEMBER\u0000user\u0000397044762240090152\u0000","description":"discord/AZ#1337"}],"id":"Q98lt8RGfrvfvxYNsbQ0fg","name":"AZ","subtype":"USER"},"mergedIdentityIds":["Q98lt8RGfrvfvxYNsbQ0fg"],"paid":"0","payoutAddresses":{}},"cred":[2.0389715564573686e-34,2.0389715564573686e-34,2.0389715564573686e-34,2.0389715564573686e-34],"totalCred":8.155886225829474e-34},{"account":{"active":false,"allocationHistory":[],"balance":"0","identity":{"address":"N\u0000sourcecred\u0000core\u0000IDENTITY\u0000BxYvQmJsdAndhK7dznJwzA\u0000","aliases":[{"address":"N\u0000sourcecred\u0000discord\u0000MEMBER\u0000user\u0000399892650666229770\u0000","description":"discord/ManuAlzuru | &#x1F951;#5047"}],"id":"BxYvQmJsdAndhK7dznJwzA","name":"ManuAlzuru-----","subtype":"USER"},"mergedIdentityIds":["BxYvQmJsdAndhK7dznJwzA"],"paid":"0","payoutAddresses":{}},"cred":[2.0389715564573686e-34,2.0389715564573686e-34,2.0389715564573686e-34,2.0389715564573686e-34],"totalCred":8.155886225829474e-34},{"account":{"active":false,"allocationHistory":[],"balance":"0","identity":{"address":"N\u0000sourcecred\u0000core\u0000IDENTITY\u00005d9RvvlOHpWHy5NEQheHzQ\u0000","aliases":[{"address":"N\u0000sourcecred\u0000discord\u0000MEMBER\u0000user\u0000403029420203573250\u0000","description":"discord/bfresh#0001"}],"id":"5d9RvvlOHpWHy5NEQheHzQ","name":"bfresh","subtype":"USER"},"mergedIdentityIds":["5d9RvvlOHpWHy5NEQheHzQ"],"paid":"0","payoutAddresses":{}},"cred":[0.0003379194745225351,0.003041277372534702,0.03007481823931729,0.2977072427652845],"totalCred":0.331161257851659},{"account":{"active":false,"allocationHistory":[],"balance":"0","identity":{"address":"N\u0000sourcecred\u0000core\u0000IDENTITY\u0000aRMoHvHLwJmVWWxWcoo1oA\u0000","aliases":[{"address":"N\u0000sourcecred\u0000discord\u0000MEMBER\u0000user\u0000404491788460752909\u0000","description":"discord/Pratik#7777"}],"id":"aRMoHvHLwJmVWWxWcoo1oA","name":"Pratik","subtype":"USER"},"mergedIdentityIds":["aRMoHvHLwJmVWWxWcoo1oA"],"paid":"0","payoutAddresses":{}},"cred":[0.2284613187818037,0.023079518482785836,0.002333882502610429,0.00025932061737642874],"totalCred":0.2541340403845764},{"account":{"active":false,"allocationHistory":[],"balance":"0","identity":{"address":"N\u0000sourcecred\u0000core\u0000IDENTITY\u0000kKolagyJK4FJg653nGNKww\u0000","aliases":[{"address":"N\u0000sourcecred\u0000discord\u0000MEMBER\u0000user\u0000408039049928900608\u0000","description":"discord/wloka#3263"}],"id":"kKolagyJK4FJg653nGNKww","name":"wloka","subtype":"USER"},"mergedIdentityIds":["kKolagyJK4FJg653nGNKww"],"paid":"0","payoutAddresses":{}},"cred":[2.0389715564573686e-34,2.0389715564573686e-34,2.0389715564573686e-34,2.0389715564573686e-34],"totalCred":8.155886225829474e-34},{"account":{"active":false,"allocationHistory":[],"balance":"0","identity":{"address":"N\u0000sourcecred\u0000core\u0000IDENTITY\u0000kHwRyN7Q7GaA8DrI27OY4w\u0000","aliases":[{"address":"N\u0000sourcecred\u0000discord\u0000MEMBER\u0000user\u0000449981975931912202\u0000","description":"discord/Blump#9066"}],"id":"kHwRyN7Q7GaA8DrI27OY4w","name":"Blump","subtype":"USER"},"mergedIdentityIds":["kHwRyN7Q7GaA8DrI27OY4w"],"paid":"0","payoutAddresses":{}},"cred":[2.0389715564573686e-34,2.0389715564573686e-34,2.0389715564573686e-34,2.0389715564573686e-34],"totalCred":8.155886225829474e-34},{"account":{"active":false,"allocationHistory":[],"balance":"0","identity":{"address":"N\u0000sourcecred\u0000core\u0000IDENTITY\u0000jaqomWvAZjmpgPZZOJ8AeA\u0000","aliases":[{"address":"N\u0000sourcecred\u0000discord\u0000MEMBER\u0000user\u0000455356864767590411\u0000","description":"discord/jnbtc#1636"}],"id":"jaqomWvAZjmpgPZZOJ8AeA","name":"jnbtc","subtype":"USER"},"mergedIdentityIds":["jaqomWvAZjmpgPZZOJ8AeA"],"paid":"0","payoutAddresses":{}},"cred":[2.0389715564573686e-34,2.0389715564573686e-34,2.0389715564573686e-34,2.0389715564573686e-34],"totalCred":8.155886225829474e-34},{"account":{"active":false,"allocationHistory":[],"balance":"0","identity":{"address":"N\u0000sourcecred\u0000core\u0000IDENTITY\u0000uA5mpP6LKkrXSLO2YtOTKg\u0000","aliases":[{"address":"N\u0000sourcecred\u0000discord\u0000MEMBER\u0000user\u0000457451544120524813\u0000","description":"discord/KingOfDenmark#0302"}],"id":"uA5mpP6LKkrXSLO2YtOTKg","name":"KingOfDenmark","subtype":"USER"},"mergedIdentityIds":["uA5mpP6LKkrXSLO2YtOTKg"],"paid":"0","payoutAddresses":{}},"cred":[0.002119307940658123,0.01907379874295488,0.18861852826649766,1.8671115176983433],"totalCred":2.0769231526484537},{"account":{"active":false,"allocationHistory":[],"balance":"0","identity":{"address":"N\u0000sourcecred\u0000core\u0000IDENTITY\u0000JAHzE4xra2eNbcerBTqFGw\u0000","aliases":[{"address":"N\u0000sourcecred\u0000discord\u0000MEMBER\u0000user\u0000479621838780235778\u0000","description":"discord/orionxiaohan#1807"}],"id":"JAHzE4xra2eNbcerBTqFGw","name":"orionxiaohan","subtype":"USER"},"mergedIdentityIds":["JAHzE4xra2eNbcerBTqFGw"],"paid":"0","payoutAddresses":{}},"cred":[0.057115329695450925,0.005769879620696459,0.0005834706256526073,0.00006483015434410718],"totalCred":0.0635335100961441},{"account":{"active":false,"allocationHistory":[],"balance":"0","identity":{"address":"N\u0000sourcecred\u0000core\u0000IDENTITY\u0000g8wAQwCGSKMydWq10uLXMg\u0000","aliases":[{"address":"N\u0000sourcecred\u0000discord\u0000MEMBER\u0000user\u0000481572613047451669\u0000","description":"discord/sudo#0002"}],"id":"g8wAQwCGSKMydWq10uLXMg","name":"sudo","subtype":"USER"},"mergedIdentityIds":["g8wAQwCGSKMydWq10uLXMg"],"paid":"0","payoutAddresses":{}},"cred":[2.0389715564573686e-34,2.0389715564573686e-34,2.0389715564573686e-34,2.0389715564573686e-34],"totalCred":8.155886225829474e-34},{"account":{"active":false,"allocationHistory":[],"balance":"0","identity":{"address":"N\u0000sourcecred\u0000core\u0000IDENTITY\u00005tWnMGyDv3pWxAoOQi60Tg\u0000","aliases":[{"address":"N\u0000sourcecred\u0000discord\u0000MEMBER\u0000user\u0000494908382889639977\u0000","description":"discord/andrew.i#0298"}],"id":"5tWnMGyDv3pWxAoOQi60Tg","name":"andrew-i","subtype":"USER"},"mergedIdentityIds":["5tWnMGyDv3pWxAoOQi60Tg"],"paid":"0","payoutAddresses":{}},"cred":[0.008282474731377752,0.07454214563154166,0.7371396623503568,0.08190434721949558],"totalCred":0.9018686299327717},{"account":{"active":false,"allocationHistory":[],"balance":"0","identity":{"address":"N\u0000sourcecred\u0000core\u0000IDENTITY\u0000rHVUdIx1C416ZkrlcL2vrg\u0000","aliases":[{"address":"N\u0000sourcecred\u0000discord\u0000MEMBER\u0000bot\u0000530145634444115968\u0000","description":"discord/Todo#9724"}],"id":"rHVUdIx1C416ZkrlcL2vrg","name":"Todo","subtype":"BOT"},"mergedIdentityIds":["rHVUdIx1C416ZkrlcL2vrg"],"paid":"0","payoutAddresses":{}},"cred":[2.0389715564573686e-34,2.0389715564573686e-34,2.0389715564573686e-34,2.0389715564573686e-34],"totalCred":8.155886225829474e-34},{"account":{"active":false,"allocationHistory":[],"balance":"0","identity":{"address":"N\u0000sourcecred\u0000core\u0000IDENTITY\u0000VN8W6uWBE5vrOlR5lqeE1w\u0000","aliases":[{"address":"N\u0000sourcecred\u0000discord\u0000MEMBER\u0000user\u0000533053420819578902\u0000","description":"discord/triteanderivative#5738"}],"id":"VN8W6uWBE5vrOlR5lqeE1w","name":"triteanderivative","subtype":"USER"},"mergedIdentityIds":["VN8W6uWBE5vrOlR5lqeE1w"],"paid":"0","payoutAddresses":{}},"cred":[0.32963741613413633,0.9175940862195078,8.846307424753505,1.925629628542809],"totalCred":12.019168555649959},{"account":{"active":false,"allocationHistory":[],"balance":"0","identity":{"address":"N\u0000sourcecred\u0000core\u0000IDENTITY\u0000LJJ1VZNoaYJYtEmgtk4ZgA\u0000","aliases":[{"address":"N\u0000sourcecred\u0000discord\u0000MEMBER\u0000user\u0000583175641139118083\u0000","description":"discord/redicko#3550"}],"id":"LJJ1VZNoaYJYtEmgtk4ZgA","name":"redicko","subtype":"USER"},"mergedIdentityIds":["LJJ1VZNoaYJYtEmgtk4ZgA"],"paid":"0","payoutAddresses":{}},"cred":[2.0389715564573686e-34,2.0389715564573686e-34,2.0389715564573686e-34,2.0389715564573686e-34],"totalCred":8.155886225829474e-34},{"account":{"active":false,"allocationHistory":[],"balance":"0","identity":{"address":"N\u0000sourcecred\u0000core\u0000IDENTITY\u00007zQk7GBu9ADdAI4S14BgOg\u0000","aliases":[{"address":"N\u0000sourcecred\u0000discord\u0000MEMBER\u0000user\u0000598904638409801739\u0000","description":"discord/jamesrt#0629"}],"id":"7zQk7GBu9ADdAI4S14BgOg","name":"jamesrt","subtype":"USER"},"mergedIdentityIds":["7zQk7GBu9ADdAI4S14BgOg"],"paid":"0","payoutAddresses":{}},"cred":[2.0389715564573686e-34,2.0389715564573686e-34,2.0389715564573686e-34,2.0389715564573686e-34],"totalCred":8.155886225829474e-34},{"account":{"active":false,"allocationHistory":[],"balance":"0","identity":{"address":"N\u0000sourcecred\u0000core\u0000IDENTITY\u0000aKGnzXBh4dxyjXEGjPLNWw\u0000","aliases":[{"address":"N\u0000sourcecred\u0000discord\u0000MEMBER\u0000user\u0000600551241965109254\u0000","description":"discord/Bay | zoomermoney#8545"}],"id":"aKGnzXBh4dxyjXEGjPLNWw","name":"Bay---zoomermoney","subtype":"USER"},"mergedIdentityIds":["aKGnzXBh4dxyjXEGjPLNWw"],"paid":"0","payoutAddresses":{}},"cred":[0.0005511190895344658,0.004960075016590424,0.04904963656045852,0.0054499585650371754],"totalCred":0.060010789231620586},{"account":{"active":false,"allocationHistory":[],"balance":"0","identity":{"address":"N\u0000sourcecred\u0000core\u0000IDENTITY\u00004K385Ym2nD4rkGaIxzTr4Q\u0000","aliases":[{"address":"N\u0000sourcecred\u0000discord\u0000MEMBER\u0000user\u0000632230294929408020\u0000","description":"discord/gamgee#1933"}],"id":"4K385Ym2nD4rkGaIxzTr4Q","name":"gamgee","subtype":"USER"},"mergedIdentityIds":["4K385Ym2nD4rkGaIxzTr4Q"],"paid":"0","payoutAddresses":{}},"cred":[2.0389715564573686e-34,2.0389715564573686e-34,2.0389715564573686e-34,2.0389715564573686e-34],"totalCred":8.155886225829474e-34},{"account":{"active":false,"allocationHistory":[],"balance":"0","identity":{"address":"N\u0000sourcecred\u0000core\u0000IDENTITY\u0000r9CdFK9WcBKF0lBMNwym8g\u0000","aliases":[{"address":"N\u0000sourcecred\u0000discord\u0000MEMBER\u0000user\u0000676946869217132544\u0000","description":"discord/DeFiTrader#3014"}],"id":"r9CdFK9WcBKF0lBMNwym8g","name":"DeFiTrader","subtype":"USER"},"mergedIdentityIds":["r9CdFK9WcBKF0lBMNwym8g"],"paid":"0","payoutAddresses":{}},"cred":[0.06232191310208373,0.05180216213993738,0.45569975095019394,0.19955017314887472],"totalCred":0.7693739993410897},{"account":{"active":false,"allocationHistory":[],"balance":"0","identity":{"address":"N\u0000sourcecred\u0000core\u0000IDENTITY\u0000WdPQas3ProqocEeLuQZc4w\u0000","aliases":[{"address":"N\u0000sourcecred\u0000discord\u0000MEMBER\u0000user\u0000686614577604984906\u0000","description":"discord/Toljona#6202"}],"id":"WdPQas3ProqocEeLuQZc4w","name":"Toljona","subtype":"USER"},"mergedIdentityIds":["WdPQas3ProqocEeLuQZc4w"],"paid":"0","payoutAddresses":{}},"cred":[2.0389715564573686e-34,2.0389715564573686e-34,2.0389715564573686e-34,2.0389715564573686e-34],"totalCred":8.155886225829474e-34},{"account":{"active":false,"allocationHistory":[],"balance":"0","identity":{"address":"N\u0000sourcecred\u0000core\u0000IDENTITY\u0000SwW5jym1rmSLk7hAHxcAjA\u0000","aliases":[{"address":"N\u0000sourcecred\u0000discord\u0000MEMBER\u0000bot\u0000712620191045124126\u0000","description":"discord/Orli PM#5036"}],"id":"SwW5jym1rmSLk7hAHxcAjA","name":"Orli-PM","subtype":"BOT"},"mergedIdentityIds":["SwW5jym1rmSLk7hAHxcAjA"],"paid":"0","payoutAddresses":{}},"cred":[0.03103776260500409,0.27933977183251874,2.76235854872133,0.3069288983447754],"totalCred":3.3796649815036286},{"account":{"active":false,"allocationHistory":[],"balance":"0","identity":{"address":"N\u0000sourcecred\u0000core\u0000IDENTITY\u0000wg8qhyYLYKgPmmbpMFMung\u0000","aliases":[{"address":"N\u0000sourcecred\u0000discord\u0000MEMBER\u0000user\u0000721781903979708506\u0000","description":"discord/0xCart#4039"}],"id":"wg8qhyYLYKgPmmbpMFMung","name":"0xCart","subtype":"USER"},"mergedIdentityIds":["wg8qhyYLYKgPmmbpMFMung"],"paid":"0","payoutAddresses":{}},"cred":[2.0389715564573686e-34,2.0389715564573686e-34,2.0389715564573686e-34,2.0389715564573686e-34],"totalCred":8.155886225829474e-34},{"account":{"active":false,"allocationHistory":[],"balance":"0","identity":{"address":"N\u0000sourcecred\u0000core\u0000IDENTITY\u0000oPF7PLBo3Z1yzSQgBg53FQ\u0000","aliases":[{"address":"N\u0000sourcecred\u0000discord\u0000MEMBER\u0000user\u0000731804595226935456\u0000","description":"discord/Mariodigital#9440"}],"id":"oPF7PLBo3Z1yzSQgBg53FQ","name":"Mariodigital","subtype":"USER"},"mergedIdentityIds":["oPF7PLBo3Z1yzSQgBg53FQ"],"paid":"0","payoutAddresses":{}},"cred":[2.0389715564573686e-34,2.0389715564573686e-34,2.0389715564573686e-34,2.0389715564573686e-34],"totalCred":8.155886225829474e-34},{"account":{"active":false,"allocationHistory":[],"balance":"0","identity":{"address":"N\u0000sourcecred\u0000core\u0000IDENTITY\u0000wbW12JfyfBqLo5NVoXVmBA\u0000","aliases":[{"address":"N\u0000sourcecred\u0000discord\u0000MEMBER\u0000user\u0000740513815665311836\u0000","description":"discord/Gibbo#0183"}],"id":"wbW12JfyfBqLo5NVoXVmBA","name":"Gibbo","subtype":"USER"},"mergedIdentityIds":["wbW12JfyfBqLo5NVoXVmBA"],"paid":"0","payoutAddresses":{}},"cred":[2.0389715564573686e-34,2.0389715564573686e-34,2.0389715564573686e-34,2.0389715564573686e-34],"totalCred":8.155886225829474e-34},{"account":{"active":false,"allocationHistory":[],"balance":"0","identity":{"address":"N\u0000sourcecred\u0000core\u0000IDENTITY\u0000y71GX6bxOSaq0xpkWzzBrA\u0000","aliases":[{"address":"N\u0000sourcecred\u0000discord\u0000MEMBER\u0000user\u0000749838412911083541\u0000","description":"discord/SP#6842"}],"id":"y71GX6bxOSaq0xpkWzzBrA","name":"SP","subtype":"USER"},"mergedIdentityIds":["y71GX6bxOSaq0xpkWzzBrA"],"paid":"0","payoutAddresses":{}},"cred":[2.0389715564573686e-34,2.0389715564573686e-34,2.0389715564573686e-34,2.0389715564573686e-34],"totalCred":8.155886225829474e-34},{"account":{"active":false,"allocationHistory":[],"balance":"0","identity":{"address":"N\u0000sourcecred\u0000core\u0000IDENTITY\u0000ofDGuzbne0Gl4RVQnlkcoQ\u0000","aliases":[{"address":"N\u0000sourcecred\u0000discord\u0000MEMBER\u0000user\u0000754473088111869994\u0000","description":"discord/LS00#2306"}],"id":"ofDGuzbne0Gl4RVQnlkcoQ","name":"LS00","subtype":"USER"},"mergedIdentityIds":["ofDGuzbne0Gl4RVQnlkcoQ"],"paid":"0","payoutAddresses":{}},"cred":[2.0389715564573686e-34,2.0389715564573686e-34,2.0389715564573686e-34,2.0389715564573686e-34],"totalCred":8.155886225829474e-34},{"account":{"active":false,"allocationHistory":[],"balance":"0","identity":{"address":"N\u0000sourcecred\u0000core\u0000IDENTITY\u0000keOLiQWEKjiEdzBlxBFdIg\u0000","aliases":[{"address":"N\u0000sourcecred\u0000discord\u0000MEMBER\u0000user\u0000754789399677370399\u0000","description":"discord/shpa97#8457"}],"id":"keOLiQWEKjiEdzBlxBFdIg","name":"shpa97","subtype":"USER"},"mergedIdentityIds":["keOLiQWEKjiEdzBlxBFdIg"],"paid":"0","payoutAddresses":{}},"cred":[2.0389715564573686e-34,2.0389715564573686e-34,2.0389715564573686e-34,2.0389715564573686e-34],"totalCred":8.155886225829474e-34},{"account":{"active":false,"allocationHistory":[],"balance":"0","identity":{"address":"N\u0000sourcecred\u0000core\u0000IDENTITY\u0000sBaocAHxwJDqKoqesxlDmA\u0000","aliases":[{"address":"N\u0000sourcecred\u0000discord\u0000MEMBER\u0000user\u0000756464490677272606\u0000","description":"discord/Aakash Athawasya#9942"}],"id":"sBaocAHxwJDqKoqesxlDmA","name":"Aakash-Athawasya","subtype":"USER"},"mergedIdentityIds":["sBaocAHxwJDqKoqesxlDmA"],"paid":"0","payoutAddresses":{}},"cred":[2.0389715564573686e-34,2.0389715564573686e-34,2.0389715564573686e-34,2.0389715564573686e-34],"totalCred":8.155886225829474e-34},{"account":{"active":false,"allocationHistory":[],"balance":"0","identity":{"address":"N\u0000sourcecred\u0000core\u0000IDENTITY\u0000oZkYRRGLLcg51amLqOOQAg\u0000","aliases":[{"address":"N\u0000sourcecred\u0000discord\u0000MEMBER\u0000user\u0000766693440368410695\u0000","description":"discord/adamalamode#6893"}],"id":"oZkYRRGLLcg51amLqOOQAg","name":"adamalamode","subtype":"USER"},"mergedIdentityIds":["oZkYRRGLLcg51amLqOOQAg"],"paid":"0","payoutAddresses":{}},"cred":[0.23302672308007233,0.0634430203837428,0.4014035916279861,0.04460039452562364],"totalCred":0.7424737296174249},{"account":{"active":false,"allocationHistory":[],"balance":"0","identity":{"address":"N\u0000sourcecred\u0000core\u0000IDENTITY\u0000a8l6G7obi0DULg8ebC9jNg\u0000","aliases":[{"address":"N\u0000sourcecred\u0000discord\u0000MEMBER\u0000user\u0000781746890962108426\u0000","description":"discord/Kyloe#0448"}],"id":"a8l6G7obi0DULg8ebC9jNg","name":"Kyloe","subtype":"USER"},"mergedIdentityIds":["a8l6G7obi0DULg8ebC9jNg"],"paid":"0","payoutAddresses":{}},"cred":[2.0389715564573686e-34,2.0389715564573686e-34,2.0389715564573686e-34,2.0389715564573686e-34],"totalCred":8.155886225829474e-34},{"account":{"active":false,"allocationHistory":[],"balance":"0","identity":{"address":"N\u0000sourcecred\u0000core\u0000IDENTITY\u0000NiJuRxHZbJGRFg0VpPbUBw\u0000","aliases":[{"address":"N\u0000sourcecred\u0000discord\u0000MEMBER\u0000user\u0000789883455252725772\u0000","description":"discord/thewolfofrapa#0716"}],"id":"NiJuRxHZbJGRFg0VpPbUBw","name":"thewolfofrapa","subtype":"USER"},"mergedIdentityIds":["NiJuRxHZbJGRFg0VpPbUBw"],"paid":"0","payoutAddresses":{}},"cred":[2.0389715564573686e-34,2.0389715564573686e-34,2.0389715564573686e-34,2.0389715564573686e-34],"totalCred":8.155886225829474e-34},{"account":{"active":false,"allocationHistory":[],"balance":"0","identity":{"address":"N\u0000sourcecred\u0000core\u0000IDENTITY\u0000yMuEaEZm035lS5AN2im95g\u0000","aliases":[{"address":"N\u0000sourcecred\u0000discord\u0000MEMBER\u0000user\u0000794965298477924392\u0000","description":"discord/reedrick#7224"}],"id":"yMuEaEZm035lS5AN2im95g","name":"reedrick","subtype":"USER"},"mergedIdentityIds":["yMuEaEZm035lS5AN2im95g"],"paid":"0","payoutAddresses":{}},"cred":[2.0389715564573686e-34,2.0389715564573686e-34,2.0389715564573686e-34,2.0389715564573686e-34],"totalCred":8.155886225829474e-34},{"account":{"active":false,"allocationHistory":[],"balance":"0","identity":{"address":"N\u0000sourcecred\u0000core\u0000IDENTITY\u00003BTlaZO6jvW0tN80b0LXwg\u0000","aliases":[{"address":"N\u0000sourcecred\u0000discord\u0000MEMBER\u0000user\u0000800213182115217438\u0000","description":"discord/Max0x#5092"}],"id":"3BTlaZO6jvW0tN80b0LXwg","name":"Max0x","subtype":"USER"},"mergedIdentityIds":["3BTlaZO6jvW0tN80b0LXwg"],"paid":"0","payoutAddresses":{}},"cred":[0.02031145846803046,0.18280287803717418,1.8077184723173216,0.20085751161867926],"totalCred":2.211690320441206},{"account":{"active":false,"allocationHistory":[],"balance":"0","identity":{"address":"N\u0000sourcecred\u0000core\u0000IDENTITY\u0000atLYlTmma9TDdAj7LVW90g\u0000","aliases":[{"address":"N\u0000sourcecred\u0000discord\u0000MEMBER\u0000user\u0000803455455912525834\u0000","description":"discord/CPTNskeletor#0379"}],"id":"atLYlTmma9TDdAj7LVW90g","name":"CPTNskeletor","subtype":"USER"},"mergedIdentityIds":["atLYlTmma9TDdAj7LVW90g"],"paid":"0","payoutAddresses":{}},"cred":[0.0048327056508265,0.043494297430765994,0.43011040844975873,0.04779003678094073],"totalCred":0.526227448312292},{"account":{"active":false,"allocationHistory":[],"balance":"0","identity":{"address":"N\u0000sourcecred\u0000core\u0000IDENTITY\u0000WFmdVNq8Mmur2BLj3owMDQ\u0000","aliases":[{"address":"N\u0000sourcecred\u0000discord\u0000MEMBER\u0000user\u0000810849610347053077\u0000","description":"discord/christianocripto#7194"}],"id":"WFmdVNq8Mmur2BLj3owMDQ","name":"christianocripto","subtype":"USER"},"mergedIdentityIds":["WFmdVNq8Mmur2BLj3owMDQ"],"paid":"0","payoutAddresses":{}},"cred":[0.0005240015132173398,0.004716003953216322,0.04663613417974058,0.0051817831480660765],"totalCred":0.057057922794240316},{"account":{"active":false,"allocationHistory":[],"balance":"0","identity":{"address":"N\u0000sourcecred\u0000core\u0000IDENTITY\u0000E6adTgpdIBkB9vgdSXQRtw\u0000","aliases":[{"address":"N\u0000sourcecred\u0000discord\u0000MEMBER\u0000user\u0000811084579367682089\u0000","description":"discord/zaza#6743"}],"id":"E6adTgpdIBkB9vgdSXQRtw","name":"zaza","subtype":"USER"},"mergedIdentityIds":["E6adTgpdIBkB9vgdSXQRtw"],"paid":"0","payoutAddresses":{}},"cred":[2.0389715564573686e-34,2.0389715564573686e-34,2.0389715564573686e-34,2.0389715564573686e-34],"totalCred":8.155886225829474e-34},{"account":{"active":false,"allocationHistory":[],"balance":"0","identity":{"address":"N\u0000sourcecred\u0000core\u0000IDENTITY\u0000D7YbmkLN8nPEBAAnLSX0hA\u0000","aliases":[{"address":"N\u0000sourcecred\u0000discord\u0000MEMBER\u0000user\u0000814184476891414558\u0000","description":"discord/Markio#1150"}],"id":"D7YbmkLN8nPEBAAnLSX0hA","name":"Markio","subtype":"USER"},"mergedIdentityIds":["D7YbmkLN8nPEBAAnLSX0hA"],"paid":"0","payoutAddresses":{}},"cred":[0.01813853608729261,0.16324663023875113,1.6143282660865534,0.17936977704870607],"totalCred":1.9750832094613033},{"account":{"active":false,"allocationHistory":[],"balance":"0","identity":{"address":"N\u0000sourcecred\u0000core\u0000IDENTITY\u0000Tnoez8kS9ij7Yc8HJJJRxA\u0000","aliases":[{"address":"N\u0000sourcecred\u0000discord\u0000MEMBER\u0000user\u0000815254053586993183\u0000","description":"discord/NotMissing#4805"}],"id":"Tnoez8kS9ij7Yc8HJJJRxA","name":"NotMissing","subtype":"USER"},"mergedIdentityIds":["Tnoez8kS9ij7Yc8HJJJRxA"],"paid":"0","payoutAddresses":{}},"cred":[0.0002620007566086699,0.002358001976608161,0.02331806708987029,0.0025908915740330382],"totalCred":0.028528961397120158},{"account":{"active":false,"allocationHistory":[],"balance":"0","identity":{"address":"N\u0000sourcecred\u0000core\u0000IDENTITY\u0000iVUjv2EXVwubqo0pe0NnXw\u0000","aliases":[{"address":"N\u0000sourcecred\u0000discord\u0000MEMBER\u0000user\u0000822938057451765833\u0000","description":"discord/thedefisage#3252"}],"id":"iVUjv2EXVwubqo0pe0NnXw","name":"thedefisage","subtype":"USER"},"mergedIdentityIds":["iVUjv2EXVwubqo0pe0NnXw"],"paid":"0","payoutAddresses":{}},"cred":[0.057329540983840514,0.007663757940972327,0.019308043775384014,0.18541676411314892],"totalCred":0.2697181068133458},{"account":{"active":false,"allocationHistory":[],"balance":"0","identity":{"address":"N\u0000sourcecred\u0000core\u0000IDENTITY\u0000yY9bmoZVpCYuPGL1o81qTg\u0000","aliases":[{"address":"N\u0000sourcecred\u0000discord\u0000MEMBER\u0000user\u0000824477079226679306\u0000","description":"discord/av1dan#8548"}],"id":"yY9bmoZVpCYuPGL1o81qTg","name":"av1dan","subtype":"USER"},"mergedIdentityIds":["yY9bmoZVpCYuPGL1o81qTg"],"paid":"0","payoutAddresses":{}},"cred":[2.0389715564573686e-34,2.0389715564573686e-34,2.0389715564573686e-34,2.0389715564573686e-34],"totalCred":8.155886225829474e-34},{"account":{"active":false,"allocationHistory":[],"balance":"0","identity":{"address":"N\u0000sourcecred\u0000core\u0000IDENTITY\u0000EZoRbQG2tdKJSGl8brLETg\u0000","aliases":[{"address":"N\u0000sourcecred\u0000discord\u0000MEMBER\u0000user\u0000859625604454547486\u0000","description":"discord/CryptoGucci#3381"}],"id":"EZoRbQG2tdKJSGl8brLETg","name":"CryptoGucci","subtype":"USER"},"mergedIdentityIds":["EZoRbQG2tdKJSGl8brLETg"],"paid":"0","payoutAddresses":{}},"cred":[0.008414392637607182,0.07572957008602899,0.05052709743579037,0.005614119037167608],"totalCred":0.14028517919659414},{"account":{"active":true,"allocationHistory":[],"balance":"0","identity":{"address":"N\u0000sourcecred\u0000core\u0000IDENTITY\u0000cq4g55FvgqltoJJzt7epLw\u0000","aliases":[],"id":"cq4g55FvgqltoJJzt7epLw","name":"SourceCred","subtype":"PROJECT"},"mergedIdentityIds":["cq4g55FvgqltoJJzt7epLw"],"paid":"0","payoutAddresses":{}},"cred":[2.0389715564573686e-34,2.0389715564573686e-34,2.0389715564573686e-34,2.0389715564573686e-34],"totalCred":8.155886225829474e-34}],"intervals":[{"endTimeMs":1625356800000,"startTimeMs":1624752000000},{"endTimeMs":1625961600000,"startTimeMs":1625356800000},{"endTimeMs":1626566400000,"startTimeMs":1625961600000},{"endTimeMs":1627171200000,"startTimeMs":1626566400000}],"unclaimedAliases":[]}