{"action":{"identity":{"address":"N\u0000sourcecred\u0000core\u0000IDENTITY\u0000NJwYHRQl1nrPv3zCQmI89w\u0000","aliases":[],"id":"NJwYHRQl1nrPv3zCQmI89w","name":"Justin","subtype":"USER"},"type":"CREATE_IDENTITY"},"ledgerTimestamp":1626654287001,"uuid":"4nbXT7SjmiEPIEDXW0FjAQ","version":"1"}
{"action":{"alias":{"address":"N\u0000sourcecred\u0000discord\u0000MEMBER\u0000user\u0000104190369457016832\u0000","description":"discord/Justin#8531"},"identityId":"NJwYHRQl1nrPv3zCQmI89w","type":"ADD_ALIAS"},"ledgerTimestamp":1626654287002,"uuid":"aXWBMa0jpJ2km5orLw6tgA","version":"1"}
{"action":{"identity":{"address":"N\u0000sourcecred\u0000core\u0000IDENTITY\u00009oaNlEu8zIZWqbwVR5Wg6A\u0000","aliases":[],"id":"9oaNlEu8zIZWqbwVR5Wg6A","name":"cryptocrpt","subtype":"USER"},"type":"CREATE_IDENTITY"},"ledgerTimestamp":1626654287002,"uuid":"d1vNjEYRqKTb5yl0ram1YQ","version":"1"}
{"action":{"alias":{"address":"N\u0000sourcecred\u0000discord\u0000MEMBER\u0000user\u0000137289101983350784\u0000","description":"discord/cryptocrpt#5239"},"identityId":"9oaNlEu8zIZWqbwVR5Wg6A","type":"ADD_ALIAS"},"ledgerTimestamp":1626654287002,"uuid":"LQ8twHpxcwwzh9z5bXh4kg","version":"1"}
{"action":{"identity":{"address":"N\u0000sourcecred\u0000core\u0000IDENTITY\u0000KOQ7wyBu0yJq2gMOeVAetQ\u0000","aliases":[],"id":"KOQ7wyBu0yJq2gMOeVAetQ","name":"Dheeraj","subtype":"USER"},"type":"CREATE_IDENTITY"},"ledgerTimestamp":1626654287003,"uuid":"87DyAdoOrUDcbw30kMD4cQ","version":"1"}
{"action":{"alias":{"address":"N\u0000sourcecred\u0000discord\u0000MEMBER\u0000user\u0000142538186109747200\u0000","description":"discord/Dheeraj#6128"},"identityId":"KOQ7wyBu0yJq2gMOeVAetQ","type":"ADD_ALIAS"},"ledgerTimestamp":1626654287003,"uuid":"LsPJngbqJS7Nd4sxaUj4sg","version":"1"}
{"action":{"identity":{"address":"N\u0000sourcecred\u0000core\u0000IDENTITY\u0000b4lTOhgExJZmIkmFbg0JeQ\u0000","aliases":[],"id":"b4lTOhgExJZmIkmFbg0JeQ","name":"Target-Sir","subtype":"USER"},"type":"CREATE_IDENTITY"},"ledgerTimestamp":1626654287003,"uuid":"gOeHbxPrAybO7JlfXH8xhQ","version":"1"}
{"action":{"alias":{"address":"N\u0000sourcecred\u0000discord\u0000MEMBER\u0000user\u0000182163295262867458\u0000","description":"discord/Target_Sir#4116"},"identityId":"b4lTOhgExJZmIkmFbg0JeQ","type":"ADD_ALIAS"},"ledgerTimestamp":1626654287004,"uuid":"wFMOvY1eW5iaXQHpLnWI5Q","version":"1"}
{"action":{"identity":{"address":"N\u0000sourcecred\u0000core\u0000IDENTITY\u0000RjLelvUvkTrrEmqMpoJN9Q\u0000","aliases":[],"id":"RjLelvUvkTrrEmqMpoJN9Q","name":"magicturtle","subtype":"USER"},"type":"CREATE_IDENTITY"},"ledgerTimestamp":1626654287004,"uuid":"kEMz61SBFAs7XQasBjLNMg","version":"1"}
{"action":{"alias":{"address":"N\u0000sourcecred\u0000discord\u0000MEMBER\u0000user\u0000209315927005724672\u0000","description":"discord/magicturtle#3057"},"identityId":"RjLelvUvkTrrEmqMpoJN9Q","type":"ADD_ALIAS"},"ledgerTimestamp":1626654287004,"uuid":"zbCVTLzlKAKP0IPJfoLfYg","version":"1"}
{"action":{"identity":{"address":"N\u0000sourcecred\u0000core\u0000IDENTITY\u0000819ByqtYQTxBEv3rF57vtw\u0000","aliases":[],"id":"819ByqtYQTxBEv3rF57vtw","name":"atakan-IntroToDefi","subtype":"USER"},"type":"CREATE_IDENTITY"},"ledgerTimestamp":1626654287005,"uuid":"C2dWEr3yIjTk52gy7TbneQ","version":"1"}
{"action":{"alias":{"address":"N\u0000sourcecred\u0000discord\u0000MEMBER\u0000user\u0000228250011115323392\u0000","description":"discord/atakan-IntroToDefi#7962"},"identityId":"819ByqtYQTxBEv3rF57vtw","type":"ADD_ALIAS"},"ledgerTimestamp":1626654287005,"uuid":"OW6XBu89iPDgePEqSV7nlA","version":"1"}
{"action":{"identity":{"address":"N\u0000sourcecred\u0000core\u0000IDENTITY\u000092tlK4PAApeO1CLgxKt6lw\u0000","aliases":[],"id":"92tlK4PAApeO1CLgxKt6lw","name":"bigba-daboom","subtype":"USER"},"type":"CREATE_IDENTITY"},"ledgerTimestamp":1626654287005,"uuid":"cGR5dA7ap2jAqbarWltN2w","version":"1"}
{"action":{"alias":{"address":"N\u0000sourcecred\u0000discord\u0000MEMBER\u0000user\u0000242510303248646146\u0000","description":"discord/bigba_daboom#2008"},"identityId":"92tlK4PAApeO1CLgxKt6lw","type":"ADD_ALIAS"},"ledgerTimestamp":1626654287006,"uuid":"UD6fe41jDfpf9ylEUvyoZA","version":"1"}
{"action":{"identity":{"address":"N\u0000sourcecred\u0000core\u0000IDENTITY\u0000iyOgwTMuKUjIyHkU297IjA\u0000","aliases":[],"id":"iyOgwTMuKUjIyHkU297IjA","name":"cusx","subtype":"USER"},"type":"CREATE_IDENTITY"},"ledgerTimestamp":1626654287006,"uuid":"84KoEClqUQg8p3haBO5mZg","version":"1"}
{"action":{"alias":{"address":"N\u0000sourcecred\u0000discord\u0000MEMBER\u0000user\u0000281055990315614208\u0000","description":"discord/cusx#2103"},"identityId":"iyOgwTMuKUjIyHkU297IjA","type":"ADD_ALIAS"},"ledgerTimestamp":1626654287006,"uuid":"MWX7Z18oLI2foijpgklBCg","version":"1"}
{"action":{"identity":{"address":"N\u0000sourcecred\u0000core\u0000IDENTITY\u0000aykeWdsnWSww8g6xvXTAAw\u0000","aliases":[],"id":"aykeWdsnWSww8g6xvXTAAw","name":"Tony-Tony-Chopper","subtype":"USER"},"type":"CREATE_IDENTITY"},"ledgerTimestamp":1626654287006,"uuid":"djoC6AqUwbmxIYW5mpZfqQ","version":"1"}
{"action":{"alias":{"address":"N\u0000sourcecred\u0000discord\u0000MEMBER\u0000user\u0000282871599563014144\u0000","description":"discord/Tony Tony Chopper#4606"},"identityId":"aykeWdsnWSww8g6xvXTAAw","type":"ADD_ALIAS"},"ledgerTimestamp":1626654287006,"uuid":"oE76kaYvH8niXQRZdZ0pBQ","version":"1"}
{"action":{"identity":{"address":"N\u0000sourcecred\u0000core\u0000IDENTITY\u0000sWYJ6Y9IYgXOA2H9pm1Qhg\u0000","aliases":[],"id":"sWYJ6Y9IYgXOA2H9pm1Qhg","name":"QE4EVER---hotnewcrypto","subtype":"USER"},"type":"CREATE_IDENTITY"},"ledgerTimestamp":1626654287006,"uuid":"crGrg6XzXzA8zDLNkJCeMg","version":"1"}
{"action":{"alias":{"address":"N\u0000sourcecred\u0000discord\u0000MEMBER\u0000user\u0000310803263530336257\u0000","description":"discord/QE4EVER | hotnewcrypto#4324"},"identityId":"sWYJ6Y9IYgXOA2H9pm1Qhg","type":"ADD_ALIAS"},"ledgerTimestamp":1626654287006,"uuid":"NMfvqjoF6JTeOVc7nd5uLQ","version":"1"}
{"action":{"identity":{"address":"N\u0000sourcecred\u0000core\u0000IDENTITY\u00001hNd1ZAGP8XVVCDKRbXxQA\u0000","aliases":[],"id":"1hNd1ZAGP8XVVCDKRbXxQA","name":"poopster","subtype":"USER"},"type":"CREATE_IDENTITY"},"ledgerTimestamp":1626654287006,"uuid":"jIbAdrEIxOn3K1GeyJqWUQ","version":"1"}
{"action":{"alias":{"address":"N\u0000sourcecred\u0000discord\u0000MEMBER\u0000user\u0000318511843020767252\u0000","description":"discord/poopster#3593"},"identityId":"1hNd1ZAGP8XVVCDKRbXxQA","type":"ADD_ALIAS"},"ledgerTimestamp":1626654287007,"uuid":"7d9rgTakJiEUOSXImVhAZw","version":"1"}
{"action":{"identity":{"address":"N\u0000sourcecred\u0000core\u0000IDENTITY\u0000OEm305uO8XKA7glB4312Uw\u0000","aliases":[],"id":"OEm305uO8XKA7glB4312Uw","name":"pupuu","subtype":"USER"},"type":"CREATE_IDENTITY"},"ledgerTimestamp":1626654287007,"uuid":"eraQvHXcLop59Iyk5TamZA","version":"1"}
{"action":{"alias":{"address":"N\u0000sourcecred\u0000discord\u0000MEMBER\u0000user\u0000325303654376538113\u0000","description":"discord/pupuu#4248"},"identityId":"OEm305uO8XKA7glB4312Uw","type":"ADD_ALIAS"},"ledgerTimestamp":1626654287007,"uuid":"JlbUq3X5j1q71kkmTKeqWQ","version":"1"}
{"action":{"identity":{"address":"N\u0000sourcecred\u0000core\u0000IDENTITY\u0000AIJmd60TJ6WN6Yyh697aIw\u0000","aliases":[],"id":"AIJmd60TJ6WN6Yyh697aIw","name":"redmption","subtype":"USER"},"type":"CREATE_IDENTITY"},"ledgerTimestamp":1626654287007,"uuid":"QksYDjOyG6O12KYt0ZMy8Q","version":"1"}
{"action":{"alias":{"address":"N\u0000sourcecred\u0000discord\u0000MEMBER\u0000user\u0000334693448131149834\u0000","description":"discord/redmption#7706"},"identityId":"AIJmd60TJ6WN6Yyh697aIw","type":"ADD_ALIAS"},"ledgerTimestamp":1626654287007,"uuid":"1dZJjseXdyqjQzosASozhw","version":"1"}
{"action":{"identity":{"address":"N\u0000sourcecred\u0000core\u0000IDENTITY\u0000mKCmqv7DWu8QJ5yV7YBw4w\u0000","aliases":[],"id":"mKCmqv7DWu8QJ5yV7YBw4w","name":"Goon-Machine","subtype":"USER"},"type":"CREATE_IDENTITY"},"ledgerTimestamp":1626654287009,"uuid":"SaWbCMyKUNWlkfxP8m9JKA","version":"1"}
{"action":{"alias":{"address":"N\u0000sourcecred\u0000discord\u0000MEMBER\u0000user\u0000335535847002865674\u0000","description":"discord/Goon Machine#3334"},"identityId":"mKCmqv7DWu8QJ5yV7YBw4w","type":"ADD_ALIAS"},"ledgerTimestamp":1626654287009,"uuid":"GsZXO3glSoJZWCYE8N4gQA","version":"1"}
{"action":{"identity":{"address":"N\u0000sourcecred\u0000core\u0000IDENTITY\u0000kqztW0qjal7Vp7CzJ5iQsw\u0000","aliases":[],"id":"kqztW0qjal7Vp7CzJ5iQsw","name":"Magnus","subtype":"USER"},"type":"CREATE_IDENTITY"},"ledgerTimestamp":1626654287009,"uuid":"jrMQrkUrzs6LrLLKVRiZSg","version":"1"}
{"action":{"alias":{"address":"N\u0000sourcecred\u0000discord\u0000MEMBER\u0000user\u0000337602572514754560\u0000","description":"discord/Magnus#3558"},"identityId":"kqztW0qjal7Vp7CzJ5iQsw","type":"ADD_ALIAS"},"ledgerTimestamp":1626654287009,"uuid":"osdXLkUJn3wvqATjs9LiAQ","version":"1"}
{"action":{"identity":{"address":"N\u0000sourcecred\u0000core\u0000IDENTITY\u0000GTv3VjyhMDFeayKIP2fbSQ\u0000","aliases":[],"id":"GTv3VjyhMDFeayKIP2fbSQ","name":"sls","subtype":"USER"},"type":"CREATE_IDENTITY"},"ledgerTimestamp":1626654287009,"uuid":"Gm2i6OA2io61PkqQpk6yCA","version":"1"}
{"action":{"alias":{"address":"N\u0000sourcecred\u0000discord\u0000MEMBER\u0000user\u0000344236964385521666\u0000","description":"discord/sls#0012"},"identityId":"GTv3VjyhMDFeayKIP2fbSQ","type":"ADD_ALIAS"},"ledgerTimestamp":1626654287009,"uuid":"EsM0WgonVeNNjA2t8zHXvw","version":"1"}
{"action":{"identity":{"address":"N\u0000sourcecred\u0000core\u0000IDENTITY\u0000ErNGR0QyKFwI6WrIYyr4cw\u0000","aliases":[],"id":"ErNGR0QyKFwI6WrIYyr4cw","name":"Viktorskf--Viktor-","subtype":"USER"},"type":"CREATE_IDENTITY"},"ledgerTimestamp":1626654287009,"uuid":"CN7ldAlto8mfp0GEm92qTA","version":"1"}
{"action":{"alias":{"address":"N\u0000sourcecred\u0000discord\u0000MEMBER\u0000user\u0000347836520100659202\u0000","description":"discord/Viktorskf (Viktor)#3931"},"identityId":"ErNGR0QyKFwI6WrIYyr4cw","type":"ADD_ALIAS"},"ledgerTimestamp":1626654287009,"uuid":"0W36iDSqkAMl5zOOMdHgfg","version":"1"}
{"action":{"identity":{"address":"N\u0000sourcecred\u0000core\u0000IDENTITY\u00004QI2Xwz6Fx4c2q1AMNIJZA\u0000","aliases":[],"id":"4QI2Xwz6Fx4c2q1AMNIJZA","name":"Satish143--3--3-","subtype":"USER"},"type":"CREATE_IDENTITY"},"ledgerTimestamp":1626654287009,"uuid":"kHlkBCRjV0nnmYQh3wOBHQ","version":"1"}
{"action":{"alias":{"address":"N\u0000sourcecred\u0000discord\u0000MEMBER\u0000user\u0000362804848996909077\u0000","description":"discord/Satish143 (3, 3)#8241"},"identityId":"4QI2Xwz6Fx4c2q1AMNIJZA","type":"ADD_ALIAS"},"ledgerTimestamp":1626654287010,"uuid":"IdVJ1vE4VRHLPeA2RSny4Q","version":"1"}
{"action":{"identity":{"address":"N\u0000sourcecred\u0000core\u0000IDENTITY\u0000TerkvxIpaAS9Mnl8aI9xXQ\u0000","aliases":[],"id":"TerkvxIpaAS9Mnl8aI9xXQ","name":"Nikhil","subtype":"USER"},"type":"CREATE_IDENTITY"},"ledgerTimestamp":1626654287010,"uuid":"8sXGPEt2nO8qMWoE3PjDxg","version":"1"}
{"action":{"alias":{"address":"N\u0000sourcecred\u0000discord\u0000MEMBER\u0000user\u0000369959429476712449\u0000","description":"discord/Nikhil#3582"},"identityId":"TerkvxIpaAS9Mnl8aI9xXQ","type":"ADD_ALIAS"},"ledgerTimestamp":1626654287010,"uuid":"4D6EklDvABzGuyoS8POC0g","version":"1"}
{"action":{"identity":{"address":"N\u0000sourcecred\u0000core\u0000IDENTITY\u0000qy7wmQjFNVdOgI9BsBDhwA\u0000","aliases":[],"id":"qy7wmQjFNVdOgI9BsBDhwA","name":"HD","subtype":"USER"},"type":"CREATE_IDENTITY"},"ledgerTimestamp":1626654287010,"uuid":"rX73Rdg4pxRtXRSzc7Tgdw","version":"1"}
{"action":{"alias":{"address":"N\u0000sourcecred\u0000discord\u0000MEMBER\u0000user\u0000370678198632972289\u0000","description":"discord/HD#0330"},"identityId":"qy7wmQjFNVdOgI9BsBDhwA","type":"ADD_ALIAS"},"ledgerTimestamp":1626654287010,"uuid":"GsEeKhRQ8TBc1PKpa11teg","version":"1"}
{"action":{"identity":{"address":"N\u0000sourcecred\u0000core\u0000IDENTITY\u00006EnIrSM7W6wrDxmCmHO65g\u0000","aliases":[],"id":"6EnIrSM7W6wrDxmCmHO65g","name":"sniper25","subtype":"USER"},"type":"CREATE_IDENTITY"},"ledgerTimestamp":1626654287010,"uuid":"NZyEDJ3d1dNJNJ3DFovkXg","version":"1"}
{"action":{"alias":{"address":"N\u0000sourcecred\u0000discord\u0000MEMBER\u0000user\u0000385601403944566785\u0000","description":"discord/sniper25#0414"},"identityId":"6EnIrSM7W6wrDxmCmHO65g","type":"ADD_ALIAS"},"ledgerTimestamp":1626654287010,"uuid":"281iRS9aecqm003sBxjAzQ","version":"1"}
{"action":{"identity":{"address":"N\u0000sourcecred\u0000core\u0000IDENTITY\u0000hJKvH4KYuzEp4G1sotwAFA\u0000","aliases":[],"id":"hJKvH4KYuzEp4G1sotwAFA","name":"Strikeanerve","subtype":"USER"},"type":"CREATE_IDENTITY"},"ledgerTimestamp":1626654287010,"uuid":"LcYgsNQ86hWBWkTOjMGznA","version":"1"}
{"action":{"alias":{"address":"N\u0000sourcecred\u0000discord\u0000MEMBER\u0000user\u0000391276669702242319\u0000","description":"discord/Strikeanerve#3801"},"identityId":"hJKvH4KYuzEp4G1sotwAFA","type":"ADD_ALIAS"},"ledgerTimestamp":1626654287010,"uuid":"kSDo6lyCEOaqgpnAsddzow","version":"1"}
{"action":{"identity":{"address":"N\u0000sourcecred\u0000core\u0000IDENTITY\u0000PtKB0J0qswuYQVIQtrHyAw\u0000","aliases":[],"id":"PtKB0J0qswuYQVIQtrHyAw","name":"theshark","subtype":"USER"},"type":"CREATE_IDENTITY"},"ledgerTimestamp":1626654287010,"uuid":"jLJNYc69wgl9f9Rueyg4Bg","version":"1"}
{"action":{"alias":{"address":"N\u0000sourcecred\u0000discord\u0000MEMBER\u0000user\u0000392154072691638272\u0000","description":"discord/theshark#4172"},"identityId":"PtKB0J0qswuYQVIQtrHyAw","type":"ADD_ALIAS"},"ledgerTimestamp":1626654287010,"uuid":"VFDUg0uAUldJBl3wY0BREw","version":"1"}
{"action":{"identity":{"address":"N\u0000sourcecred\u0000core\u0000IDENTITY\u0000tdgi3G7vfzbtKPKBntgJ2A\u0000","aliases":[],"id":"tdgi3G7vfzbtKPKBntgJ2A","name":"ayyylmao","subtype":"USER"},"type":"CREATE_IDENTITY"},"ledgerTimestamp":1626654287011,"uuid":"4g9HQ0UyBbtK9A9ioBA4xw","version":"1"}
{"action":{"alias":{"address":"N\u0000sourcecred\u0000discord\u0000MEMBER\u0000user\u0000392634073455263744\u0000","description":"discord/ayyylmao#5047"},"identityId":"tdgi3G7vfzbtKPKBntgJ2A","type":"ADD_ALIAS"},"ledgerTimestamp":1626654287011,"uuid":"nc9T4VPB8t7UbABEEIRGsw","version":"1"}
{"action":{"identity":{"address":"N\u0000sourcecred\u0000core\u0000IDENTITY\u0000h29IjPoYdG4Sa5p36hbJRg\u0000","aliases":[],"id":"h29IjPoYdG4Sa5p36hbJRg","name":"500bitcoins","subtype":"USER"},"type":"CREATE_IDENTITY"},"ledgerTimestamp":1626654287011,"uuid":"KpgsdOkP9hr89vNt3YxjBw","version":"1"}
{"action":{"alias":{"address":"N\u0000sourcecred\u0000discord\u0000MEMBER\u0000user\u0000393318050465579009\u0000","description":"discord/500bitcoins#0682"},"identityId":"h29IjPoYdG4Sa5p36hbJRg","type":"ADD_ALIAS"},"ledgerTimestamp":1626654287011,"uuid":"bfWaMVVxg1wsLEh8l9wOtw","version":"1"}
{"action":{"identity":{"address":"N\u0000sourcecred\u0000core\u0000IDENTITY\u0000bkznXjAM9awMUQwvWtol6w\u0000","aliases":[],"id":"bkznXjAM9awMUQwvWtol6w","name":"cryptodetweiler","subtype":"USER"},"type":"CREATE_IDENTITY"},"ledgerTimestamp":1626654287011,"uuid":"X3l0jGkEEH6mpdXm3DRWQQ","version":"1"}
{"action":{"alias":{"address":"N\u0000sourcecred\u0000discord\u0000MEMBER\u0000user\u0000394339917888487445\u0000","description":"discord/cryptodetweiler#0830"},"identityId":"bkznXjAM9awMUQwvWtol6w","type":"ADD_ALIAS"},"ledgerTimestamp":1626654287011,"uuid":"k23F2SdUvkcJpnoT56JWNg","version":"1"}
{"action":{"identity":{"address":"N\u0000sourcecred\u0000core\u0000IDENTITY\u0000CERIqtBhmCzSy8xnzUN0gg\u0000","aliases":[],"id":"CERIqtBhmCzSy8xnzUN0gg","name":"arunphilips---Polygon","subtype":"USER"},"type":"CREATE_IDENTITY"},"ledgerTimestamp":1626654287011,"uuid":"Kn2g34OO1KnPd6v77X6k9A","version":"1"}
{"action":{"alias":{"address":"N\u0000sourcecred\u0000discord\u0000MEMBER\u0000user\u0000396007432675131405\u0000","description":"discord/arunphilips | Polygon#9899"},"identityId":"CERIqtBhmCzSy8xnzUN0gg","type":"ADD_ALIAS"},"ledgerTimestamp":1626654287011,"uuid":"IodKECY6RLVQE3k6J7bDEw","version":"1"}
{"action":{"identity":{"address":"N\u0000sourcecred\u0000core\u0000IDENTITY\u0000rSNAxQTvjkQgwj3s9U9e4w\u0000","aliases":[],"id":"rSNAxQTvjkQgwj3s9U9e4w","name":"Eric-Bal","subtype":"USER"},"type":"CREATE_IDENTITY"},"ledgerTimestamp":1626654287011,"uuid":"W8Tx4HKuxWp6IoCbu02BDg","version":"1"}
{"action":{"alias":{"address":"N\u0000sourcecred\u0000discord\u0000MEMBER\u0000user\u0000398213240703811604\u0000","description":"discord/Eric Bal#8862"},"identityId":"rSNAxQTvjkQgwj3s9U9e4w","type":"ADD_ALIAS"},"ledgerTimestamp":1626654287012,"uuid":"JDnu28AJfboZvaoVbvfRyw","version":"1"}
{"action":{"identity":{"address":"N\u0000sourcecred\u0000core\u0000IDENTITY\u0000wx0OnDUm1Neegl9tyMFQ0g\u0000","aliases":[],"id":"wx0OnDUm1Neegl9tyMFQ0g","name":"dogoshii","subtype":"USER"},"type":"CREATE_IDENTITY"},"ledgerTimestamp":1626654287012,"uuid":"s5DIOM8oirxbf9a7h8F68Q","version":"1"}
{"action":{"alias":{"address":"N\u0000sourcecred\u0000discord\u0000MEMBER\u0000user\u0000398644583308853249\u0000","description":"discord/dogoshii#3081"},"identityId":"wx0OnDUm1Neegl9tyMFQ0g","type":"ADD_ALIAS"},"ledgerTimestamp":1626654287012,"uuid":"GXdOb3wFM7nKdRR9IKCZ9A","version":"1"}
{"action":{"identity":{"address":"N\u0000sourcecred\u0000core\u0000IDENTITY\u0000xe82WrzsACAXohdDzLJUVw\u0000","aliases":[],"id":"xe82WrzsACAXohdDzLJUVw","name":"atron","subtype":"USER"},"type":"CREATE_IDENTITY"},"ledgerTimestamp":1626654287012,"uuid":"m42ndjbA6SADOLfDSQLl2g","version":"1"}
{"action":{"alias":{"address":"N\u0000sourcecred\u0000discord\u0000MEMBER\u0000user\u0000401590407160659978\u0000","description":"discord/atron#1528"},"identityId":"xe82WrzsACAXohdDzLJUVw","type":"ADD_ALIAS"},"ledgerTimestamp":1626654287012,"uuid":"CwJpNks5QW9HXYpX6CdBbw","version":"1"}
{"action":{"identity":{"address":"N\u0000sourcecred\u0000core\u0000IDENTITY\u0000KzOORf7fOrbLZw8mAqzPfQ\u0000","aliases":[],"id":"KzOORf7fOrbLZw8mAqzPfQ","name":"NameMe","subtype":"USER"},"type":"CREATE_IDENTITY"},"ledgerTimestamp":1626654287012,"uuid":"zpM17x5lYM8c0t5diNZrgg","version":"1"}
{"action":{"alias":{"address":"N\u0000sourcecred\u0000discord\u0000MEMBER\u0000user\u0000408416190700978176\u0000","description":"discord/NameMe#5233"},"identityId":"KzOORf7fOrbLZw8mAqzPfQ","type":"ADD_ALIAS"},"ledgerTimestamp":1626654287013,"uuid":"tyujCAjniDjB4jlD0u6kjQ","version":"1"}
{"action":{"identity":{"address":"N\u0000sourcecred\u0000core\u0000IDENTITY\u0000Di7VdZTd2ZFyY1Kw67Yw6g\u0000","aliases":[],"id":"Di7VdZTd2ZFyY1Kw67Yw6g","name":"Classics23","subtype":"USER"},"type":"CREATE_IDENTITY"},"ledgerTimestamp":1626654287013,"uuid":"2mv8d18T6RSNh1D7wUviaA","version":"1"}
{"action":{"alias":{"address":"N\u0000sourcecred\u0000discord\u0000MEMBER\u0000user\u0000415086679649550347\u0000","description":"discord/Classics23#5299"},"identityId":"Di7VdZTd2ZFyY1Kw67Yw6g","type":"ADD_ALIAS"},"ledgerTimestamp":1626654287013,"uuid":"5YjpGFl9yvxBD3DgTRRZhQ","version":"1"}
{"action":{"identity":{"address":"N\u0000sourcecred\u0000core\u0000IDENTITY\u0000syzHbLiAhEJaJlV4WWVuAQ\u0000","aliases":[],"id":"syzHbLiAhEJaJlV4WWVuAQ","name":"Ceazor-eth--Snack-Sandwich-YT-","subtype":"USER"},"type":"CREATE_IDENTITY"},"ledgerTimestamp":1626654287013,"uuid":"Qemp4X0kXehJve7vtzSmDQ","version":"1"}
{"action":{"alias":{"address":"N\u0000sourcecred\u0000discord\u0000MEMBER\u0000user\u0000417846775395647499\u0000","description":"discord/Ceazor.eth (Snack Sandwich YT)#8074"},"identityId":"syzHbLiAhEJaJlV4WWVuAQ","type":"ADD_ALIAS"},"ledgerTimestamp":1626654287013,"uuid":"v7id5Gnh0CQESe9pJ2jRjA","version":"1"}
{"action":{"identity":{"address":"N\u0000sourcecred\u0000core\u0000IDENTITY\u0000WCOtlbC9PXJHvkT4mHowsw\u0000","aliases":[],"id":"WCOtlbC9PXJHvkT4mHowsw","name":"E-S","subtype":"USER"},"type":"CREATE_IDENTITY"},"ledgerTimestamp":1626654287013,"uuid":"Zc0NXcA32B0vAVEdwoqGEQ","version":"1"}
{"action":{"alias":{"address":"N\u0000sourcecred\u0000discord\u0000MEMBER\u0000user\u0000437030516282097685\u0000","description":"discord/E.S#6018"},"identityId":"WCOtlbC9PXJHvkT4mHowsw","type":"ADD_ALIAS"},"ledgerTimestamp":1626654287013,"uuid":"GtDyryU5uMD2jk1JIaiXZg","version":"1"}
{"action":{"identity":{"address":"N\u0000sourcecred\u0000core\u0000IDENTITY\u00004s0IGUxR574kcwg24ZiO2Q\u0000","aliases":[],"id":"4s0IGUxR574kcwg24ZiO2Q","name":"Pedrowww","subtype":"USER"},"type":"CREATE_IDENTITY"},"ledgerTimestamp":1626654287013,"uuid":"56d2lAtDRnYQUMM1nXTXfw","version":"1"}
{"action":{"alias":{"address":"N\u0000sourcecred\u0000discord\u0000MEMBER\u0000user\u0000445851056308748301\u0000","description":"discord/Pedrowww#8870"},"identityId":"4s0IGUxR574kcwg24ZiO2Q","type":"ADD_ALIAS"},"ledgerTimestamp":1626654287013,"uuid":"aTon4HliOqiNG37JN1ozqg","version":"1"}
{"action":{"identity":{"address":"N\u0000sourcecred\u0000core\u0000IDENTITY\u00003l2Yl1rGhjKQXsbKk4Qf5Q\u0000","aliases":[],"id":"3l2Yl1rGhjKQXsbKk4Qf5Q","name":"0xJudah","subtype":"USER"},"type":"CREATE_IDENTITY"},"ledgerTimestamp":1626654287014,"uuid":"2SGc34n5IGWtv8dCRNdPbg","version":"1"}
{"action":{"alias":{"address":"N\u0000sourcecred\u0000discord\u0000MEMBER\u0000user\u0000448599377590878208\u0000","description":"discord/0xJudah#2820"},"identityId":"3l2Yl1rGhjKQXsbKk4Qf5Q","type":"ADD_ALIAS"},"ledgerTimestamp":1626654287014,"uuid":"IOZuPQEBZdG9UEAQAe61ug","version":"1"}
{"action":{"identity":{"address":"N\u0000sourcecred\u0000core\u0000IDENTITY\u0000fwMCmRHbrqEuBIa1pqSYfA\u0000","aliases":[],"id":"fwMCmRHbrqEuBIa1pqSYfA","name":"LeoY","subtype":"USER"},"type":"CREATE_IDENTITY"},"ledgerTimestamp":1626654287014,"uuid":"5E3xBUAqgW6KpSXlTV2jMw","version":"1"}
{"action":{"alias":{"address":"N\u0000sourcecred\u0000discord\u0000MEMBER\u0000user\u0000455731206919684097\u0000","description":"discord/LeoY#6329"},"identityId":"fwMCmRHbrqEuBIa1pqSYfA","type":"ADD_ALIAS"},"ledgerTimestamp":1626654287014,"uuid":"0vDvLuQzvFzQvi2KEq31rg","version":"1"}
{"action":{"identity":{"address":"N\u0000sourcecred\u0000core\u0000IDENTITY\u0000l1GiMtOqxjESBYnZg8g0Zw\u0000","aliases":[],"id":"l1GiMtOqxjESBYnZg8g0Zw","name":"CryptoInfluence","subtype":"USER"},"type":"CREATE_IDENTITY"},"ledgerTimestamp":1626654287014,"uuid":"KTPKdY094d1G1P5IoMpvog","version":"1"}
{"action":{"alias":{"address":"N\u0000sourcecred\u0000discord\u0000MEMBER\u0000user\u0000457977265997742090\u0000","description":"discord/CryptoInfluence#1805"},"identityId":"l1GiMtOqxjESBYnZg8g0Zw","type":"ADD_ALIAS"},"ledgerTimestamp":1626654287014,"uuid":"DNsr4SeRtRTeFwx826ZxHg","version":"1"}
{"action":{"identity":{"address":"N\u0000sourcecred\u0000core\u0000IDENTITY\u0000z5O7uoyVhbJvYWwYDj6ejw\u0000","aliases":[],"id":"z5O7uoyVhbJvYWwYDj6ejw","name":"david-sunil","subtype":"USER"},"type":"CREATE_IDENTITY"},"ledgerTimestamp":1626654287014,"uuid":"XGuDV6VMvLpHwvE51XzyAA","version":"1"}
{"action":{"alias":{"address":"N\u0000sourcecred\u0000discord\u0000MEMBER\u0000user\u0000465372733308534785\u0000","description":"discord/david sunil#2490"},"identityId":"z5O7uoyVhbJvYWwYDj6ejw","type":"ADD_ALIAS"},"ledgerTimestamp":1626654287014,"uuid":"qOlpkXOorFRJVhzjdQGzWA","version":"1"}
{"action":{"identity":{"address":"N\u0000sourcecred\u0000core\u0000IDENTITY\u0000jMtVA8ZIQOoHqpgK6wELRw\u0000","aliases":[],"id":"jMtVA8ZIQOoHqpgK6wELRw","name":"Dan---Benchmark","subtype":"USER"},"type":"CREATE_IDENTITY"},"ledgerTimestamp":1626654287015,"uuid":"kWVl4ynoAqqliEMnQNdCyg","version":"1"}
{"action":{"alias":{"address":"N\u0000sourcecred\u0000discord\u0000MEMBER\u0000user\u0000470961639399620608\u0000","description":"discord/Dan | Benchmark#8122"},"identityId":"jMtVA8ZIQOoHqpgK6wELRw","type":"ADD_ALIAS"},"ledgerTimestamp":1626654287015,"uuid":"vIvvZczDbggpGCQbmVt9lQ","version":"1"}
{"action":{"identity":{"address":"N\u0000sourcecred\u0000core\u0000IDENTITY\u0000818hpMfJWqJmt94l1xm3Dw\u0000","aliases":[],"id":"818hpMfJWqJmt94l1xm3Dw","name":"Degen","subtype":"USER"},"type":"CREATE_IDENTITY"},"ledgerTimestamp":1626654287015,"uuid":"r1WZ7emJF2KyKZio8sDdVw","version":"1"}
{"action":{"alias":{"address":"N\u0000sourcecred\u0000discord\u0000MEMBER\u0000user\u0000476544222833672204\u0000","description":"discord/Degen#8380"},"identityId":"818hpMfJWqJmt94l1xm3Dw","type":"ADD_ALIAS"},"ledgerTimestamp":1626654287015,"uuid":"kq0TrRtYPWDyOkUbSqNkyA","version":"1"}
{"action":{"identity":{"address":"N\u0000sourcecred\u0000core\u0000IDENTITY\u0000rnf2BgF3IVhZxibXVb6Btg\u0000","aliases":[],"id":"rnf2BgF3IVhZxibXVb6Btg","name":"wir","subtype":"USER"},"type":"CREATE_IDENTITY"},"ledgerTimestamp":1626654287015,"uuid":"OXBXlZBs44bd7qQUpZ4EvA","version":"1"}
{"action":{"alias":{"address":"N\u0000sourcecred\u0000discord\u0000MEMBER\u0000user\u0000484191958743384085\u0000","description":"discord/wir#4873"},"identityId":"rnf2BgF3IVhZxibXVb6Btg","type":"ADD_ALIAS"},"ledgerTimestamp":1626654287015,"uuid":"YJ5jQ687AGH2EfrPFlo5JA","version":"1"}
{"action":{"identity":{"address":"N\u0000sourcecred\u0000core\u0000IDENTITY\u0000KoCKNX2sNXgh3cxN0H5glA\u0000","aliases":[],"id":"KoCKNX2sNXgh3cxN0H5glA","name":"blakeburrito","subtype":"USER"},"type":"CREATE_IDENTITY"},"ledgerTimestamp":1626654287015,"uuid":"eNmR0egJwDjg6WvrMmiB7g","version":"1"}
{"action":{"alias":{"address":"N\u0000sourcecred\u0000discord\u0000MEMBER\u0000user\u0000488408777981165571\u0000","description":"discord/blakeburrito#1313"},"identityId":"KoCKNX2sNXgh3cxN0H5glA","type":"ADD_ALIAS"},"ledgerTimestamp":1626654287015,"uuid":"cMD5e0k3DN2Jml7QZnRcyQ","version":"1"}
{"action":{"identity":{"address":"N\u0000sourcecred\u0000core\u0000IDENTITY\u0000NspJSWODmbGL1JZPPMQKoA\u0000","aliases":[],"id":"NspJSWODmbGL1JZPPMQKoA","name":"SurfTranquille","subtype":"USER"},"type":"CREATE_IDENTITY"},"ledgerTimestamp":1626654287015,"uuid":"PYfQ49J9bBVyl4qfMBaRew","version":"1"}
{"action":{"alias":{"address":"N\u0000sourcecred\u0000discord\u0000MEMBER\u0000user\u0000492160201420701696\u0000","description":"discord/SurfTranquille#5721"},"identityId":"NspJSWODmbGL1JZPPMQKoA","type":"ADD_ALIAS"},"ledgerTimestamp":1626654287016,"uuid":"ayxFavclf0rRUJJPs5yppQ","version":"1"}
{"action":{"identity":{"address":"N\u0000sourcecred\u0000core\u0000IDENTITY\u0000NjnpYlhdtyfyBuwSjrPJXQ\u0000","aliases":[],"id":"NjnpYlhdtyfyBuwSjrPJXQ","name":"--haikukoten---Honey-DAO---","subtype":"USER"},"type":"CREATE_IDENTITY"},"ledgerTimestamp":1626654287016,"uuid":"jt45vbwRCZPeEdrY3P651w","version":"1"}
{"action":{"alias":{"address":"N\u0000sourcecred\u0000discord\u0000MEMBER\u0000user\u0000502120545186218007\u0000","description":"discord/&#x221E; haikukoten | Honey DAO &#x1F36F;#8725"},"identityId":"NjnpYlhdtyfyBuwSjrPJXQ","type":"ADD_ALIAS"},"ledgerTimestamp":1626654287016,"uuid":"AR8kyHpGEeMBlGjnJDxZdw","version":"1"}
{"action":{"identity":{"address":"N\u0000sourcecred\u0000core\u0000IDENTITY\u0000qBsxE1rB9SgOVwZbcjN0Ww\u0000","aliases":[],"id":"qBsxE1rB9SgOVwZbcjN0Ww","name":"ayyyeandy","subtype":"USER"},"type":"CREATE_IDENTITY"},"ledgerTimestamp":1626654287016,"uuid":"1rREX9ivMjcnyVdMl4C5gA","version":"1"}
{"action":{"alias":{"address":"N\u0000sourcecred\u0000discord\u0000MEMBER\u0000user\u0000540264282927923232\u0000","description":"discord/ayyyeandy#1924"},"identityId":"qBsxE1rB9SgOVwZbcjN0Ww","type":"ADD_ALIAS"},"ledgerTimestamp":1626654287016,"uuid":"4Gf1sdnr0JxExeNGLxrzxg","version":"1"}
{"action":{"identity":{"address":"N\u0000sourcecred\u0000core\u0000IDENTITY\u0000A6fOYDHEsDUYOsy9QE946g\u0000","aliases":[],"id":"A6fOYDHEsDUYOsy9QE946g","name":"Bee926","subtype":"USER"},"type":"CREATE_IDENTITY"},"ledgerTimestamp":1626654287016,"uuid":"V3iQ5OdL04HlktAmuMBI7w","version":"1"}
{"action":{"alias":{"address":"N\u0000sourcecred\u0000discord\u0000MEMBER\u0000user\u0000542761771405017099\u0000","description":"discord/Bee926#4033"},"identityId":"A6fOYDHEsDUYOsy9QE946g","type":"ADD_ALIAS"},"ledgerTimestamp":1626654287016,"uuid":"XK1AP5A6A8fV9TJ5hnVc1g","version":"1"}
{"action":{"identity":{"address":"N\u0000sourcecred\u0000core\u0000IDENTITY\u0000dEXeSMdcnage2u0JcY1ioA\u0000","aliases":[],"id":"dEXeSMdcnage2u0JcY1ioA","name":"TokenBrice-xyz","subtype":"USER"},"type":"CREATE_IDENTITY"},"ledgerTimestamp":1626654287017,"uuid":"KZQRHda0DJX6IwnJ962dZQ","version":"1"}
{"action":{"alias":{"address":"N\u0000sourcecred\u0000discord\u0000MEMBER\u0000user\u0000547419159785373708\u0000","description":"discord/TokenBrice.xyz#6531"},"identityId":"dEXeSMdcnage2u0JcY1ioA","type":"ADD_ALIAS"},"ledgerTimestamp":1626654287017,"uuid":"eyKkl9x2kxY9Pe2aYt1aLg","version":"1"}
{"action":{"identity":{"address":"N\u0000sourcecred\u0000core\u0000IDENTITY\u00009O1EoSmxFpE3VJDaaQIJgw\u0000","aliases":[],"id":"9O1EoSmxFpE3VJDaaQIJgw","name":"dunks411","subtype":"USER"},"type":"CREATE_IDENTITY"},"ledgerTimestamp":1626654287017,"uuid":"rvpaKRwaWQlO6a1pkyv6uw","version":"1"}
{"action":{"alias":{"address":"N\u0000sourcecred\u0000discord\u0000MEMBER\u0000user\u0000548358064076619776\u0000","description":"discord/dunks411#2178"},"identityId":"9O1EoSmxFpE3VJDaaQIJgw","type":"ADD_ALIAS"},"ledgerTimestamp":1626654287017,"uuid":"8asLmbi3CwYt9CD7HEmNOw","version":"1"}
{"action":{"identity":{"address":"N\u0000sourcecred\u0000core\u0000IDENTITY\u0000D47yCOqPCDi1NUpMAOJxsw\u0000","aliases":[],"id":"D47yCOqPCDi1NUpMAOJxsw","name":"Ade","subtype":"USER"},"type":"CREATE_IDENTITY"},"ledgerTimestamp":1626654287017,"uuid":"yGSQ4sBUEyeupu99nYSnTg","version":"1"}
{"action":{"alias":{"address":"N\u0000sourcecred\u0000discord\u0000MEMBER\u0000user\u0000561559631072198656\u0000","description":"discord/Ade#2314"},"identityId":"D47yCOqPCDi1NUpMAOJxsw","type":"ADD_ALIAS"},"ledgerTimestamp":1626654287017,"uuid":"YN6Lt3lcEIZs318psmGRkw","version":"1"}
{"action":{"identity":{"address":"N\u0000sourcecred\u0000core\u0000IDENTITY\u0000zWV8hDNI2RflJdAwD9nIPw\u0000","aliases":[],"id":"zWV8hDNI2RflJdAwD9nIPw","name":"greenbarkeep","subtype":"USER"},"type":"CREATE_IDENTITY"},"ledgerTimestamp":1626654287018,"uuid":"78OQ5BIpJuDBfaZ2kORHgg","version":"1"}
{"action":{"alias":{"address":"N\u0000sourcecred\u0000discord\u0000MEMBER\u0000user\u0000585660108542050347\u0000","description":"discord/greenbarkeep#2998"},"identityId":"zWV8hDNI2RflJdAwD9nIPw","type":"ADD_ALIAS"},"ledgerTimestamp":1626654287018,"uuid":"Je1iPv3T6KvDPuZtDi2eaQ","version":"1"}
{"action":{"identity":{"address":"N\u0000sourcecred\u0000core\u0000IDENTITY\u00009XGk3gVKfXpLgWMyzxkOOg\u0000","aliases":[],"id":"9XGk3gVKfXpLgWMyzxkOOg","name":"28ickler-Zorx-","subtype":"USER"},"type":"CREATE_IDENTITY"},"ledgerTimestamp":1626654287018,"uuid":"26d7Yy32Z7KVmLBiYqGwUA","version":"1"}
{"action":{"alias":{"address":"N\u0000sourcecred\u0000discord\u0000MEMBER\u0000user\u0000588212990990352384\u0000","description":"discord/28ickler(Zorx)#1913"},"identityId":"9XGk3gVKfXpLgWMyzxkOOg","type":"ADD_ALIAS"},"ledgerTimestamp":1626654287018,"uuid":"PzL0duG0cjtjwvETQnQU1A","version":"1"}
{"action":{"identity":{"address":"N\u0000sourcecred\u0000core\u0000IDENTITY\u0000pRbXsLkrjsGiJOpDJO6M8A\u0000","aliases":[],"id":"pRbXsLkrjsGiJOpDJO6M8A","name":"brrrick","subtype":"USER"},"type":"CREATE_IDENTITY"},"ledgerTimestamp":1626654287018,"uuid":"wxRNH8Syv9d16DOdJ4ORQw","version":"1"}
{"action":{"alias":{"address":"N\u0000sourcecred\u0000discord\u0000MEMBER\u0000user\u0000602285689056526366\u0000","description":"discord/brrrick#9351"},"identityId":"pRbXsLkrjsGiJOpDJO6M8A","type":"ADD_ALIAS"},"ledgerTimestamp":1626654287018,"uuid":"yUZoyKQSrS1fovyeNqRbBg","version":"1"}
{"action":{"identity":{"address":"N\u0000sourcecred\u0000core\u0000IDENTITY\u0000Y0U7BjmToPiz0VGgpt4eUA\u0000","aliases":[],"id":"Y0U7BjmToPiz0VGgpt4eUA","name":"sesh","subtype":"BOT"},"type":"CREATE_IDENTITY"},"ledgerTimestamp":1626654287019,"uuid":"xKsgnQf6WoERnu8DqwnwLA","version":"1"}
{"action":{"alias":{"address":"N\u0000sourcecred\u0000discord\u0000MEMBER\u0000bot\u0000616754792965865495\u0000","description":"discord/sesh#1244"},"identityId":"Y0U7BjmToPiz0VGgpt4eUA","type":"ADD_ALIAS"},"ledgerTimestamp":1626654287019,"uuid":"73dUPdsq6eUWQ5Nj4RpOoQ","version":"1"}
{"action":{"identity":{"address":"N\u0000sourcecred\u0000core\u0000IDENTITY\u0000pB6yYPqY5Epe2sZ95ptM8w\u0000","aliases":[],"id":"pB6yYPqY5Epe2sZ95ptM8w","name":"jaybird","subtype":"USER"},"type":"CREATE_IDENTITY"},"ledgerTimestamp":1626654287019,"uuid":"zhnapTyWMuomRAkZVxRF9A","version":"1"}
{"action":{"alias":{"address":"N\u0000sourcecred\u0000discord\u0000MEMBER\u0000user\u0000618248969901965312\u0000","description":"discord/jaybird#5235"},"identityId":"pB6yYPqY5Epe2sZ95ptM8w","type":"ADD_ALIAS"},"ledgerTimestamp":1626654287019,"uuid":"sknM6lK877ZB3iwxnofg7g","version":"1"}
{"action":{"identity":{"address":"N\u0000sourcecred\u0000core\u0000IDENTITY\u0000KlzZHec1o1730aFxWb3xfw\u0000","aliases":[],"id":"KlzZHec1o1730aFxWb3xfw","name":"Taco","subtype":"BOT"},"type":"CREATE_IDENTITY"},"ledgerTimestamp":1626654287019,"uuid":"OIq2DlrzJyQi3dLe76yF5w","version":"1"}
{"action":{"alias":{"address":"N\u0000sourcecred\u0000discord\u0000MEMBER\u0000bot\u0000620126394390675466\u0000","description":"discord/Taco#0086"},"identityId":"KlzZHec1o1730aFxWb3xfw","type":"ADD_ALIAS"},"ledgerTimestamp":1626654287019,"uuid":"6YLCLMVFojDAc0ykfZrieQ","version":"1"}
{"action":{"identity":{"address":"N\u0000sourcecred\u0000core\u0000IDENTITY\u0000aeeDw02d0QMg2wmN2YcAlA\u0000","aliases":[],"id":"aeeDw02d0QMg2wmN2YcAlA","name":"SkyHawkDP","subtype":"USER"},"type":"CREATE_IDENTITY"},"ledgerTimestamp":1626654287019,"uuid":"bAGgPbzJBM651AD3ypptLQ","version":"1"}
{"action":{"alias":{"address":"N\u0000sourcecred\u0000discord\u0000MEMBER\u0000user\u0000634462979911581713\u0000","description":"discord/SkyHawkDP#3825"},"identityId":"aeeDw02d0QMg2wmN2YcAlA","type":"ADD_ALIAS"},"ledgerTimestamp":1626654287019,"uuid":"z2qpP04qriERMdLdaXoxag","version":"1"}
{"action":{"identity":{"address":"N\u0000sourcecred\u0000core\u0000IDENTITY\u0000c9dZxHobGmhQgk3acv30Lg\u0000","aliases":[],"id":"c9dZxHobGmhQgk3acv30Lg","name":"uh","subtype":"USER"},"type":"CREATE_IDENTITY"},"ledgerTimestamp":1626654287020,"uuid":"fEkfLhg7sr5X5aKNTRkNIg","version":"1"}
{"action":{"alias":{"address":"N\u0000sourcecred\u0000discord\u0000MEMBER\u0000user\u0000638493028952178738\u0000","description":"discord/uh#2064"},"identityId":"c9dZxHobGmhQgk3acv30Lg","type":"ADD_ALIAS"},"ledgerTimestamp":1626654287020,"uuid":"mwsAa8LA88kTZuBvARnxMA","version":"1"}
{"action":{"identity":{"address":"N\u0000sourcecred\u0000core\u0000IDENTITY\u0000tjBdGJGJyWEkyXpx8KQjsA\u0000","aliases":[],"id":"tjBdGJGJyWEkyXpx8KQjsA","name":"sisyphus1337","subtype":"USER"},"type":"CREATE_IDENTITY"},"ledgerTimestamp":1626654287020,"uuid":"7uPtRCZJFXHpj0CyC9o0fA","version":"1"}
{"action":{"alias":{"address":"N\u0000sourcecred\u0000discord\u0000MEMBER\u0000user\u0000640144569710673930\u0000","description":"discord/sisyphus1337#7913"},"identityId":"tjBdGJGJyWEkyXpx8KQjsA","type":"ADD_ALIAS"},"ledgerTimestamp":1626654287020,"uuid":"3SRiMEDg0KpSximakP8DKQ","version":"1"}
{"action":{"identity":{"address":"N\u0000sourcecred\u0000core\u0000IDENTITY\u0000s82d0G0ksAKgkW4jy3QWFg\u0000","aliases":[],"id":"s82d0G0ksAKgkW4jy3QWFg","name":"Gabrielhaines","subtype":"USER"},"type":"CREATE_IDENTITY"},"ledgerTimestamp":1626654287020,"uuid":"jsPdPB3qnwJoc439T0n5YA","version":"1"}
{"action":{"alias":{"address":"N\u0000sourcecred\u0000discord\u0000MEMBER\u0000user\u0000653348489433972756\u0000","description":"discord/Gabrielhaines#0617"},"identityId":"s82d0G0ksAKgkW4jy3QWFg","type":"ADD_ALIAS"},"ledgerTimestamp":1626654287020,"uuid":"0v7ViapaOWn7J2e09Pg8yg","version":"1"}
{"action":{"identity":{"address":"N\u0000sourcecred\u0000core\u0000IDENTITY\u0000O7hVjVuAV60ekxWwrFzBOQ\u0000","aliases":[],"id":"O7hVjVuAV60ekxWwrFzBOQ","name":"0x-Hemsta","subtype":"USER"},"type":"CREATE_IDENTITY"},"ledgerTimestamp":1626654287021,"uuid":"a6hVfKEj3aN5wgmp5BdNbA","version":"1"}
{"action":{"alias":{"address":"N\u0000sourcecred\u0000discord\u0000MEMBER\u0000user\u0000655679782360449075\u0000","description":"discord/0x.Hemsta#3248"},"identityId":"O7hVjVuAV60ekxWwrFzBOQ","type":"ADD_ALIAS"},"ledgerTimestamp":1626654287022,"uuid":"iWYAOrn4nMmliPkb1Kt1PQ","version":"1"}
{"action":{"identity":{"address":"N\u0000sourcecred\u0000core\u0000IDENTITY\u0000BuOF8ViKklk4gbYbAHYNKQ\u0000","aliases":[],"id":"BuOF8ViKklk4gbYbAHYNKQ","name":"cryptouf","subtype":"USER"},"type":"CREATE_IDENTITY"},"ledgerTimestamp":1626654287022,"uuid":"f1JgTE9VrijDx6wHrmlGxQ","version":"1"}
{"action":{"alias":{"address":"N\u0000sourcecred\u0000discord\u0000MEMBER\u0000user\u0000693968649052094525\u0000","description":"discord/cryptouf#2315"},"identityId":"BuOF8ViKklk4gbYbAHYNKQ","type":"ADD_ALIAS"},"ledgerTimestamp":1626654287022,"uuid":"OAWOKy9seLDkMImD7NM2iA","version":"1"}
{"action":{"identity":{"address":"N\u0000sourcecred\u0000core\u0000IDENTITY\u0000dfRXHrfjfldYJdAz621E6A\u0000","aliases":[],"id":"dfRXHrfjfldYJdAz621E6A","name":"revolutionary-spaces","subtype":"USER"},"type":"CREATE_IDENTITY"},"ledgerTimestamp":1626654287022,"uuid":"yqR8eC6ZysaYZgbt91z7fg","version":"1"}
{"action":{"alias":{"address":"N\u0000sourcecred\u0000discord\u0000MEMBER\u0000user\u0000698267000845238483\u0000","description":"discord/revolutionary_spaces#5629"},"identityId":"dfRXHrfjfldYJdAz621E6A","type":"ADD_ALIAS"},"ledgerTimestamp":1626654287022,"uuid":"IAviQMh0bvP2BXvSBGIEJw","version":"1"}
{"action":{"identity":{"address":"N\u0000sourcecred\u0000core\u0000IDENTITY\u0000lN0qHMai8dp7hrvT1S0wqw\u0000","aliases":[],"id":"lN0qHMai8dp7hrvT1S0wqw","name":"bg999","subtype":"USER"},"type":"CREATE_IDENTITY"},"ledgerTimestamp":1626654287023,"uuid":"yXXjwrXKFr9zknrBIJu7Aw","version":"1"}
{"action":{"alias":{"address":"N\u0000sourcecred\u0000discord\u0000MEMBER\u0000user\u0000698723963014217790\u0000","description":"discord/bg999#6547"},"identityId":"lN0qHMai8dp7hrvT1S0wqw","type":"ADD_ALIAS"},"ledgerTimestamp":1626654287023,"uuid":"bNO3oZwwt5iDYxU4p01nUA","version":"1"}
{"action":{"identity":{"address":"N\u0000sourcecred\u0000core\u0000IDENTITY\u0000GkcvhafvjKcwJdQjlz9aXA\u0000","aliases":[],"id":"GkcvhafvjKcwJdQjlz9aXA","name":"Heruvim78","subtype":"USER"},"type":"CREATE_IDENTITY"},"ledgerTimestamp":1626654287023,"uuid":"Ll2ZLBJ37767YBLaejwtaw","version":"1"}
{"action":{"alias":{"address":"N\u0000sourcecred\u0000discord\u0000MEMBER\u0000user\u0000719350246223642687\u0000","description":"discord/Heruvim78#6876"},"identityId":"GkcvhafvjKcwJdQjlz9aXA","type":"ADD_ALIAS"},"ledgerTimestamp":1626654287023,"uuid":"7TqzAIDgenDRNgqt8dpuZg","version":"1"}
{"action":{"identity":{"address":"N\u0000sourcecred\u0000core\u0000IDENTITY\u0000kMiV7QJ8LXB9LXyiPKzkcQ\u0000","aliases":[],"id":"kMiV7QJ8LXB9LXyiPKzkcQ","name":"PVMihalache","subtype":"USER"},"type":"CREATE_IDENTITY"},"ledgerTimestamp":1626654287023,"uuid":"RfO8aD537PP9EK7dwU7sjg","version":"1"}
{"action":{"alias":{"address":"N\u0000sourcecred\u0000discord\u0000MEMBER\u0000user\u0000722575082156851211\u0000","description":"discord/PVMihalache#8517"},"identityId":"kMiV7QJ8LXB9LXyiPKzkcQ","type":"ADD_ALIAS"},"ledgerTimestamp":1626654287023,"uuid":"imMji5RUd1nvUeE4qJyLFg","version":"1"}
{"action":{"identity":{"address":"N\u0000sourcecred\u0000core\u0000IDENTITY\u0000E3JvpKdcAbBWbobTb4DVHQ\u0000","aliases":[],"id":"E3JvpKdcAbBWbobTb4DVHQ","name":"louve--","subtype":"USER"},"type":"CREATE_IDENTITY"},"ledgerTimestamp":1626654287024,"uuid":"SYU1vFrkRHK47iw6SLArbQ","version":"1"}
{"action":{"alias":{"address":"N\u0000sourcecred\u0000discord\u0000MEMBER\u0000user\u0000739481321105260677\u0000","description":"discord/louve&#x1F311;#8063"},"identityId":"E3JvpKdcAbBWbobTb4DVHQ","type":"ADD_ALIAS"},"ledgerTimestamp":1626654287024,"uuid":"Z6AV6TMIAW7m7r5GGnhLHQ","version":"1"}
{"action":{"identity":{"address":"N\u0000sourcecred\u0000core\u0000IDENTITY\u00008F6u15Urv1XatRQuom0BuA\u0000","aliases":[],"id":"8F6u15Urv1XatRQuom0BuA","name":"Bertaliot","subtype":"USER"},"type":"CREATE_IDENTITY"},"ledgerTimestamp":1626654287024,"uuid":"2RWI6JwQa4O9zcRmvyeKBQ","version":"1"}
{"action":{"alias":{"address":"N\u0000sourcecred\u0000discord\u0000MEMBER\u0000user\u0000744095301173772358\u0000","description":"discord/Bertaliot#0156"},"identityId":"8F6u15Urv1XatRQuom0BuA","type":"ADD_ALIAS"},"ledgerTimestamp":1626654287024,"uuid":"uWHDfg9yYPvDtpP9PTPw6w","version":"1"}
{"action":{"identity":{"address":"N\u0000sourcecred\u0000core\u0000IDENTITY\u0000lY7EQ1EghxGOOgZQU3yUXw\u0000","aliases":[],"id":"lY7EQ1EghxGOOgZQU3yUXw","name":"0xkowloon","subtype":"USER"},"type":"CREATE_IDENTITY"},"ledgerTimestamp":1626654287024,"uuid":"nuKmB0pKx9vCluKF6kup8w","version":"1"}
{"action":{"alias":{"address":"N\u0000sourcecred\u0000discord\u0000MEMBER\u0000user\u0000744523836115910758\u0000","description":"discord/0xkowloon#3337"},"identityId":"lY7EQ1EghxGOOgZQU3yUXw","type":"ADD_ALIAS"},"ledgerTimestamp":1626654287024,"uuid":"HAnEuyymqnVR1xViat29sw","version":"1"}
{"action":{"identity":{"address":"N\u0000sourcecred\u0000core\u0000IDENTITY\u00002pcLIgfjY2z3ZWomFYsE6g\u0000","aliases":[],"id":"2pcLIgfjY2z3ZWomFYsE6g","name":"Singikin","subtype":"USER"},"type":"CREATE_IDENTITY"},"ledgerTimestamp":1626654287025,"uuid":"IQ77GjYF7jXDXLzq6iE0zQ","version":"1"}
{"action":{"alias":{"address":"N\u0000sourcecred\u0000discord\u0000MEMBER\u0000user\u0000745702107801452634\u0000","description":"discord/Singikin#6817"},"identityId":"2pcLIgfjY2z3ZWomFYsE6g","type":"ADD_ALIAS"},"ledgerTimestamp":1626654287025,"uuid":"P3jaedA79JkzT2IxcRDe5A","version":"1"}
{"action":{"identity":{"address":"N\u0000sourcecred\u0000core\u0000IDENTITY\u0000ALUYRGxSXB6bM1z3zbpkJA\u0000","aliases":[],"id":"ALUYRGxSXB6bM1z3zbpkJA","name":"akshayraw","subtype":"USER"},"type":"CREATE_IDENTITY"},"ledgerTimestamp":1626654287025,"uuid":"KlKTn6LKi606gaP8fZ0iVQ","version":"1"}
{"action":{"alias":{"address":"N\u0000sourcecred\u0000discord\u0000MEMBER\u0000user\u0000764477382185713690\u0000","description":"discord/akshayraw#0698"},"identityId":"ALUYRGxSXB6bM1z3zbpkJA","type":"ADD_ALIAS"},"ledgerTimestamp":1626654287025,"uuid":"sYqGGqflmwtw35qLZcgI3g","version":"1"}
{"action":{"identity":{"address":"N\u0000sourcecred\u0000core\u0000IDENTITY\u0000rwOyAfGTBu0srofXQHrFng\u0000","aliases":[],"id":"rwOyAfGTBu0srofXQHrFng","name":"fugu","subtype":"USER"},"type":"CREATE_IDENTITY"},"ledgerTimestamp":1626654287025,"uuid":"tnaP4mKVsB9Kb0i6WJlc2w","version":"1"}
{"action":{"alias":{"address":"N\u0000sourcecred\u0000discord\u0000MEMBER\u0000user\u0000775192734562517016\u0000","description":"discord/fugu#1472"},"identityId":"rwOyAfGTBu0srofXQHrFng","type":"ADD_ALIAS"},"ledgerTimestamp":1626654287025,"uuid":"RpU6ggWAximpwcbfKIruEg","version":"1"}
{"action":{"identity":{"address":"N\u0000sourcecred\u0000core\u0000IDENTITY\u0000OCO3LJk4jVJvYoz7SnXqMA\u0000","aliases":[],"id":"OCO3LJk4jVJvYoz7SnXqMA","name":"PassiveCrypto","subtype":"USER"},"type":"CREATE_IDENTITY"},"ledgerTimestamp":1626654287026,"uuid":"2rd02974ORpzQuq0KhAyVQ","version":"1"}
{"action":{"alias":{"address":"N\u0000sourcecred\u0000discord\u0000MEMBER\u0000user\u0000794837781801205761\u0000","description":"discord/PassiveCrypto#6857"},"identityId":"OCO3LJk4jVJvYoz7SnXqMA","type":"ADD_ALIAS"},"ledgerTimestamp":1626654287026,"uuid":"Zw1DI3xbBAXRtBAQ7Ge4IA","version":"1"}
{"action":{"identity":{"address":"N\u0000sourcecred\u0000core\u0000IDENTITY\u0000mJpPJH3RENgJydy55AYZ8g\u0000","aliases":[],"id":"mJpPJH3RENgJydy55AYZ8g","name":"loco","subtype":"USER"},"type":"CREATE_IDENTITY"},"ledgerTimestamp":1626654287026,"uuid":"1ncBvXkcOAEPN1nJHn6zbQ","version":"1"}
{"action":{"alias":{"address":"N\u0000sourcecred\u0000discord\u0000MEMBER\u0000user\u0000795973530025066506\u0000","description":"discord/loco#1403"},"identityId":"mJpPJH3RENgJydy55AYZ8g","type":"ADD_ALIAS"},"ledgerTimestamp":1626654287026,"uuid":"g550akqkN22N489TpKV5ug","version":"1"}
{"action":{"identity":{"address":"N\u0000sourcecred\u0000core\u0000IDENTITY\u0000FJ3Ir1qCGwpm9bAZ4DWMBw\u0000","aliases":[],"id":"FJ3Ir1qCGwpm9bAZ4DWMBw","name":"cc2","subtype":"USER"},"type":"CREATE_IDENTITY"},"ledgerTimestamp":1626654287026,"uuid":"Lfyjre2JUpw88c6i1jeHWg","version":"1"}
{"action":{"alias":{"address":"N\u0000sourcecred\u0000discord\u0000MEMBER\u0000user\u0000797330295371202613\u0000","description":"discord/cc2#2803"},"identityId":"FJ3Ir1qCGwpm9bAZ4DWMBw","type":"ADD_ALIAS"},"ledgerTimestamp":1626654287026,"uuid":"0QqiLSYoNyuQyZz2nCLqXA","version":"1"}
{"action":{"identity":{"address":"N\u0000sourcecred\u0000core\u0000IDENTITY\u00008e3WnMQRg17fQvNdEq4ZBw\u0000","aliases":[],"id":"8e3WnMQRg17fQvNdEq4ZBw","name":"Beij","subtype":"USER"},"type":"CREATE_IDENTITY"},"ledgerTimestamp":1626654287026,"uuid":"zN6FbJOdmcQHazSQAhEMew","version":"1"}
{"action":{"alias":{"address":"N\u0000sourcecred\u0000discord\u0000MEMBER\u0000user\u0000812348750394556457\u0000","description":"discord/Beij#2923"},"identityId":"8e3WnMQRg17fQvNdEq4ZBw","type":"ADD_ALIAS"},"ledgerTimestamp":1626654287026,"uuid":"X8RANnclrF36ckrLxhYK3g","version":"1"}
{"action":{"identity":{"address":"N\u0000sourcecred\u0000core\u0000IDENTITY\u0000vvdrvVDvd0sV1311xdsGeQ\u0000","aliases":[],"id":"vvdrvVDvd0sV1311xdsGeQ","name":"evgeniy","subtype":"USER"},"type":"CREATE_IDENTITY"},"ledgerTimestamp":1626654287026,"uuid":"5im5wYmDrrvDMGWTw4SVnw","version":"1"}
{"action":{"alias":{"address":"N\u0000sourcecred\u0000discord\u0000MEMBER\u0000user\u0000814527474251726928\u0000","description":"discord/evgeniy#5551"},"identityId":"vvdrvVDvd0sV1311xdsGeQ","type":"ADD_ALIAS"},"ledgerTimestamp":1626654287027,"uuid":"P5BPX1x8f977bn8Ca2FrDQ","version":"1"}
{"action":{"identity":{"address":"N\u0000sourcecred\u0000core\u0000IDENTITY\u0000ktQSgg8ZbsjPwYHj5ZGOfw\u0000","aliases":[],"id":"ktQSgg8ZbsjPwYHj5ZGOfw","name":"0xtundra","subtype":"USER"},"type":"CREATE_IDENTITY"},"ledgerTimestamp":1626654287027,"uuid":"rOZH6PkJmhONuB2YWhN7CQ","version":"1"}
{"action":{"alias":{"address":"N\u0000sourcecred\u0000discord\u0000MEMBER\u0000user\u0000820466501022122034\u0000","description":"discord/0xtundra#7151"},"identityId":"ktQSgg8ZbsjPwYHj5ZGOfw","type":"ADD_ALIAS"},"ledgerTimestamp":1626654287027,"uuid":"HaUz2iNgL9Ie69YCxebYKA","version":"1"}
{"action":{"identity":{"address":"N\u0000sourcecred\u0000core\u0000IDENTITY\u0000E5OaePr7hGYZCQI9yFlkYw\u0000","aliases":[],"id":"E5OaePr7hGYZCQI9yFlkYw","name":"Rheta-Thurber","subtype":"USER"},"type":"CREATE_IDENTITY"},"ledgerTimestamp":1626654287027,"uuid":"9CqDMnd1qx9MNnN87KQzew","version":"1"}
{"action":{"alias":{"address":"N\u0000sourcecred\u0000discord\u0000MEMBER\u0000user\u0000823084051589103668\u0000","description":"discord/Rheta Thurber#0017"},"identityId":"E5OaePr7hGYZCQI9yFlkYw","type":"ADD_ALIAS"},"ledgerTimestamp":1626654287027,"uuid":"jJOSNlye8FXkpsOjkd00Vw","version":"1"}
{"action":{"identity":{"address":"N\u0000sourcecred\u0000core\u0000IDENTITY\u0000WeLgYQd4CYZOYdYaulacYg\u0000","aliases":[],"id":"WeLgYQd4CYZOYdYaulacYg","name":"0xLingonberry","subtype":"USER"},"type":"CREATE_IDENTITY"},"ledgerTimestamp":1626654287028,"uuid":"OMklJq1In0qjnlX3ovx79A","version":"1"}
{"action":{"alias":{"address":"N\u0000sourcecred\u0000discord\u0000MEMBER\u0000user\u0000824093377544454185\u0000","description":"discord/0xLingonberry#2327"},"identityId":"WeLgYQd4CYZOYdYaulacYg","type":"ADD_ALIAS"},"ledgerTimestamp":1626654287028,"uuid":"IZx64grfaVGGhVZzdQQpJQ","version":"1"}
{"action":{"identity":{"address":"N\u0000sourcecred\u0000core\u0000IDENTITY\u0000c17qhq48mxT7KIWG4zN3Eg\u0000","aliases":[],"id":"c17qhq48mxT7KIWG4zN3Eg","name":"yousnoel","subtype":"USER"},"type":"CREATE_IDENTITY"},"ledgerTimestamp":1626654287028,"uuid":"1ZDg3vi0IGmJ3SNwi1Qj8Q","version":"1"}
{"action":{"alias":{"address":"N\u0000sourcecred\u0000discord\u0000MEMBER\u0000user\u0000827017198660747274\u0000","description":"discord/yousnoel#7108"},"identityId":"c17qhq48mxT7KIWG4zN3Eg","type":"ADD_ALIAS"},"ledgerTimestamp":1626654287028,"uuid":"4JUmm9aBlpPgirbmb4FBsA","version":"1"}
{"action":{"identity":{"address":"N\u0000sourcecred\u0000core\u0000IDENTITY\u0000MVesXnRFeJ2wPXwKuLpsaQ\u0000","aliases":[],"id":"MVesXnRFeJ2wPXwKuLpsaQ","name":"redefined-life","subtype":"USER"},"type":"CREATE_IDENTITY"},"ledgerTimestamp":1626654287028,"uuid":"RILkJaSpKnDTbzs1f343cg","version":"1"}
{"action":{"alias":{"address":"N\u0000sourcecred\u0000discord\u0000MEMBER\u0000user\u0000830296854428254229\u0000","description":"discord/redefined_life#4464"},"identityId":"MVesXnRFeJ2wPXwKuLpsaQ","type":"ADD_ALIAS"},"ledgerTimestamp":1626654287028,"uuid":"QfrdKqR6NSp2ELPseKf0RQ","version":"1"}
{"action":{"identity":{"address":"N\u0000sourcecred\u0000core\u0000IDENTITY\u00007tPr8BrxM45jGxjlsZpUvw\u0000","aliases":[],"id":"7tPr8BrxM45jGxjlsZpUvw","name":"C1DoubleDown","subtype":"USER"},"type":"CREATE_IDENTITY"},"ledgerTimestamp":1626654287029,"uuid":"xZnZnJxOBfMv4iNT81CZiA","version":"1"}
{"action":{"alias":{"address":"N\u0000sourcecred\u0000discord\u0000MEMBER\u0000user\u0000836830322787221546\u0000","description":"discord/C1DoubleDown#4331"},"identityId":"7tPr8BrxM45jGxjlsZpUvw","type":"ADD_ALIAS"},"ledgerTimestamp":1626654287029,"uuid":"8jvOvqQzRZyAwnXGd5cnvg","version":"1"}
{"action":{"identity":{"address":"N\u0000sourcecred\u0000core\u0000IDENTITY\u00001DXZP7g1UGJFyImrD7jguw\u0000","aliases":[],"id":"1DXZP7g1UGJFyImrD7jguw","name":"insider","subtype":"USER"},"type":"CREATE_IDENTITY"},"ledgerTimestamp":1626654287029,"uuid":"brpizab2rJO9swTjRtlFNw","version":"1"}
{"action":{"alias":{"address":"N\u0000sourcecred\u0000discord\u0000MEMBER\u0000user\u0000848366279785709598\u0000","description":"discord/insider#7291"},"identityId":"1DXZP7g1UGJFyImrD7jguw","type":"ADD_ALIAS"},"ledgerTimestamp":1626654287029,"uuid":"ad5bnJcv3eD1tXgz6x23wA","version":"1"}
{"action":{"identity":{"address":"N\u0000sourcecred\u0000core\u0000IDENTITY\u0000HlvygMlcmzlKkOWDWOMVCg\u0000","aliases":[],"id":"HlvygMlcmzlKkOWDWOMVCg","name":"eddyCRZ","subtype":"USER"},"type":"CREATE_IDENTITY"},"ledgerTimestamp":1626654287029,"uuid":"7ktYn2btLCqrXr6sXCMc6w","version":"1"}
{"action":{"alias":{"address":"N\u0000sourcecred\u0000discord\u0000MEMBER\u0000user\u0000856771322788708373\u0000","description":"discord/eddyCRZ#3063"},"identityId":"HlvygMlcmzlKkOWDWOMVCg","type":"ADD_ALIAS"},"ledgerTimestamp":1626654287029,"uuid":"9lA5o3E48t2OZtwigxRkGw","version":"1"}
{"action":{"identity":{"address":"N\u0000sourcecred\u0000core\u0000IDENTITY\u0000x6wFecEf8XOqx9KEIBA4qw\u0000","aliases":[],"id":"x6wFecEf8XOqx9KEIBA4qw","name":"lem","subtype":"USER"},"type":"CREATE_IDENTITY"},"ledgerTimestamp":1626654287029,"uuid":"5hedAulmKORHAQDryd1QYQ","version":"1"}
{"action":{"alias":{"address":"N\u0000sourcecred\u0000discord\u0000MEMBER\u0000user\u0000860127400628846613\u0000","description":"discord/lem#5511"},"identityId":"x6wFecEf8XOqx9KEIBA4qw","type":"ADD_ALIAS"},"ledgerTimestamp":1626654287029,"uuid":"SQrQ0WqduowNzDY5aEc3Kw","version":"1"}
{"action":{"identity":{"address":"N\u0000sourcecred\u0000core\u0000IDENTITY\u00001E2RDTg9XSNyU0YiyBR6HQ\u0000","aliases":[],"id":"1E2RDTg9XSNyU0YiyBR6HQ","name":"cre8rcred","subtype":"BOT"},"type":"CREATE_IDENTITY"},"ledgerTimestamp":1626654287030,"uuid":"d7Dgzl8L4y24fJhB15y25A","version":"1"}
{"action":{"alias":{"address":"N\u0000sourcecred\u0000discord\u0000MEMBER\u0000bot\u0000863361964549079041\u0000","description":"discord/cre8rcred#0197"},"identityId":"1E2RDTg9XSNyU0YiyBR6HQ","type":"ADD_ALIAS"},"ledgerTimestamp":1626654287030,"uuid":"3WFpnIzywOiqyGLEqOZDxw","version":"1"}
{"action":{"identity":{"address":"N\u0000sourcecred\u0000core\u0000IDENTITY\u0000vDGAZ6oW7mU5WHXyqmW2tA\u0000","aliases":[],"id":"vDGAZ6oW7mU5WHXyqmW2tA","name":"wassiecapital","subtype":"USER"},"type":"CREATE_IDENTITY"},"ledgerTimestamp":1626654287030,"uuid":"08KajpjqIaTlU1TknyKjMA","version":"1"}
{"action":{"alias":{"address":"N\u0000sourcecred\u0000discord\u0000MEMBER\u0000user\u0000180644728675500032\u0000","description":"discord/wassiecapital#3180"},"identityId":"vDGAZ6oW7mU5WHXyqmW2tA","type":"ADD_ALIAS"},"ledgerTimestamp":1626654287030,"uuid":"U1cymZ4wHLa42Eot94m1xg","version":"1"}
{"action":{"identity":{"address":"N\u0000sourcecred\u0000core\u0000IDENTITY\u0000AG6eG8UNb0E3dUB5xJoJgA\u0000","aliases":[],"id":"AG6eG8UNb0E3dUB5xJoJgA","name":"iamgaurangdesai","subtype":"USER"},"type":"CREATE_IDENTITY"},"ledgerTimestamp":1626654287030,"uuid":"i8Zpr78BINxwNJaRmC7Mdw","version":"1"}
{"action":{"alias":{"address":"N\u0000sourcecred\u0000discord\u0000MEMBER\u0000user\u0000202967732046659586\u0000","description":"discord/iamgaurangdesai#7548"},"identityId":"AG6eG8UNb0E3dUB5xJoJgA","type":"ADD_ALIAS"},"ledgerTimestamp":1626654287030,"uuid":"cMXkotoZzvsX2sohgbrf3g","version":"1"}
{"action":{"identity":{"address":"N\u0000sourcecred\u0000core\u0000IDENTITY\u0000MwTnDnqx2c5OSMgNEAaBuQ\u0000","aliases":[],"id":"MwTnDnqx2c5OSMgNEAaBuQ","name":"minkman","subtype":"USER"},"type":"CREATE_IDENTITY"},"ledgerTimestamp":1626654287031,"uuid":"3iZqbMp9YYBgasXlrbkeiQ","version":"1"}
{"action":{"alias":{"address":"N\u0000sourcecred\u0000discord\u0000MEMBER\u0000user\u0000216661390474084352\u0000","description":"discord/minkman#1727"},"identityId":"MwTnDnqx2c5OSMgNEAaBuQ","type":"ADD_ALIAS"},"ledgerTimestamp":1626654287031,"uuid":"ZbiG1nHDUXNQZDaWASWkhw","version":"1"}
{"action":{"identity":{"address":"N\u0000sourcecred\u0000core\u0000IDENTITY\u0000QwlLsaWFoBwy2g08rMDywg\u0000","aliases":[],"id":"QwlLsaWFoBwy2g08rMDywg","name":"Jacks","subtype":"USER"},"type":"CREATE_IDENTITY"},"ledgerTimestamp":1626654287031,"uuid":"KTNfnfvJeVinZNyniamKDw","version":"1"}
{"action":{"alias":{"address":"N\u0000sourcecred\u0000discord\u0000MEMBER\u0000user\u0000241759820955385856\u0000","description":"discord/Jacks#6609"},"identityId":"QwlLsaWFoBwy2g08rMDywg","type":"ADD_ALIAS"},"ledgerTimestamp":1626654287031,"uuid":"zDaJc3CBQvM22gqYv5xrYw","version":"1"}
{"action":{"identity":{"address":"N\u0000sourcecred\u0000core\u0000IDENTITY\u0000Zwj7dnAFXgzq6sOM6WrB4w\u0000","aliases":[],"id":"Zwj7dnAFXgzq6sOM6WrB4w","name":"ikonoklast","subtype":"USER"},"type":"CREATE_IDENTITY"},"ledgerTimestamp":1626654287031,"uuid":"TeKvIEeL0O6GDObTxirmfw","version":"1"}
{"action":{"alias":{"address":"N\u0000sourcecred\u0000discord\u0000MEMBER\u0000user\u0000269021622378168322\u0000","description":"discord/ikonoklast#7445"},"identityId":"Zwj7dnAFXgzq6sOM6WrB4w","type":"ADD_ALIAS"},"ledgerTimestamp":1626654287031,"uuid":"YwyBGTdvwlVZLPu5wS5EeA","version":"1"}
{"action":{"identity":{"address":"N\u0000sourcecred\u0000core\u0000IDENTITY\u0000jdlJaI8BMFqhKbqtKlIwNg\u0000","aliases":[],"id":"jdlJaI8BMFqhKbqtKlIwNg","name":"Ultima5ky","subtype":"USER"},"type":"CREATE_IDENTITY"},"ledgerTimestamp":1626654287031,"uuid":"uyvzwjfWrfDvCNgHevypAA","version":"1"}
{"action":{"alias":{"address":"N\u0000sourcecred\u0000discord\u0000MEMBER\u0000user\u0000279155446735175680\u0000","description":"discord/Ultima5ky#7126"},"identityId":"jdlJaI8BMFqhKbqtKlIwNg","type":"ADD_ALIAS"},"ledgerTimestamp":1626654287031,"uuid":"QrDIY3UWQ70yDxes6bbg3A","version":"1"}
{"action":{"identity":{"address":"N\u0000sourcecred\u0000core\u0000IDENTITY\u0000JfoX81mYA1OkDDH6uR5Ppg\u0000","aliases":[],"id":"JfoX81mYA1OkDDH6uR5Ppg","name":"Callidus","subtype":"USER"},"type":"CREATE_IDENTITY"},"ledgerTimestamp":1626654287031,"uuid":"U1vOsjNYTnUoIk5Mbnso2w","version":"1"}
{"action":{"alias":{"address":"N\u0000sourcecred\u0000discord\u0000MEMBER\u0000user\u0000280003023093366785\u0000","description":"discord/Callidus#0607"},"identityId":"JfoX81mYA1OkDDH6uR5Ppg","type":"ADD_ALIAS"},"ledgerTimestamp":1626654287031,"uuid":"4DsZePVfVkC3d7BRKDzIbA","version":"1"}
{"action":{"identity":{"address":"N\u0000sourcecred\u0000core\u0000IDENTITY\u0000vCAvOrMBBAbvKMLbYIxPAg\u0000","aliases":[],"id":"vCAvOrMBBAbvKMLbYIxPAg","name":"PunnyUserName","subtype":"USER"},"type":"CREATE_IDENTITY"},"ledgerTimestamp":1626654287032,"uuid":"jZsZ4D0MofBGxbH8Y4XRZg","version":"1"}
{"action":{"alias":{"address":"N\u0000sourcecred\u0000discord\u0000MEMBER\u0000user\u0000317075462935543808\u0000","description":"discord/PunnyUserName#7480"},"identityId":"vCAvOrMBBAbvKMLbYIxPAg","type":"ADD_ALIAS"},"ledgerTimestamp":1626654287032,"uuid":"lk3V353XdXYAVFLPIOzu7Q","version":"1"}
{"action":{"identity":{"address":"N\u0000sourcecred\u0000core\u0000IDENTITY\u0000RCNbwqLday2ROcyS5v12kg\u0000","aliases":[],"id":"RCNbwqLday2ROcyS5v12kg","name":"0xDead1","subtype":"USER"},"type":"CREATE_IDENTITY"},"ledgerTimestamp":1626654287032,"uuid":"X8xxqdyqgcXuzA05YIxp1w","version":"1"}
{"action":{"alias":{"address":"N\u0000sourcecred\u0000discord\u0000MEMBER\u0000user\u0000325769652162658314\u0000","description":"discord/0xDead1#7552"},"identityId":"RCNbwqLday2ROcyS5v12kg","type":"ADD_ALIAS"},"ledgerTimestamp":1626654287032,"uuid":"fQonWwAjWMLDVdW9UjJEIQ","version":"1"}
{"action":{"identity":{"address":"N\u0000sourcecred\u0000core\u0000IDENTITY\u000026ozrJKrhDyJ2geOiVNHRw\u0000","aliases":[],"id":"26ozrJKrhDyJ2geOiVNHRw","name":"marlo","subtype":"USER"},"type":"CREATE_IDENTITY"},"ledgerTimestamp":1626654287032,"uuid":"nnTagWr7wiXrIr1d6DWn5w","version":"1"}
{"action":{"alias":{"address":"N\u0000sourcecred\u0000discord\u0000MEMBER\u0000user\u0000328630969554960394\u0000","description":"discord/marlo#4556"},"identityId":"26ozrJKrhDyJ2geOiVNHRw","type":"ADD_ALIAS"},"ledgerTimestamp":1626654287032,"uuid":"fbGD4CR4p2YesbrK4dO0Ng","version":"1"}
{"action":{"identity":{"address":"N\u0000sourcecred\u0000core\u0000IDENTITY\u0000XMk1fEQjqdMnHlUP5YlU5A\u0000","aliases":[],"id":"XMk1fEQjqdMnHlUP5YlU5A","name":"neverclame","subtype":"USER"},"type":"CREATE_IDENTITY"},"ledgerTimestamp":1626654287032,"uuid":"WQWqZRsZPS3g6kZEGhjwAw","version":"1"}
{"action":{"alias":{"address":"N\u0000sourcecred\u0000discord\u0000MEMBER\u0000user\u0000345943681695744001\u0000","description":"discord/neverclame#1911"},"identityId":"XMk1fEQjqdMnHlUP5YlU5A","type":"ADD_ALIAS"},"ledgerTimestamp":1626654287033,"uuid":"JrB6ErnODYKyv6Y6SAwbjQ","version":"1"}
{"action":{"identity":{"address":"N\u0000sourcecred\u0000core\u0000IDENTITY\u0000KjE15efyY0gd9qHGuPxC3g\u0000","aliases":[],"id":"KjE15efyY0gd9qHGuPxC3g","name":"Dae","subtype":"USER"},"type":"CREATE_IDENTITY"},"ledgerTimestamp":1626654287033,"uuid":"IA9Nn4V4WF1KMfwjzBbACA","version":"1"}
{"action":{"alias":{"address":"N\u0000sourcecred\u0000discord\u0000MEMBER\u0000user\u0000346495966603640833\u0000","description":"discord/Dae#3193"},"identityId":"KjE15efyY0gd9qHGuPxC3g","type":"ADD_ALIAS"},"ledgerTimestamp":1626654287033,"uuid":"dOFrX1kBnAhPq7TyLfvLxQ","version":"1"}
{"action":{"identity":{"address":"N\u0000sourcecred\u0000core\u0000IDENTITY\u0000gvu869V9f8FAMnGjxgvmIg\u0000","aliases":[],"id":"gvu869V9f8FAMnGjxgvmIg","name":"Andrew-T","subtype":"USER"},"type":"CREATE_IDENTITY"},"ledgerTimestamp":1626654287033,"uuid":"fmbj81CBuzka2ouQ4wRkaQ","version":"1"}
{"action":{"alias":{"address":"N\u0000sourcecred\u0000discord\u0000MEMBER\u0000user\u0000362689616098361346\u0000","description":"discord/Andrew_T#1001"},"identityId":"gvu869V9f8FAMnGjxgvmIg","type":"ADD_ALIAS"},"ledgerTimestamp":1626654287033,"uuid":"S2eRcqGkA9Jki4wzJMMz8w","version":"1"}
{"action":{"identity":{"address":"N\u0000sourcecred\u0000core\u0000IDENTITY\u0000QOtMm0Y9Q2E4XI8q4xl0zw\u0000","aliases":[],"id":"QOtMm0Y9Q2E4XI8q4xl0zw","name":"Big-Papi","subtype":"USER"},"type":"CREATE_IDENTITY"},"ledgerTimestamp":1626654287033,"uuid":"5NVXlwU1P7pbcMwBVDWmgA","version":"1"}
{"action":{"alias":{"address":"N\u0000sourcecred\u0000discord\u0000MEMBER\u0000user\u0000372911134900092938\u0000","description":"discord/Big Papi#2308"},"identityId":"QOtMm0Y9Q2E4XI8q4xl0zw","type":"ADD_ALIAS"},"ledgerTimestamp":1626654287033,"uuid":"G0fyBGNBHV1WukmvAt4goA","version":"1"}
{"action":{"identity":{"address":"N\u0000sourcecred\u0000core\u0000IDENTITY\u0000BWt28ZKIBn5N1J0LlnbHQQ\u0000","aliases":[],"id":"BWt28ZKIBn5N1J0LlnbHQQ","name":"AliensAnonymous69","subtype":"USER"},"type":"CREATE_IDENTITY"},"ledgerTimestamp":1626654287034,"uuid":"tloUOr722Y6wTO7MzYGn2A","version":"1"}
{"action":{"alias":{"address":"N\u0000sourcecred\u0000discord\u0000MEMBER\u0000user\u0000375961688090083328\u0000","description":"discord/AliensAnonymous69#3043"},"identityId":"BWt28ZKIBn5N1J0LlnbHQQ","type":"ADD_ALIAS"},"ledgerTimestamp":1626654287034,"uuid":"HWKRdTgq4DjqQhrC8LbYgA","version":"1"}
{"action":{"identity":{"address":"N\u0000sourcecred\u0000core\u0000IDENTITY\u00005p9OumjSJAZV9TjsWasJow\u0000","aliases":[],"id":"5p9OumjSJAZV9TjsWasJow","name":"Tangle","subtype":"USER"},"type":"CREATE_IDENTITY"},"ledgerTimestamp":1626654287034,"uuid":"bHy078L6jFRfY3KwPC65xw","version":"1"}
{"action":{"alias":{"address":"N\u0000sourcecred\u0000discord\u0000MEMBER\u0000user\u0000383445328763813888\u0000","description":"discord/Tangle#0007"},"identityId":"5p9OumjSJAZV9TjsWasJow","type":"ADD_ALIAS"},"ledgerTimestamp":1626654287034,"uuid":"9AD7kXysXDXRq1rBn7RoJA","version":"1"}
{"action":{"identity":{"address":"N\u0000sourcecred\u0000core\u0000IDENTITY\u00004ZxBJ2rvkQEKT5pVGcWsww\u0000","aliases":[],"id":"4ZxBJ2rvkQEKT5pVGcWsww","name":"FullNode-Meditator","subtype":"USER"},"type":"CREATE_IDENTITY"},"ledgerTimestamp":1626654287034,"uuid":"fPDIyjC1KIDy7UDxLLptbg","version":"1"}
{"action":{"alias":{"address":"N\u0000sourcecred\u0000discord\u0000MEMBER\u0000user\u0000391912256574849034\u0000","description":"discord/FullNode Meditator#4972"},"identityId":"4ZxBJ2rvkQEKT5pVGcWsww","type":"ADD_ALIAS"},"ledgerTimestamp":1626654287034,"uuid":"glVcZnec9HQBAVmGIdalRA","version":"1"}
{"action":{"identity":{"address":"N\u0000sourcecred\u0000core\u0000IDENTITY\u0000kp62YcBfdY4bad1BFgm6nw\u0000","aliases":[],"id":"kp62YcBfdY4bad1BFgm6nw","name":"Slick---Rick","subtype":"USER"},"type":"CREATE_IDENTITY"},"ledgerTimestamp":1626654287034,"uuid":"Q9OtESrernYCvzBc7iEiMw","version":"1"}
{"action":{"alias":{"address":"N\u0000sourcecred\u0000discord\u0000MEMBER\u0000user\u0000394976051778027521\u0000","description":"discord/Slick-&#x262F;-Rick#7936"},"identityId":"kp62YcBfdY4bad1BFgm6nw","type":"ADD_ALIAS"},"ledgerTimestamp":1626654287034,"uuid":"XGGRSyRLeB0l5o3G9F8gHg","version":"1"}
{"action":{"identity":{"address":"N\u0000sourcecred\u0000core\u0000IDENTITY\u0000OdyNu4zrH1Bv4PqlMa5UBQ\u0000","aliases":[],"id":"OdyNu4zrH1Bv4PqlMa5UBQ","name":"AZ","subtype":"USER"},"type":"CREATE_IDENTITY"},"ledgerTimestamp":1626654287034,"uuid":"rhKPqtd56JTz3LdbX2mJAg","version":"1"}
{"action":{"alias":{"address":"N\u0000sourcecred\u0000discord\u0000MEMBER\u0000user\u0000397044762240090152\u0000","description":"discord/AZ#1337"},"identityId":"OdyNu4zrH1Bv4PqlMa5UBQ","type":"ADD_ALIAS"},"ledgerTimestamp":1626654287034,"uuid":"Hpb5iN81Zb9DWgmJOp7bGw","version":"1"}
{"action":{"identity":{"address":"N\u0000sourcecred\u0000core\u0000IDENTITY\u00007MmuAXOC7a44liRnQ2H8LA\u0000","aliases":[],"id":"7MmuAXOC7a44liRnQ2H8LA","name":"ManuAlzuru-----","subtype":"USER"},"type":"CREATE_IDENTITY"},"ledgerTimestamp":1626654287035,"uuid":"Ce95goH0gLBsRWel6MzdXg","version":"1"}
{"action":{"alias":{"address":"N\u0000sourcecred\u0000discord\u0000MEMBER\u0000user\u0000399892650666229770\u0000","description":"discord/ManuAlzuru | &#x1F951;#5047"},"identityId":"7MmuAXOC7a44liRnQ2H8LA","type":"ADD_ALIAS"},"ledgerTimestamp":1626654287035,"uuid":"lyr0WyxJlrJMdwull9EXwg","version":"1"}
{"action":{"identity":{"address":"N\u0000sourcecred\u0000core\u0000IDENTITY\u0000fgRkh8Unon62HWbxm81JeA\u0000","aliases":[],"id":"fgRkh8Unon62HWbxm81JeA","name":"Pratik","subtype":"USER"},"type":"CREATE_IDENTITY"},"ledgerTimestamp":1626654287035,"uuid":"1M1unwRjg7CYkWJ8J4xxeA","version":"1"}
{"action":{"alias":{"address":"N\u0000sourcecred\u0000discord\u0000MEMBER\u0000user\u0000404491788460752909\u0000","description":"discord/Pratik#7777"},"identityId":"fgRkh8Unon62HWbxm81JeA","type":"ADD_ALIAS"},"ledgerTimestamp":1626654287035,"uuid":"SjgsJUYktA8dAIG0s3a9aw","version":"1"}
{"action":{"identity":{"address":"N\u0000sourcecred\u0000core\u0000IDENTITY\u00007WgdvmWM4YiGb9DGe3XrKA\u0000","aliases":[],"id":"7WgdvmWM4YiGb9DGe3XrKA","name":"wloka","subtype":"USER"},"type":"CREATE_IDENTITY"},"ledgerTimestamp":1626654287035,"uuid":"auJMjC7EWKwxvCM5dLQh9Q","version":"1"}
{"action":{"alias":{"address":"N\u0000sourcecred\u0000discord\u0000MEMBER\u0000user\u0000408039049928900608\u0000","description":"discord/wloka#3263"},"identityId":"7WgdvmWM4YiGb9DGe3XrKA","type":"ADD_ALIAS"},"ledgerTimestamp":1626654287035,"uuid":"BnDXaytkNcgcJZY6wyPQKA","version":"1"}
{"action":{"identity":{"address":"N\u0000sourcecred\u0000core\u0000IDENTITY\u0000An8vecAQJ4zRPONW8bVbuQ\u0000","aliases":[],"id":"An8vecAQJ4zRPONW8bVbuQ","name":"jnbtc","subtype":"USER"},"type":"CREATE_IDENTITY"},"ledgerTimestamp":1626654287036,"uuid":"y49Jz6mvCDQiywNl9dMvHQ","version":"1"}
{"action":{"alias":{"address":"N\u0000sourcecred\u0000discord\u0000MEMBER\u0000user\u0000455356864767590411\u0000","description":"discord/jnbtc#1636"},"identityId":"An8vecAQJ4zRPONW8bVbuQ","type":"ADD_ALIAS"},"ledgerTimestamp":1626654287036,"uuid":"KLTWE3Ocagnrr37jwk8dIA","version":"1"}
{"action":{"identity":{"address":"N\u0000sourcecred\u0000core\u0000IDENTITY\u0000fNZg11KpSYLLnKaJ1n3qQA\u0000","aliases":[],"id":"fNZg11KpSYLLnKaJ1n3qQA","name":"KingOfDenmark","subtype":"USER"},"type":"CREATE_IDENTITY"},"ledgerTimestamp":1626654287036,"uuid":"E36sJFZTjhznqgFYB9DEaw","version":"1"}
{"action":{"alias":{"address":"N\u0000sourcecred\u0000discord\u0000MEMBER\u0000user\u0000457451544120524813\u0000","description":"discord/KingOfDenmark#0302"},"identityId":"fNZg11KpSYLLnKaJ1n3qQA","type":"ADD_ALIAS"},"ledgerTimestamp":1626654287036,"uuid":"x5g0HgmmbVl93oNJDiRj0g","version":"1"}
{"action":{"identity":{"address":"N\u0000sourcecred\u0000core\u0000IDENTITY\u0000y95DZbjYzsKjepe8P4ncxA\u0000","aliases":[],"id":"y95DZbjYzsKjepe8P4ncxA","name":"orionxiaohan","subtype":"USER"},"type":"CREATE_IDENTITY"},"ledgerTimestamp":1626654287036,"uuid":"MpfXFAAj8cBrHkH8zjJdBw","version":"1"}
{"action":{"alias":{"address":"N\u0000sourcecred\u0000discord\u0000MEMBER\u0000user\u0000479621838780235778\u0000","description":"discord/orionxiaohan#1807"},"identityId":"y95DZbjYzsKjepe8P4ncxA","type":"ADD_ALIAS"},"ledgerTimestamp":1626654287036,"uuid":"1RH1DS47LBYDsnCBQMGcAg","version":"1"}
{"action":{"identity":{"address":"N\u0000sourcecred\u0000core\u0000IDENTITY\u0000Zj3C8hr9rcd1l5tBgPgOyg\u0000","aliases":[],"id":"Zj3C8hr9rcd1l5tBgPgOyg","name":"sudo","subtype":"USER"},"type":"CREATE_IDENTITY"},"ledgerTimestamp":1626654287036,"uuid":"wqWbCkdy51aa6VlPiPRyOA","version":"1"}
{"action":{"alias":{"address":"N\u0000sourcecred\u0000discord\u0000MEMBER\u0000user\u0000481572613047451669\u0000","description":"discord/sudo#0002"},"identityId":"Zj3C8hr9rcd1l5tBgPgOyg","type":"ADD_ALIAS"},"ledgerTimestamp":1626654287036,"uuid":"K6Y4FVnr8LPnjBijqjkKVA","version":"1"}
{"action":{"identity":{"address":"N\u0000sourcecred\u0000core\u0000IDENTITY\u0000zSVxUyGrWUd3d53AXOaDmg\u0000","aliases":[],"id":"zSVxUyGrWUd3d53AXOaDmg","name":"andrew-i","subtype":"USER"},"type":"CREATE_IDENTITY"},"ledgerTimestamp":1626654287037,"uuid":"rahzWWvi29IQf8LkLBa8GQ","version":"1"}
{"action":{"alias":{"address":"N\u0000sourcecred\u0000discord\u0000MEMBER\u0000user\u0000494908382889639977\u0000","description":"discord/andrew.i#0298"},"identityId":"zSVxUyGrWUd3d53AXOaDmg","type":"ADD_ALIAS"},"ledgerTimestamp":1626654287037,"uuid":"8N8VjBuDymr6s1UWaHNBGA","version":"1"}
{"action":{"identity":{"address":"N\u0000sourcecred\u0000core\u0000IDENTITY\u0000e4KQVMpKEPF6UzwO8s8JkQ\u0000","aliases":[],"id":"e4KQVMpKEPF6UzwO8s8JkQ","name":"Todo","subtype":"BOT"},"type":"CREATE_IDENTITY"},"ledgerTimestamp":1626654287037,"uuid":"t6fOmOGwCWrcdNBuP3HAZg","version":"1"}
{"action":{"alias":{"address":"N\u0000sourcecred\u0000discord\u0000MEMBER\u0000bot\u0000530145634444115968\u0000","description":"discord/Todo#9724"},"identityId":"e4KQVMpKEPF6UzwO8s8JkQ","type":"ADD_ALIAS"},"ledgerTimestamp":1626654287037,"uuid":"q7P0Dac83w0guM9ILcwPtw","version":"1"}
{"action":{"identity":{"address":"N\u0000sourcecred\u0000core\u0000IDENTITY\u0000nrLfVtXsofrKOGjB0XRFoA\u0000","aliases":[],"id":"nrLfVtXsofrKOGjB0XRFoA","name":"triteanderivative","subtype":"USER"},"type":"CREATE_IDENTITY"},"ledgerTimestamp":1626654287037,"uuid":"LfwxAFOGtJpYnDv00V7gpw","version":"1"}
{"action":{"alias":{"address":"N\u0000sourcecred\u0000discord\u0000MEMBER\u0000user\u0000533053420819578902\u0000","description":"discord/triteanderivative#5738"},"identityId":"nrLfVtXsofrKOGjB0XRFoA","type":"ADD_ALIAS"},"ledgerTimestamp":1626654287037,"uuid":"mZrEUwWnoJUjXbjsjQWqCw","version":"1"}
{"action":{"identity":{"address":"N\u0000sourcecred\u0000core\u0000IDENTITY\u0000ZfEP3EWvw4Fv3lr7Nz1kew\u0000","aliases":[],"id":"ZfEP3EWvw4Fv3lr7Nz1kew","name":"redicko","subtype":"USER"},"type":"CREATE_IDENTITY"},"ledgerTimestamp":1626654287038,"uuid":"SRzlHDFAlrcWBV4DPt7ogg","version":"1"}
{"action":{"alias":{"address":"N\u0000sourcecred\u0000discord\u0000MEMBER\u0000user\u0000583175641139118083\u0000","description":"discord/redicko#3550"},"identityId":"ZfEP3EWvw4Fv3lr7Nz1kew","type":"ADD_ALIAS"},"ledgerTimestamp":1626654287038,"uuid":"vmdcwojRR8IpBPzLAZcPAQ","version":"1"}
{"action":{"identity":{"address":"N\u0000sourcecred\u0000core\u0000IDENTITY\u0000SX0KxUqT4wFN7TGPijKosQ\u0000","aliases":[],"id":"SX0KxUqT4wFN7TGPijKosQ","name":"jamesrt","subtype":"USER"},"type":"CREATE_IDENTITY"},"ledgerTimestamp":1626654287038,"uuid":"TmQRG1ypi3smMw3jw8E1zA","version":"1"}
{"action":{"alias":{"address":"N\u0000sourcecred\u0000discord\u0000MEMBER\u0000user\u0000598904638409801739\u0000","description":"discord/jamesrt#0629"},"identityId":"SX0KxUqT4wFN7TGPijKosQ","type":"ADD_ALIAS"},"ledgerTimestamp":1626654287038,"uuid":"JOlJ68hg8hmGenQ0tb3L6w","version":"1"}
{"action":{"identity":{"address":"N\u0000sourcecred\u0000core\u0000IDENTITY\u0000vKyUm6OJ3OuE89GikjG79w\u0000","aliases":[],"id":"vKyUm6OJ3OuE89GikjG79w","name":"Bay---zoomermoney","subtype":"USER"},"type":"CREATE_IDENTITY"},"ledgerTimestamp":1626654287038,"uuid":"4NmmCMEgMAgS4llEU0721A","version":"1"}
{"action":{"alias":{"address":"N\u0000sourcecred\u0000discord\u0000MEMBER\u0000user\u0000600551241965109254\u0000","description":"discord/Bay | zoomermoney#8545"},"identityId":"vKyUm6OJ3OuE89GikjG79w","type":"ADD_ALIAS"},"ledgerTimestamp":1626654287038,"uuid":"WVkwiexxvTnZUdKR7wS2rA","version":"1"}
{"action":{"identity":{"address":"N\u0000sourcecred\u0000core\u0000IDENTITY\u0000G62W7KIxhjy2MUoaJAdMiA\u0000","aliases":[],"id":"G62W7KIxhjy2MUoaJAdMiA","name":"gamgee","subtype":"USER"},"type":"CREATE_IDENTITY"},"ledgerTimestamp":1626654287039,"uuid":"WwaGd43LmY1pDwHVBRxOfw","version":"1"}
{"action":{"alias":{"address":"N\u0000sourcecred\u0000discord\u0000MEMBER\u0000user\u0000632230294929408020\u0000","description":"discord/gamgee#1933"},"identityId":"G62W7KIxhjy2MUoaJAdMiA","type":"ADD_ALIAS"},"ledgerTimestamp":1626654287039,"uuid":"6XXixY8RbBM5O48HYOQlgw","version":"1"}
{"action":{"identity":{"address":"N\u0000sourcecred\u0000core\u0000IDENTITY\u0000v1Fvkjgr1OTKcBX22z6s4w\u0000","aliases":[],"id":"v1Fvkjgr1OTKcBX22z6s4w","name":"DeFiTrader","subtype":"USER"},"type":"CREATE_IDENTITY"},"ledgerTimestamp":1626654287039,"uuid":"SYyW0eoYzgpYLtNEQ8bkdA","version":"1"}
{"action":{"alias":{"address":"N\u0000sourcecred\u0000discord\u0000MEMBER\u0000user\u0000676946869217132544\u0000","description":"discord/DeFiTrader#3014"},"identityId":"v1Fvkjgr1OTKcBX22z6s4w","type":"ADD_ALIAS"},"ledgerTimestamp":1626654287039,"uuid":"dj0mAGqBIE9QPqfqPQl4Bg","version":"1"}
{"action":{"identity":{"address":"N\u0000sourcecred\u0000core\u0000IDENTITY\u0000vK7nDm85mUe8Ks3gDs5KNQ\u0000","aliases":[],"id":"vK7nDm85mUe8Ks3gDs5KNQ","name":"Toljona","subtype":"USER"},"type":"CREATE_IDENTITY"},"ledgerTimestamp":1626654287039,"uuid":"AXsXwCnnQ0d9l1Ko1aFWyw","version":"1"}
{"action":{"alias":{"address":"N\u0000sourcecred\u0000discord\u0000MEMBER\u0000user\u0000686614577604984906\u0000","description":"discord/Toljona#6202"},"identityId":"vK7nDm85mUe8Ks3gDs5KNQ","type":"ADD_ALIAS"},"ledgerTimestamp":1626654287039,"uuid":"IM8GbxJTKT86WIlWnMYDtA","version":"1"}
{"action":{"identity":{"address":"N\u0000sourcecred\u0000core\u0000IDENTITY\u0000PuJyrNXgamlRjNdaMpJH8w\u0000","aliases":[],"id":"PuJyrNXgamlRjNdaMpJH8w","name":"Orli-PM","subtype":"BOT"},"type":"CREATE_IDENTITY"},"ledgerTimestamp":1626654287039,"uuid":"EXhRJKe3ugjmfA5hDqw8bw","version":"1"}
{"action":{"alias":{"address":"N\u0000sourcecred\u0000discord\u0000MEMBER\u0000bot\u0000712620191045124126\u0000","description":"discord/Orli PM#5036"},"identityId":"PuJyrNXgamlRjNdaMpJH8w","type":"ADD_ALIAS"},"ledgerTimestamp":1626654287039,"uuid":"v7qer42hzXpS9fzqZZbA4A","version":"1"}
{"action":{"identity":{"address":"N\u0000sourcecred\u0000core\u0000IDENTITY\u0000nKt6ZQ1OH598DyD2QTNFvA\u0000","aliases":[],"id":"nKt6ZQ1OH598DyD2QTNFvA","name":"0xCart","subtype":"USER"},"type":"CREATE_IDENTITY"},"ledgerTimestamp":1626654287039,"uuid":"aReupxxQxlXZ84JF5WpRPQ","version":"1"}
{"action":{"alias":{"address":"N\u0000sourcecred\u0000discord\u0000MEMBER\u0000user\u0000721781903979708506\u0000","description":"discord/0xCart#4039"},"identityId":"nKt6ZQ1OH598DyD2QTNFvA","type":"ADD_ALIAS"},"ledgerTimestamp":1626654287039,"uuid":"BudEbmiZI4SL4530zpDSYg","version":"1"}
{"action":{"identity":{"address":"N\u0000sourcecred\u0000core\u0000IDENTITY\u0000n0dYxgBVYea22JNfyGF6CQ\u0000","aliases":[],"id":"n0dYxgBVYea22JNfyGF6CQ","name":"Mariodigital","subtype":"USER"},"type":"CREATE_IDENTITY"},"ledgerTimestamp":1626654287040,"uuid":"Vquk7qODvGcnXtmr7rMnTw","version":"1"}
{"action":{"alias":{"address":"N\u0000sourcecred\u0000discord\u0000MEMBER\u0000user\u0000731804595226935456\u0000","description":"discord/Mariodigital#9440"},"identityId":"n0dYxgBVYea22JNfyGF6CQ","type":"ADD_ALIAS"},"ledgerTimestamp":1626654287040,"uuid":"jyFowj4QLDZIoFkI9n2Wgw","version":"1"}
{"action":{"identity":{"address":"N\u0000sourcecred\u0000core\u0000IDENTITY\u0000j3wqUli3y2b7w0MyYXdX6Q\u0000","aliases":[],"id":"j3wqUli3y2b7w0MyYXdX6Q","name":"Gibbo","subtype":"USER"},"type":"CREATE_IDENTITY"},"ledgerTimestamp":1626654287040,"uuid":"QRUo1b7JjsXWAqaGtGUa6A","version":"1"}
{"action":{"alias":{"address":"N\u0000sourcecred\u0000discord\u0000MEMBER\u0000user\u0000740513815665311836\u0000","description":"discord/Gibbo#0183"},"identityId":"j3wqUli3y2b7w0MyYXdX6Q","type":"ADD_ALIAS"},"ledgerTimestamp":1626654287040,"uuid":"dx9mf5r851ZfJiO64PSNcQ","version":"1"}
{"action":{"identity":{"address":"N\u0000sourcecred\u0000core\u0000IDENTITY\u0000dD4ZwWA2iJbPEoiAMVDpZQ\u0000","aliases":[],"id":"dD4ZwWA2iJbPEoiAMVDpZQ","name":"SP","subtype":"USER"},"type":"CREATE_IDENTITY"},"ledgerTimestamp":1626654287040,"uuid":"zaORwgOGmsa3uBAOju7gWA","version":"1"}
{"action":{"alias":{"address":"N\u0000sourcecred\u0000discord\u0000MEMBER\u0000user\u0000749838412911083541\u0000","description":"discord/SP#6842"},"identityId":"dD4ZwWA2iJbPEoiAMVDpZQ","type":"ADD_ALIAS"},"ledgerTimestamp":1626654287040,"uuid":"Yp7zHofdR1D0NmF2brtV2Q","version":"1"}
{"action":{"identity":{"address":"N\u0000sourcecred\u0000core\u0000IDENTITY\u0000xklXoZSamWp0HyKxAozruA\u0000","aliases":[],"id":"xklXoZSamWp0HyKxAozruA","name":"LS00","subtype":"USER"},"type":"CREATE_IDENTITY"},"ledgerTimestamp":1626654287040,"uuid":"L7xNhbvvunm2ekek3rEGZg","version":"1"}
{"action":{"alias":{"address":"N\u0000sourcecred\u0000discord\u0000MEMBER\u0000user\u0000754473088111869994\u0000","description":"discord/LS00#2306"},"identityId":"xklXoZSamWp0HyKxAozruA","type":"ADD_ALIAS"},"ledgerTimestamp":1626654287040,"uuid":"qVKxg84LpXzG8Z8dC0iZEQ","version":"1"}
{"action":{"identity":{"address":"N\u0000sourcecred\u0000core\u0000IDENTITY\u0000nEjvHvsjqcgqWTzM7ACb3g\u0000","aliases":[],"id":"nEjvHvsjqcgqWTzM7ACb3g","name":"shpa97","subtype":"USER"},"type":"CREATE_IDENTITY"},"ledgerTimestamp":1626654287041,"uuid":"IYNxbDkoOv7ojaDs5lhQ1w","version":"1"}
{"action":{"alias":{"address":"N\u0000sourcecred\u0000discord\u0000MEMBER\u0000user\u0000754789399677370399\u0000","description":"discord/shpa97#8457"},"identityId":"nEjvHvsjqcgqWTzM7ACb3g","type":"ADD_ALIAS"},"ledgerTimestamp":1626654287041,"uuid":"yLloYm6B8c58O8dZ4QLKXA","version":"1"}
{"action":{"identity":{"address":"N\u0000sourcecred\u0000core\u0000IDENTITY\u0000nug9EsGg07ClVMyp20ywPw\u0000","aliases":[],"id":"nug9EsGg07ClVMyp20ywPw","name":"adamalamode","subtype":"USER"},"type":"CREATE_IDENTITY"},"ledgerTimestamp":1626654287041,"uuid":"OX9ircxZzij5pWh70uEtdw","version":"1"}
{"action":{"alias":{"address":"N\u0000sourcecred\u0000discord\u0000MEMBER\u0000user\u0000766693440368410695\u0000","description":"discord/adamalamode#6893"},"identityId":"nug9EsGg07ClVMyp20ywPw","type":"ADD_ALIAS"},"ledgerTimestamp":1626654287041,"uuid":"kEp2viWb8zZ5rYlPEvA6tA","version":"1"}
{"action":{"identity":{"address":"N\u0000sourcecred\u0000core\u0000IDENTITY\u0000dPgoPQ0DhDlAHRt38vguKg\u0000","aliases":[],"id":"dPgoPQ0DhDlAHRt38vguKg","name":"thewolfofrapa","subtype":"USER"},"type":"CREATE_IDENTITY"},"ledgerTimestamp":1626654287041,"uuid":"i2FxS0aCkBK723IJF83s2g","version":"1"}
{"action":{"alias":{"address":"N\u0000sourcecred\u0000discord\u0000MEMBER\u0000user\u0000789883455252725772\u0000","description":"discord/thewolfofrapa#0716"},"identityId":"dPgoPQ0DhDlAHRt38vguKg","type":"ADD_ALIAS"},"ledgerTimestamp":1626654287041,"uuid":"C3i8gEt7G52pNPa0iORUwQ","version":"1"}
{"action":{"identity":{"address":"N\u0000sourcecred\u0000core\u0000IDENTITY\u00006xyExx8RjSkAMXfLh8qT9A\u0000","aliases":[],"id":"6xyExx8RjSkAMXfLh8qT9A","name":"Max0x","subtype":"USER"},"type":"CREATE_IDENTITY"},"ledgerTimestamp":1626654287041,"uuid":"7MQwwTEZp61kbXesVKa6dg","version":"1"}
{"action":{"alias":{"address":"N\u0000sourcecred\u0000discord\u0000MEMBER\u0000user\u0000800213182115217438\u0000","description":"discord/Max0x#5092"},"identityId":"6xyExx8RjSkAMXfLh8qT9A","type":"ADD_ALIAS"},"ledgerTimestamp":1626654287041,"uuid":"KNAw4uJKLKCozvzJh2xNFg","version":"1"}
{"action":{"identity":{"address":"N\u0000sourcecred\u0000core\u0000IDENTITY\u0000fMuB1qX6O4B11CRydFQ2qA\u0000","aliases":[],"id":"fMuB1qX6O4B11CRydFQ2qA","name":"CPTNskeletor","subtype":"USER"},"type":"CREATE_IDENTITY"},"ledgerTimestamp":1626654287042,"uuid":"BBD2p5JDFenp5jqaRXAqdw","version":"1"}
{"action":{"alias":{"address":"N\u0000sourcecred\u0000discord\u0000MEMBER\u0000user\u0000803455455912525834\u0000","description":"discord/CPTNskeletor#0379"},"identityId":"fMuB1qX6O4B11CRydFQ2qA","type":"ADD_ALIAS"},"ledgerTimestamp":1626654287042,"uuid":"rev93M5MevrI9aSrGyPm5w","version":"1"}
{"action":{"identity":{"address":"N\u0000sourcecred\u0000core\u0000IDENTITY\u0000gt2LqH8c9uJD9buvz9eQtQ\u0000","aliases":[],"id":"gt2LqH8c9uJD9buvz9eQtQ","name":"christianocripto","subtype":"USER"},"type":"CREATE_IDENTITY"},"ledgerTimestamp":1626654287042,"uuid":"9asypw1bU4KFvIO3v1RXvA","version":"1"}
{"action":{"alias":{"address":"N\u0000sourcecred\u0000discord\u0000MEMBER\u0000user\u0000810849610347053077\u0000","description":"discord/christianocripto#7194"},"identityId":"gt2LqH8c9uJD9buvz9eQtQ","type":"ADD_ALIAS"},"ledgerTimestamp":1626654287042,"uuid":"dOmd80x8yTRpgTxDOBAq2g","version":"1"}
{"action":{"identity":{"address":"N\u0000sourcecred\u0000core\u0000IDENTITY\u0000Vp86VcbnQrA3CrzMfVNqbg\u0000","aliases":[],"id":"Vp86VcbnQrA3CrzMfVNqbg","name":"zaza","subtype":"USER"},"type":"CREATE_IDENTITY"},"ledgerTimestamp":1626654287042,"uuid":"fowwkG6gG9j2ee1HQcAOEw","version":"1"}
{"action":{"alias":{"address":"N\u0000sourcecred\u0000discord\u0000MEMBER\u0000user\u0000811084579367682089\u0000","description":"discord/zaza#6743"},"identityId":"Vp86VcbnQrA3CrzMfVNqbg","type":"ADD_ALIAS"},"ledgerTimestamp":1626654287042,"uuid":"yXk1SdTlD6vcwy0XoqckLw","version":"1"}
{"action":{"identity":{"address":"N\u0000sourcecred\u0000core\u0000IDENTITY\u0000BbZKbIzdb6YlpVuL1JvNgw\u0000","aliases":[],"id":"BbZKbIzdb6YlpVuL1JvNgw","name":"Markio","subtype":"USER"},"type":"CREATE_IDENTITY"},"ledgerTimestamp":1626654287042,"uuid":"SKnmKxjNtnfmlterIx8TxQ","version":"1"}
{"action":{"alias":{"address":"N\u0000sourcecred\u0000discord\u0000MEMBER\u0000user\u0000814184476891414558\u0000","description":"discord/Markio#1150"},"identityId":"BbZKbIzdb6YlpVuL1JvNgw","type":"ADD_ALIAS"},"ledgerTimestamp":1626654287042,"uuid":"a59l8puzxwb6sB6t0LoF7g","version":"1"}
{"action":{"identity":{"address":"N\u0000sourcecred\u0000core\u0000IDENTITY\u0000QakAw7DamEmaDXRehwxspg\u0000","aliases":[],"id":"QakAw7DamEmaDXRehwxspg","name":"NotMissing","subtype":"USER"},"type":"CREATE_IDENTITY"},"ledgerTimestamp":1626654287042,"uuid":"fkyxPEIaKfeDgK0vvMQMDg","version":"1"}
{"action":{"alias":{"address":"N\u0000sourcecred\u0000discord\u0000MEMBER\u0000user\u0000815254053586993183\u0000","description":"discord/NotMissing#4805"},"identityId":"QakAw7DamEmaDXRehwxspg","type":"ADD_ALIAS"},"ledgerTimestamp":1626654287042,"uuid":"FlrGpYh64S8JPsGiRh38jw","version":"1"}
{"action":{"identity":{"address":"N\u0000sourcecred\u0000core\u0000IDENTITY\u0000QqJbBZX2JdVTqLrzg2nGYQ\u0000","aliases":[],"id":"QqJbBZX2JdVTqLrzg2nGYQ","name":"av1dan","subtype":"USER"},"type":"CREATE_IDENTITY"},"ledgerTimestamp":1626654287043,"uuid":"hZPFZnwoJ7kJcog7UEFvkA","version":"1"}
{"action":{"alias":{"address":"N\u0000sourcecred\u0000discord\u0000MEMBER\u0000user\u0000824477079226679306\u0000","description":"discord/av1dan#8548"},"identityId":"QqJbBZX2JdVTqLrzg2nGYQ","type":"ADD_ALIAS"},"ledgerTimestamp":1626654287043,"uuid":"oh9BN5flPbIy0yB5n98GaA","version":"1"}
{"action":{"identity":{"address":"N\u0000sourcecred\u0000core\u0000IDENTITY\u0000au6hp4oxJ3xN1SDmNLZxWw\u0000","aliases":[],"id":"au6hp4oxJ3xN1SDmNLZxWw","name":"CryptoGucci","subtype":"USER"},"type":"CREATE_IDENTITY"},"ledgerTimestamp":1626654287043,"uuid":"S7OtwVaU7DGgaKlYlipb9g","version":"1"}
{"action":{"alias":{"address":"N\u0000sourcecred\u0000discord\u0000MEMBER\u0000user\u0000859625604454547486\u0000","description":"discord/CryptoGucci#3381"},"identityId":"au6hp4oxJ3xN1SDmNLZxWw","type":"ADD_ALIAS"},"ledgerTimestamp":1626654287043,"uuid":"jGRPfrf13GIljv1mVpv5Cg","version":"1"}
{"action":{"identity":{"address":"N\u0000sourcecred\u0000core\u0000IDENTITY\u0000NjqwAt7gRuBj58c5ngVWtA\u0000","aliases":[],"id":"NjqwAt7gRuBj58c5ngVWtA","name":"SourceCred","subtype":"PROJECT"},"type":"CREATE_IDENTITY"},"ledgerTimestamp":1626654287284,"uuid":"VqBI6S45HQHkKywErR1i8Q","version":"1"}
{"action":{"identityId":"NjqwAt7gRuBj58c5ngVWtA","type":"TOGGLE_ACTIVATION"},"ledgerTimestamp":1626654287284,"uuid":"0hzhKQlTdxYmag5FZnHEZA","version":"1"}
